Workbook
Name Causas: Datos!$O$24:$O$38
Name Consolidad_Anual_ingresos: 'CONSOLIDADO REGIONAL (ingresos)'!$A$6:$AL$992
Name Consolidad_Anual_Viveros: 'CONSOLIDADO REGIONAL (ingresos)'!$A$6:$AL$992
Name Consolidad_Anual_Viveros: 'CONSOLIDADO REGIONAL'!$A$6:$AL$2000
Name NOMBRE_DE_VIVERO__CENTRO_DE_ACONDICIONAMIENTO_O_ACOPIO: [1]Hoja1!$E$2:$E$38
Name Resumen_anual2020: 'Reporte Diciembre 2026'!#REF!
Name Resumen_anual2020: 'Reporte Diciembre 2026'!#REF!

Sheet Formato explicativo
C1: FORMATO CONTROL INVENTARIO DE PLANTAS 2026
D4: INVENTARIO INICIAL | K4: MARZO | W4: JUNIO | AI4: SEPTIEMBRE | AU4: DICIEMBRE
C5: Ítems | D5: Antecedentes del vivero | E5: Antecedentes de la especie | F5: Total Plantas Enero | G5: Valores | J5: Ítems | K5: Antecedentes del vivero | L5: Antecedentes de la especie | M5: Total Plantas enero | N5: N° Plantas Ingresadas | O5: Entregas | P5: Movimientos internos | Q5: Traslados | R5: Bajas | S5: Total Plantas Marzo | T5: Valores | V5: Ítems | W5: Antecedentes del vivero | X5: Antecedentes de la especie | Y5: Total Plantas Marzo | Z5: N° Plantas Ingresadas | AA5: Entregas | AB5: Movimientos internos | AC5: Traslados | AD5: Bajas | AE5: Total Plantas Junio | AF5: Valores | AH5: Ítems | AI5: Antecedentes del vivero | AJ5: Antecedentes de la especie | AK5: Total Plantas Junio | AL5: N° Plantas Ingresadas | AM5: Entregas | AN5: Movimientos internos | AO5: Traslados | AP5: Bajas | AQ5: Total Plantas Septiembre | AR5: Valores | AT5: Ítems | AU5: Antecedentes del vivero | AV5: Antecedentes de la especie | AW5: Total Plantas Septiembre | AX5: N° Plantas Ingresadas | AY5: Entregas | AZ5: Movimientos internos | BA5: Traslados | BB5: Bajas | BC5: Total Plantas Diciembre | BD5: Valores | BF5: INFORME DE INGRESOS PLANTAS A INVENTARIO | BJ5: INFORME DE SALIDA,N° PLANTAS SEGÚN DESTINO, | BR5: INFORME DE INGRESOS PLANTAS A INVENTARIO | CA5: INFORME RESUMEN STOCK
B6: Fila 6 | C6: Inventario | D6: INVENTARIO 1 (Modificar) | F6: E | G6: $ | I6: Fila 6 | J6: Inventario | K6: INVENTARIO 1 (no modificar) | M6: E | N6: 0 | O6: X | P6: X | Q6: X | R6: X | S6: M | T6: $ | U6: Fila 6 | V6: Inventario | W6: INVENTARIO 1 (no modificar) | Y6: M | Z6: 0 | AA6: X | AB6: X | AC6: X | AD6: X | AE6: J | AF6: $ | AG6: Fila 6 | AH6: Inventario | AI6: INVENTARIO 1 (no modificar) | AK6: J | AL6: 0 | AM6: X | AN6: X | AO6: X | AP6: X | AQ6: S | AR6: $ | AS6: Fila 6 | AT6: Inventario | AU6: INVENTARIO 1 (no modificar) | AW6: S | AX6: 0 | AY6: X | AZ6: X | BA6: X | BB6: X | BC6: D | BD6: $ | BF6: MES | BG6: FUENTE DE ABASTECIMIENTO | BH6: N° PLANTAS | BJ6: VIVEROS | BK6: MES | BL6: DIFUSION | BM6: PROGRAMAS | BN6: TRASLADOS | BR6: VIVERO | BS6: FECHA | BT6: ESPECIES | BU6: ORIGEN | BV6: RANGO DE ALTURA | BW6: CONTENEDOR | BX6: VALOR | BY6: N° PLANTAS DE BAJA | CA6: MES | CB6: FUENTE DE ABASTECIMIENTO | CC6: N° PLANTAS
B7: Fila 7 | C7: Inventario | F7: E | G7: $ | I7: Fila 7 | J7: Inventario | M7: E | N7: 0 | O7: X | P7: X | Q7: X | R7: X | S7: M | T7: $ | U7: Fila 7 | V7: Inventario | Y7: M | Z7: 0 | AA7: X | AB7: X | AC7: X | AD7: X | AE7: J | AF7: $ | AG7: Fila 7 | AH7: Inventario | AK7: J | AL7: 0 | AM7: X | AN7: X | AO7: X | AP7: X | AQ7: S | AR7: $ | AS7: Fila 7 | AT7: Inventario | AW7: S | AX7: 0 | AY7: X | AZ7: X | BA7: X | BB7: X | BC7: D | BD7: $
B8: Fila 8 | C8: Inventario | F8: E | G8: $ | I8: Fila 8 | J8: Inventario | M8: E | N8: 0 | O8: X | P8: X | Q8: X | R8: X | S8: M | T8: $ | U8: Fila 8 | V8: Inventario | Y8: M | Z8: 0 | AA8: X | AB8: X | AC8: X | AD8: X | AE8: J | AF8: $ | AG8: Fila 8 | AH8: Inventario | AK8: J | AL8: 0 | AM8: X | AN8: X | AO8: X | AP8: X | AQ8: S | AR8: $ | AS8: Fila 8 | AT8: Inventario | AW8: S | AX8: 0 | AY8: X | AZ8: X | BA8: X | BB8: X | BC8: D | BD8: $ | BF8: MARZO | BG8: PRODUCCIÓN PROPIA | BH8: X | BJ8: XXX | BK8: MARZO | BL8: X | BM8: X | BN8: X | BR8: X | BS8: XX/XX/XXX | BT8: X | BU8: X | BV8: X | BW8: X | BX8: X | BY8: X | CA8: MARZO | CB8: PRODUCCIÓN PROPIA
B9: Fila 9 | C9: Inventario | F9: E | G9: $ | I9: Fila 9 | J9: Inventario | M9: E | N9: 0 | O9: X | P9: X | Q9: X | R9: X | S9: M | T9: $ | U9: Fila 9 | V9: Inventario | Y9: M | Z9: 0 | AA9: X | AB9: X | AC9: X | AD9: X | AE9: J | AF9: $ | AG9: Fila 9 | AH9: Inventario | AK9: J | AL9: 0 | AM9: X | AN9: X | AO9: X | AP9: X | AQ9: S | AR9: $ | AS9: Fila 9 | AT9: Inventario | AW9: S | AX9: 0 | AY9: X | AZ9: X | BA9: X | BB9: X | BC9: D | BD9: $ | BR9: X
B10: Fila 10 | C10: Inventario | F10: E | G10: $ | I10: Fila 10 | J10: Inventario | M10: E | N10: 0 | O10: X | P10: X | Q10: X | R10: X | S10: M | T10: $ | U10: Fila 10 | V10: Inventario | Y10: M | Z10: 0 | AA10: X | AB10: X | AC10: X | AD10: X | AE10: J | AF10: $ | AG10: Fila 10 | AH10: Inventario | AK10: J | AL10: 0 | AM10: X | AN10: X | AO10: X | AP10: X | AQ10: S | AR10: $ | AS10: Fila 10 | AT10: Inventario | AW10: S | AX10: 0 | AY10: X | AZ10: X | BA10: X | BB10: X | BC10: D | BD10: $ | BF10: JUNIO | BG10: COMPRAS | BH10: X | BJ10: XXX | BK10: JUNIO | BL10: X | BM10: X | BN10: X | BR10: X | BS10: XX/XX/XXX | BT10: X | BU10: X | BV10: X | BW10: X | BX10: X | BY10: X | CA10: JUNIO | CB10: COMPRAS
B11: Fila 11 | C11: Inventario | F11: E | G11: $ | I11: Fila 11 | J11: Inventario | M11: E | N11: 0 | O11: X | P11: X | Q11: X | R11: X | S11: M | T11: $ | U11: Fila 11 | V11: Inventario | Y11: M | Z11: 0 | AA11: X | AB11: X | AC11: X | AD11: X | AE11: J | AF11: $ | AG11: Fila 11 | AH11: Inventario | AK11: J | AL11: 0 | AM11: X | AN11: X | AO11: X | AP11: X | AQ11: S | AR11: $ | AS11: Fila 11 | AT11: Inventario | AW11: S | AX11: 0 | AY11: X | AZ11: X | BA11: X | BB11: X | BC11: D | BD11: $ | BR11: X
B12: Fila 12 | C12: Inventario | F12: E | G12: $ | I12: Fila 12 | J12: Inventario | M12: E | N12: 0 | O12: X | P12: X | Q12: X | R12: X | S12: M | T12: $ | U12: Fila 12 | V12: Inventario | Y12: M | Z12: 0 | AA12: X | AB12: X | AC12: X | AD12: X | AE12: J | AF12: $ | AG12: Fila 12 | AH12: Inventario | AK12: J | AL12: 0 | AM12: X | AN12: X | AO12: X | AP12: X | AQ12: S | AR12: $ | AS12: Fila 12 | AT12: Inventario | AW12: S | AX12: 0 | AY12: X | AZ12: X | BA12: X | BB12: X | BC12: D | BD12: $ | BF12: SEPTIEMBRE | BG12: DONACIONES | BH12: X | BJ12: XXX | BK12: SEPTIEMBRE | BL12: X | BM12: X | BN12: X | BR12: X | BS12: XX/XX/XXX | BT12: X | BU12: X | BV12: X | BW12: X | BX12: X | BY12: X | CA12: SEPTIEMBRE | CB12: DONACIONES
C13: Total | F13: E | G13: $ | I13: Fila 13 | J13: Ingreso (M) | K13: MMM | L13: MM | M13: 0 | N13: X | O13: X | P13: X | Q13: X | R13: X | S13: M | T13: $ | U13: Fila 13 | V13: Ingreso (M) | W13: MMM | X13: MM | Y13: M | Z13: 0 | AA13: X | AB13: X | AC13: X | AD13: X | AE13: J | AF13: $ | AG13: Fila 13 | AH13: Ingreso (M) | AI13: MMM | AJ13: MM | AK13: J | AL13: 0 | AM13: X | AN13: X | AO13: X | AP13: X | AQ13: S | AR13: $ | AS13: Fila 13 | AT13: Ingreso (M) | AU13: MMM | AV13: MM | AW13: S | AX13: 0 | AY13: X | AZ13: X | BA13: X | BB13: X | BC13: D | BD13: $ | BR13: X
I14: Fila 14 | J14: Ingreso (M) | K14: MMM | L14: MM | M14: 0 | N14: X | O14: X | P14: X | Q14: X | R14: X | S14: M | T14: $ | U14: Fila 14 | V14: Ingreso (M) | W14: MMM | X14: MM | Y14: M | Z14: 0 | AA14: X | AB14: X | AC14: X | AD14: X | AE14: J | AF14: $ | AG14: Fila 14 | AH14: Ingreso (M) | AI14: MMM | AJ14: MM | AK14: J | AL14: 0 | AM14: X | AN14: X | AO14: X | AP14: X | AQ14: S | AR14: $ | AS14: Fila 14 | AT14: Ingreso (M) | AU14: MMM | AV14: MM | AW14: S | AX14: 0 | AY14: X | AZ14: X | BA14: X | BB14: X | BC14: D | BD14: $ | BF14: DICIEMBRE | BJ14: XX | BK14: DICIEMBRE | BL14: X | BM14: X | BN14: X | BR14: X | BS14: XX/XX/XXX | BT14: X | BU14: X | BV14: X | BW14: X | BX14: X | BY14: X | CA14: DICIEMBRE
D15: HOJA 2 | I15: Fila 15 | J15: Ingreso (M) | K15: MMM | L15: MM | M15: 0 | N15: X | O15: X | P15: X | Q15: X | R15: X | S15: M | T15: $ | U15: Fila 15 | V15: Ingreso (M) | W15: MMM | X15: MM | Y15: M | Z15: 0 | AA15: X | AB15: X | AC15: X | AD15: X | AE15: J | AF15: $ | AG15: Fila 15 | AH15: Ingreso (M) | AI15: MMM | AJ15: MM | AK15: J | AL15: 0 | AM15: X | AN15: X | AO15: X | AP15: X | AQ15: S | AR15: $ | AS15: Fila 15 | AT15: Ingreso (M) | AU15: MMM | AV15: MM | AW15: S | AX15: 0 | AY15: X | AZ15: X | BA15: X | BB15: X | BC15: D | BD15: $
I16: Fila 16 | J16: Ingresos | M16: 0 | U16: Fila 16 | V16: Ingresos (J) | W16: JJJ | X16: JJJ | Y16: 0 | Z16: X | AA16: X | AB16: X | AC16: X | AD16: X | AE16: J | AF16: $ | AG16: Fila 16 | AH16: Ingresos (J) | AI16: JJJ | AJ16: JJJ | AK16: J | AL16: 0 | AM16: X | AN16: X | AO16: X | AP16: X | AQ16: S | AR16: $ | AS16: Fila 16 | AT16: Ingresos (J) | AU16: JJJ | AV16: JJJ | AW16: S | AX16: 0 | AY16: X | AZ16: X | BA16: X | BB16: X | BC16: D | BD16: $ | BG16: TOTAL | BH16: XX | BK16: TOTAL | BL16: XX | BM16: XX | BN16: XX | BT16: TOTAL | BU16: XX | BV16: XX | BW16: XX | BY16: XX
I17: Fila 17 | J17: Ingresos | M17: 0 | U17: Fila 17 | AE17: 0 | AF17: $ | AG17: Fila 17 | AH17: Ingresos (S) | AI17: SSS | AJ17: SSS | AK17: 0 | AL17: X | AM17: X | AN17: X | AO17: X | AP17: X | AQ17: S | AR17: $ | AS17: Fila 17 | AT17: Ingresos (S) | AU17: SSS | AV17: SSS | AW17: S | AX17: 0 | AY17: X | AZ17: X | BA17: X | BB17: X | BC17: D | BD17: $
I18: Fila 18 | J18: Ingresos | M18: 0 | U18: Fila 18 | AE18: 0 | AF18: $ | AG18: Fila 18 | AK18: 0 | AQ18: 0 | AR18: $ | AS18: Fila 18 | AT18: Ingresos (D) | AU18: DDD | AV18: DDD | AW18: 0 | AX18: X | AY18: X | AZ18: X | BA18: X | BB18: X | BC18: D | BD18: $
I19: Fila 19 | J19: Ingresos | M19: 0 | U19: Fila 19 | AE19: 0 | AF19: $ | AG19: Fila 19 | AK19: 0 | AQ19: 0 | AR19: $ | AS19: Fila 19 | AW19: 0 | BC19: 0 | BD19: $
J20: Total | M20: E | N20: X | O20: X | P20: X | Q20: X | R20: X | S20: M | T20: $ | V20: Total | Y20: M | Z20: X | AA20: X | AB20: X | AC20: X | AD20: X | AE20: J | AF20: $ | AH20: Total | AK20: J | AL20: X | AM20: X | AN20: X | AO20: X | AP20: X | AQ20: S | AR20: $ | AT20: Total | AW20: S | AX20: X | AY20: X | AZ20: X | BA20: X | BB20: X | BC20: D | BD20: $
M22: HOJA 3 | Y22: HOJA 4 | AK22: HOJA 5 | AW22: HOJA 6
C24: Observaciones
C25: 1 | D25: En la hoja Inventario Inicial: sólo registrar la información del inventario de diciembre 2025, que debe ser el mismo.
C26: 2 | D26: En la hoja Inventario Inicial, AL LLENARLA , los valores se copian en forma automática en todos los reportes de los trimestres posteriores.
C27: 3 | D27: La columna "Total" de la hoja Inventario Inicial, se repite en la hoja Reporte Marzo 2026. A esta columna se le descuentan las salidas, dando como resultado el "Total de Plantas Marzo".
C28: 4 | D28: La columna "Total Plantas Marzo" se repite en hoja Reporte Junio 2026 y lo mismo sucede con los otros reportes.
C29: 5 | D29: Es obligación llenar todas las filas (INGRESOS DEL AÑO) de forma ordenada en la hoja Inventario Inicial, pues como se explicó, estas se repiten en las otras. hojas.
C30: 6 | D30: No se pueden modificar la zona de "Inventario Marzo, Junio, Septiembre o Diciembre".
C31: 7 | D31: La zona con "X" corresponde al lugar donde se registran las salidas (entregas, traslados y bajas) (Formato explicativo).
C32: 8 | D32: Se pueden realizar nuevos ingresos sólo a partir de la hoja Inventario Marzo 2026.
C33: 9 | D33: El número de plantas ingresadas, solo registrarlas en la intersección columna X fila de ingresos (X).
C34: 10 | D34: El orden para registrar los nuevos ingresos es: primero todos los ingresos de marzo, después los ingreso de junio hasta diciembre, ya que no se puede ingresar valores de marzo, teniendo completadas las mismas filas de junio, igual en los otros reportes (ver formato explicativo).
C36: 11 | D36: Los ingresos deben hacerse en las fechas correspondiente y no después (Si es trimestre Reporte Marzo, no puede ser en Reporte de Junio, hay que seguir ese orden).
C37: 12 | D37: Para insertar una fila nueva, posicionarse en la barra numérica al lado de la columna, apretar el botón derecho del mouse, después insertar bajo esta como "insertar celdas copiadas", tantas veces como sea necesario.(Hacerlo en Marzo para arrastrar los totales).
... C43: 16 | D43: NO BORRAR NINGUNA FILA, SOLO OCULTARLAS
C46: Para actualizar las planillas y tablas dinámicas, después de hacer modificaciones, ir al menu parte superior, hacer clic en Datos y elegir "actualizar todo."

Sheet INVENTARIO INICIAL
B1: Control Inventario de Plantas SIGI GBCC 8 | 2026
B2: Viveros, centros de acopio y acondicionamiento CONAF
B3: Inventario Diciembre 2025
A5: ANTECEDENTES DEL VIVERO | H5: ANTECEDENTES DE LA ESPECIE | T5: VALORIZACIÓN | V5: Observaciones | X5: Código de planta para Guía de Despacho
A6: Items | B6: Unidad Productiva | C6: Unidad Administrativa | D6: Provincia | E6: Comuna | F6: Nombre del Encargado | G6: Teléfono de Contacto | H6: Nombre Científico | I6: Nombre Común | J6: Origen | K6: Fuente de Abastecimiento | L6: Destino de la Planta | M6: Tipo de Reproducción | N6: Tipo de Contenedor | O6: Fecha Ingreso a Inventario (Día-Mes-Año) | P6: Tiempo de Viverización (años) | Q6: Rango de Altura | R6: Sectores del Vivero | S6: N° Total Plantas Control Inventario Diciembre 2025 | T6: Valor Neto ($) por Planta | U6: Valor Total ($) por Lote
A7: Inventario | C7: =IF(B7=0,"",VLOOKUP(B7,Datos!$H$2:$K$39,2,FALSE)) | D7: =IF(B7=0,"",VLOOKUP(B7,Datos!$H$2:$K$39,3,FALSE)) | E7: =IF(B7=0,"",VLOOKUP(B7,Datos!$H$2:$K$39,4,FALSE)) | I7: =IF(H7=0,"",VLOOKUP(H7,Datos!$B$2:$D$891,2,FALSE)) | J7: =IF(H7=0,"",VLOOKUP(H7,Datos!$B$2:$D$891,3,FALSE)) | U7: =S7*T7 -> 0
A8: Inventario | C8: =IF(B8=0,"",VLOOKUP(B8,Datos!$H$2:$K$39,2,FALSE)) | D8: =IF(B8=0,"",VLOOKUP(B8,Datos!$H$2:$K$39,3,FALSE)) | E8: =IF(B8=0,"",VLOOKUP(B8,Datos!$H$2:$K$39,4,FALSE)) | I8: =IF(H8=0,"",VLOOKUP(H8,Datos!$B$2:$D$891,2,FALSE)) | J8: =IF(H8=0,"",VLOOKUP(H8,Datos!$B$2:$D$891,3,FALSE)) | U8: =S8*T8 -> 0
A9: Inventario | C9: =IF(B9=0,"",VLOOKUP(B9,Datos!$H$2:$K$39,2,FALSE)) | D9: =IF(B9=0,"",VLOOKUP(B9,Datos!$H$2:$K$39,3,FALSE)) | E9: =IF(B9=0,"",VLOOKUP(B9,Datos!$H$2:$K$39,4,FALSE)) | I9: =IF(H9=0,"",VLOOKUP(H9,Datos!$B$2:$D$891,2,FALSE)) | J9: =IF(H9=0,"",VLOOKUP(H9,Datos!$B$2:$D$891,3,FALSE)) | U9: =S9*T9 -> 0
A10: Inventario | C10: =IF(B10=0,"",VLOOKUP(B10,Datos!$H$2:$K$39,2,FALSE)) | D10: =IF(B10=0,"",VLOOKUP(B10,Datos!$H$2:$K$39,3,FALSE)) | E10: =IF(B10=0,"",VLOOKUP(B10,Datos!$H$2:$K$39,4,FALSE)) | I10: =IF(H10=0,"",VLOOKUP(H10,Datos!$B$2:$D$891,2,FALSE)) | J10: =IF(H10=0,"",VLOOKUP(H10,Datos!$B$2:$D$891,3,FALSE)) | U10: =S10*T10 -> 0
A11: Inventario | C11: =IF(B11=0,"",VLOOKUP(B11,Datos!$H$2:$K$39,2,FALSE)) | D11: =IF(B11=0,"",VLOOKUP(B11,Datos!$H$2:$K$39,3,FALSE)) | E11: =IF(B11=0,"",VLOOKUP(B11,Datos!$H$2:$K$39,4,FALSE)) | I11: =IF(H11=0,"",VLOOKUP(H11,Datos!$B$2:$D$891,2,FALSE)) | J11: =IF(H11=0,"",VLOOKUP(H11,Datos!$B$2:$D$891,3,FALSE)) | U11: =S11*T11 -> 0
A12: Inventario | C12: =IF(B12=0,"",VLOOKUP(B12,Datos!$H$2:$K$39,2,FALSE)) | D12: =IF(B12=0,"",VLOOKUP(B12,Datos!$H$2:$K$39,3,FALSE)) | E12: =IF(B12=0,"",VLOOKUP(B12,Datos!$H$2:$K$39,4,FALSE)) | I12: =IF(H12=0,"",VLOOKUP(H12,Datos!$B$2:$D$891,2,FALSE)) | J12: =IF(H12=0,"",VLOOKUP(H12,Datos!$B$2:$D$891,3,FALSE)) | U12: =S12*T12 -> 0
A13: Inventario | C13: =IF(B13=0,"",VLOOKUP(B13,Datos!$H$2:$K$39,2,FALSE)) | D13: =IF(B13=0,"",VLOOKUP(B13,Datos!$H$2:$K$39,3,FALSE)) | E13: =IF(B13=0,"",VLOOKUP(B13,Datos!$H$2:$K$39,4,FALSE)) | I13: =IF(H13=0,"",VLOOKUP(H13,Datos!$B$2:$D$891,2,FALSE)) | J13: =IF(H13=0,"",VLOOKUP(H13,Datos!$B$2:$D$891,3,FALSE)) | U13: =S13*T13 -> 0
A14: Inventario | C14: =IF(B14=0,"",VLOOKUP(B14,Datos!$H$2:$K$39,2,FALSE)) | D14: =IF(B14=0,"",VLOOKUP(B14,Datos!$H$2:$K$39,3,FALSE)) | E14: =IF(B14=0,"",VLOOKUP(B14,Datos!$H$2:$K$39,4,FALSE)) | I14: =IF(H14=0,"",VLOOKUP(H14,Datos!$B$2:$D$891,2,FALSE)) | J14: =IF(H14=0,"",VLOOKUP(H14,Datos!$B$2:$D$891,3,FALSE)) | U14: =S14*T14 -> 0
A15: Inventario | C15: =IF(B15=0,"",VLOOKUP(B15,Datos!$H$2:$K$39,2,FALSE)) | D15: =IF(B15=0,"",VLOOKUP(B15,Datos!$H$2:$K$39,3,FALSE)) | E15: =IF(B15=0,"",VLOOKUP(B15,Datos!$H$2:$K$39,4,FALSE)) | I15: =IF(H15=0,"",VLOOKUP(H15,Datos!$B$2:$D$891,2,FALSE)) | J15: =IF(H15=0,"",VLOOKUP(H15,Datos!$B$2:$D$891,3,FALSE)) | U15: =S15*T15 -> 0
A16: Inventario | C16: =IF(B16=0,"",VLOOKUP(B16,Datos!$H$2:$K$39,2,FALSE)) | D16: =IF(B16=0,"",VLOOKUP(B16,Datos!$H$2:$K$39,3,FALSE)) | E16: =IF(B16=0,"",VLOOKUP(B16,Datos!$H$2:$K$39,4,FALSE)) | I16: =IF(H16=0,"",VLOOKUP(H16,Datos!$B$2:$D$891,2,FALSE)) | J16: =IF(H16=0,"",VLOOKUP(H16,Datos!$B$2:$D$891,3,FALSE)) | U16: =S16*T16 -> 0
A17: Inventario | C17: =IF(B17=0,"",VLOOKUP(B17,Datos!$H$2:$K$39,2,FALSE)) | D17: =IF(B17=0,"",VLOOKUP(B17,Datos!$H$2:$K$39,3,FALSE)) | E17: =IF(B17=0,"",VLOOKUP(B17,Datos!$H$2:$K$39,4,FALSE)) | I17: =IF(H17=0,"",VLOOKUP(H17,Datos!$B$2:$D$891,2,FALSE)) | J17: =IF(H17=0,"",VLOOKUP(H17,Datos!$B$2:$D$891,3,FALSE)) | U17: =S17*T17 -> 0
A18: Inventario | C18: =IF(B18=0,"",VLOOKUP(B18,Datos!$H$2:$K$39,2,FALSE)) | D18: =IF(B18=0,"",VLOOKUP(B18,Datos!$H$2:$K$39,3,FALSE)) | E18: =IF(B18=0,"",VLOOKUP(B18,Datos!$H$2:$K$39,4,FALSE)) | I18: =IF(H18=0,"",VLOOKUP(H18,Datos!$B$2:$D$891,2,FALSE)) | J18: =IF(H18=0,"",VLOOKUP(H18,Datos!$B$2:$D$891,3,FALSE)) | U18: =S18*T18 -> 0
... A360: Inventario | C360: =IF(B360=0,"",VLOOKUP(B360,Datos!$H$2:$K$39,2,FALSE)) | D360: =IF(B360=0,"",VLOOKUP(B360,Datos!$H$2:$K$39,3,FALSE)) | E360: =IF(B360=0,"",VLOOKUP(B360,Datos!$H$2:$K$39,4,FALSE)) | I360: =IF(H360=0,"",VLOOKUP(H360,Datos!$B$2:$D$891,2,FALSE)) | J360: =IF(H360=0,"",VLOOKUP(H360,Datos!$B$2:$D$891,3,FALSE)) | U360: =S360*T360 -> 0
A361: TOTAL | S361: =SUM(S7:S360) -> 0 | U361: =SUM(U7:U360) -> 0

Sheet Reporte Marzo 2026
B1: Control Inventario de Plantas SIGI GBCC 8 | 2026
B2: Viveros, centros de acopio y acondicionamiento CONAF
B3: Reporte Marzo 2026
T4: INGRESOS Y EGRESOS DE PLANTAS EN EL PRIMER TRIMESTRE (ENERO A MARZO)
A5: ANTECEDENTES DEL VIVERO | H5: ANTECEDENTES DE LA ESPECIE | T5: N° DE PLANTAS NUEVAS | U5: N° DE PLANTAS ENTREGADAS Y/O VENDIDAS | X5: Movimientos Internos (Cambios Rango de Altura o Contenedor) | Y5: TRASLADOS INTERNOS A OTRAS UNIDADES CONAF | AB5: BAJA DE PLANTAS DE INVENTARIO | AF5: STOCK | AG5: VALORIZACIÓN
A6: Ítems | B6: Unidad Productiva | C6: Unidad Administrativa | D6: Provincia | E6: Comuna | F6: Nombre del Encargado | G6: Teléfono de Contacto | H6: Nombre Científico | I6: Nombre Común | J6: Origen | K6: Fuente de Abastecimiento | L6: Destino de la Planta | M6: Tipo de Reproducción | N6: Tipo de Contenedor | O6: Fecha Ingreso a Inventario (Día-Mes-Año) | P6: Tiempo de Viverización (años) | Q6: Rango de Altura | R6: Sectores del Vivero | S6: N° Total Plantas Control Inventario Diciembre 2025 | T6: N° Plantas NUEVAS Ingresadas a Inventario | U6: N° Entregas por Difusión | V6: N° Entregas a Programas | W6: N° Plantas Venta | X6: N° Plantas (M.I.) | Y6: N° Plantas Trasladadas | Z6: Unidades Recepción de Traslado | AA6: N° de Documento, Factura o Guía de Despacho | AB6: N° Plantas de Baja | AC6: Causas | AD6: N° Resolución | AE6: Fecha de Resolución | AF6: N° TOTAL DE PLANTAS INVENTARIO MARZO 2026 | AG6: Valor Neto ($) por Planta | AH6: Valor Total ($) por Lote | AI6: Ingresos e Inventario Inicial | AJ6: Egresos | AK6: stock Marzo | AL6: MES REPORTE | AN6: Código de planta para Guía de Despacho
A7: ='INVENTARIO INICIAL'!A7 -> Inventario | B7: ='INVENTARIO INICIAL'!B7 -> 0 | C7: =IF(B7=0,"",VLOOKUP(B7,Datos!$H$2:$K$39,2,FALSE)) | D7: =IF(B7=0,"",VLOOKUP(B7,Datos!$H$2:$K$39,3,FALSE)) | E7: =IF(B7=0,"",VLOOKUP(B7,Datos!$H$2:$K$39,4,FALSE)) | F7: ='INVENTARIO INICIAL'!F7 -> 0 | G7: ='INVENTARIO INICIAL'!G7 -> 0 | H7: ='INVENTARIO INICIAL'!H7 -> 0 | I7: =IF(H7=0,"",VLOOKUP(H7,Datos!$B$2:$D$908,2,FALSE)) | J7: =IF(H7=0,"",VLOOKUP(H7,Datos!$B$2:$D$908,3,FALSE)) | K7: ='INVENTARIO INICIAL'!K7 -> 0 | L7: ='INVENTARIO INICIAL'!L7 -> 0 | M7: ='INVENTARIO INICIAL'!M7 -> 0 | N7: ='INVENTARIO INICIAL'!N7 -> 0 | O7: ='INVENTARIO INICIAL'!O7 -> 0 | P7: ='INVENTARIO INICIAL'!P7 -> 0 | Q7: ='INVENTARIO INICIAL'!Q7 -> 0 | R7: ='INVENTARIO INICIAL'!R7 -> 0 | S7: ='INVENTARIO INICIAL'!S7 -> 0 | AF7: =IF(AI7>=AJ7,IF(AK7>=0,IF(AJ7>=0,AK7,"Error"))) -> 0 | AG7: ='INVENTARIO INICIAL'!T7 -> 0 | AH7: =AF7*AG7 -> 0 | AI7: =S7+T7 -> 0 | AJ7: =U7+V7+W7+X7+Y7+AB7 -> 0 | AK7: =AI7-AJ7 -> 0 | AL7: Marzo | AN7: ='INVENTARIO INICIAL'!X7 -> 0
A8: ='INVENTARIO INICIAL'!A8 -> Inventario | B8: ='INVENTARIO INICIAL'!B8 -> 0 | C8: =IF(B8=0,"",VLOOKUP(B8,Datos!$H$2:$K$39,2,FALSE)) | D8: =IF(B8=0,"",VLOOKUP(B8,Datos!$H$2:$K$39,3,FALSE)) | E8: =IF(B8=0,"",VLOOKUP(B8,Datos!$H$2:$K$39,4,FALSE)) | F8: ='INVENTARIO INICIAL'!F8 -> 0 | G8: ='INVENTARIO INICIAL'!G8 -> 0 | H8: ='INVENTARIO INICIAL'!H8 -> 0 | I8: =IF(H8=0,"",VLOOKUP(H8,Datos!$B$2:$D$908,2,FALSE)) | J8: =IF(H8=0,"",VLOOKUP(H8,Datos!$B$2:$D$908,3,FALSE)) | K8: ='INVENTARIO INICIAL'!K8 -> 0 | L8: ='INVENTARIO INICIAL'!L8 -> 0 | M8: ='INVENTARIO INICIAL'!M8 -> 0 | N8: ='INVENTARIO INICIAL'!N8 -> 0 | O8: ='INVENTARIO INICIAL'!O8 -> 0 | P8: ='INVENTARIO INICIAL'!P8 -> 0 | Q8: ='INVENTARIO INICIAL'!Q8 -> 0 | R8: ='INVENTARIO INICIAL'!R8 -> 0 | S8: ='INVENTARIO INICIAL'!S8 -> 0 | AF8: =IF(AI8>=AJ8,IF(AK8>=0,IF(AJ8>=0,AK8,"Error"))) -> 0 | AG8: ='INVENTARIO INICIAL'!T8 -> 0 | AH8: =AF8*AG8 -> 0 | AI8: =S8+T8 -> 0 | AJ8: =U8+V8+W8+X8+Y8+AB8 -> 0 | AK8: =AI8-AJ8 -> 0 | AL8: Marzo | AN8: ='INVENTARIO INICIAL'!X8 -> 0
A9: ='INVENTARIO INICIAL'!A9 -> Inventario | B9: ='INVENTARIO INICIAL'!B9 -> 0 | C9: =IF(B9=0,"",VLOOKUP(B9,Datos!$H$2:$K$39,2,FALSE)) | D9: =IF(B9=0,"",VLOOKUP(B9,Datos!$H$2:$K$39,3,FALSE)) | E9: =IF(B9=0,"",VLOOKUP(B9,Datos!$H$2:$K$39,4,FALSE)) | F9: ='INVENTARIO INICIAL'!F9 -> 0 | G9: ='INVENTARIO INICIAL'!G9 -> 0 | H9: ='INVENTARIO INICIAL'!H9 -> 0 | I9: =IF(H9=0,"",VLOOKUP(H9,Datos!$B$2:$D$908,2,FALSE)) | J9: =IF(H9=0,"",VLOOKUP(H9,Datos!$B$2:$D$908,3,FALSE)) | K9: ='INVENTARIO INICIAL'!K9 -> 0 | L9: ='INVENTARIO INICIAL'!L9 -> 0 | M9: ='INVENTARIO INICIAL'!M9 -> 0 | N9: ='INVENTARIO INICIAL'!N9 -> 0 | O9: ='INVENTARIO INICIAL'!O9 -> 0 | P9: ='INVENTARIO INICIAL'!P9 -> 0 | Q9: ='INVENTARIO INICIAL'!Q9 -> 0 | R9: ='INVENTARIO INICIAL'!R9 -> 0 | S9: ='INVENTARIO INICIAL'!S9 -> 0 | AF9: =IF(AI9>=AJ9,IF(AK9>=0,IF(AJ9>=0,AK9,"Error"))) -> 0 | AG9: ='INVENTARIO INICIAL'!T9 -> 0 | AH9: =AF9*AG9 -> 0 | AI9: =S9+T9 -> 0 | AJ9: =U9+V9+W9+X9+Y9+AB9 -> 0 | AK9: =AI9-AJ9 -> 0 | AL9: Marzo | AN9: ='INVENTARIO INICIAL'!X9 -> 0
A10: ='INVENTARIO INICIAL'!A10 -> Inventario | B10: ='INVENTARIO INICIAL'!B10 -> 0 | C10: =IF(B10=0,"",VLOOKUP(B10,Datos!$H$2:$K$39,2,FALSE)) | D10: =IF(B10=0,"",VLOOKUP(B10,Datos!$H$2:$K$39,3,FALSE)) | E10: =IF(B10=0,"",VLOOKUP(B10,Datos!$H$2:$K$39,4,FALSE)) | F10: ='INVENTARIO INICIAL'!F10 -> 0 | G10: ='INVENTARIO INICIAL'!G10 -> 0 | H10: ='INVENTARIO INICIAL'!H10 -> 0 | I10: =IF(H10=0,"",VLOOKUP(H10,Datos!$B$2:$D$908,2,FALSE)) | J10: =IF(H10=0,"",VLOOKUP(H10,Datos!$B$2:$D$908,3,FALSE)) | K10: ='INVENTARIO INICIAL'!K10 -> 0 | L10: ='INVENTARIO INICIAL'!L10 -> 0 | M10: ='INVENTARIO INICIAL'!M10 -> 0 | N10: ='INVENTARIO INICIAL'!N10 -> 0 | O10: ='INVENTARIO INICIAL'!O10 -> 0 | P10: ='INVENTARIO INICIAL'!P10 -> 0 | Q10: ='INVENTARIO INICIAL'!Q10 -> 0 | R10: ='INVENTARIO INICIAL'!R10 -> 0 | S10: ='INVENTARIO INICIAL'!S10 -> 0 | AF10: =IF(AI10>=AJ10,IF(AK10>=0,IF(AJ10>=0,AK10,"Error"))) -> 0 | AG10: ='INVENTARIO INICIAL'!T10 -> 0 | AH10: =AF10*AG10 -> 0 | AI10: =S10+T10 -> 0 | AJ10: =U10+V10+W10+X10+Y10+AB10 -> 0 | AK10: =AI10-AJ10 -> 0 | AL10: Marzo | AN10: ='INVENTARIO INICIAL'!X10 -> 0
A11: ='INVENTARIO INICIAL'!A11 -> Inventario | B11: ='INVENTARIO INICIAL'!B11 -> 0 | C11: =IF(B11=0,"",VLOOKUP(B11,Datos!$H$2:$K$39,2,FALSE)) | D11: =IF(B11=0,"",VLOOKUP(B11,Datos!$H$2:$K$39,3,FALSE)) | E11: =IF(B11=0,"",VLOOKUP(B11,Datos!$H$2:$K$39,4,FALSE)) | F11: ='INVENTARIO INICIAL'!F11 -> 0 | G11: ='INVENTARIO INICIAL'!G11 -> 0 | H11: ='INVENTARIO INICIAL'!H11 -> 0 | I11: =IF(H11=0,"",VLOOKUP(H11,Datos!$B$2:$D$908,2,FALSE)) | J11: =IF(H11=0,"",VLOOKUP(H11,Datos!$B$2:$D$908,3,FALSE)) | K11: ='INVENTARIO INICIAL'!K11 -> 0 | L11: ='INVENTARIO INICIAL'!L11 -> 0 | M11: ='INVENTARIO INICIAL'!M11 -> 0 | N11: ='INVENTARIO INICIAL'!N11 -> 0 | O11: ='INVENTARIO INICIAL'!O11 -> 0 | P11: ='INVENTARIO INICIAL'!P11 -> 0 | Q11: ='INVENTARIO INICIAL'!Q11 -> 0 | R11: ='INVENTARIO INICIAL'!R11 -> 0 | S11: ='INVENTARIO INICIAL'!S11 -> 0 | AF11: =IF(AI11>=AJ11,IF(AK11>=0,IF(AJ11>=0,AK11,"Error"))) -> 0 | AG11: ='INVENTARIO INICIAL'!T11 -> 0 | AH11: =AF11*AG11 -> 0 | AI11: =S11+T11 -> 0 | AJ11: =U11+V11+W11+X11+Y11+AB11 -> 0 | AK11: =AI11-AJ11 -> 0 | AL11: Marzo | AN11: ='INVENTARIO INICIAL'!X11 -> 0
A12: ='INVENTARIO INICIAL'!A12 -> Inventario | B12: ='INVENTARIO INICIAL'!B12 -> 0 | C12: =IF(B12=0,"",VLOOKUP(B12,Datos!$H$2:$K$39,2,FALSE)) | D12: =IF(B12=0,"",VLOOKUP(B12,Datos!$H$2:$K$39,3,FALSE)) | E12: =IF(B12=0,"",VLOOKUP(B12,Datos!$H$2:$K$39,4,FALSE)) | F12: ='INVENTARIO INICIAL'!F12 -> 0 | G12: ='INVENTARIO INICIAL'!G12 -> 0 | H12: ='INVENTARIO INICIAL'!H12 -> 0 | I12: =IF(H12=0,"",VLOOKUP(H12,Datos!$B$2:$D$908,2,FALSE)) | J12: =IF(H12=0,"",VLOOKUP(H12,Datos!$B$2:$D$908,3,FALSE)) | K12: ='INVENTARIO INICIAL'!K12 -> 0 | L12: ='INVENTARIO INICIAL'!L12 -> 0 | M12: ='INVENTARIO INICIAL'!M12 -> 0 | N12: ='INVENTARIO INICIAL'!N12 -> 0 | O12: ='INVENTARIO INICIAL'!O12 -> 0 | P12: ='INVENTARIO INICIAL'!P12 -> 0 | Q12: ='INVENTARIO INICIAL'!Q12 -> 0 | R12: ='INVENTARIO INICIAL'!R12 -> 0 | S12: ='INVENTARIO INICIAL'!S12 -> 0 | AF12: =IF(AI12>=AJ12,IF(AK12>=0,IF(AJ12>=0,AK12,"Error"))) -> 0 | AG12: ='INVENTARIO INICIAL'!T12 -> 0 | AH12: =AF12*AG12 -> 0 | AI12: =S12+T12 -> 0 | AJ12: =U12+V12+W12+X12+Y12+AB12 -> 0 | AK12: =AI12-AJ12 -> 0 | AL12: Marzo | AN12: ='INVENTARIO INICIAL'!X12 -> 0
A13: ='INVENTARIO INICIAL'!A13 -> Inventario | B13: ='INVENTARIO INICIAL'!B13 -> 0 | C13: =IF(B13=0,"",VLOOKUP(B13,Datos!$H$2:$K$39,2,FALSE)) | D13: =IF(B13=0,"",VLOOKUP(B13,Datos!$H$2:$K$39,3,FALSE)) | E13: =IF(B13=0,"",VLOOKUP(B13,Datos!$H$2:$K$39,4,FALSE)) | F13: ='INVENTARIO INICIAL'!F13 -> 0 | G13: ='INVENTARIO INICIAL'!G13 -> 0 | H13: ='INVENTARIO INICIAL'!H13 -> 0 | I13: =IF(H13=0,"",VLOOKUP(H13,Datos!$B$2:$D$908,2,FALSE)) | J13: =IF(H13=0,"",VLOOKUP(H13,Datos!$B$2:$D$908,3,FALSE)) | K13: ='INVENTARIO INICIAL'!K13 -> 0 | L13: ='INVENTARIO INICIAL'!L13 -> 0 | M13: ='INVENTARIO INICIAL'!M13 -> 0 | N13: ='INVENTARIO INICIAL'!N13 -> 0 | O13: ='INVENTARIO INICIAL'!O13 -> 0 | P13: ='INVENTARIO INICIAL'!P13 -> 0 | Q13: ='INVENTARIO INICIAL'!Q13 -> 0 | R13: ='INVENTARIO INICIAL'!R13 -> 0 | S13: ='INVENTARIO INICIAL'!S13 -> 0 | AF13: =IF(AI13>=AJ13,IF(AK13>=0,IF(AJ13>=0,AK13,"Error"))) -> 0 | AG13: ='INVENTARIO INICIAL'!T13 -> 0 | AH13: =AF13*AG13 -> 0 | AI13: =S13+T13 -> 0 | AJ13: =U13+V13+W13+X13+Y13+AB13 -> 0 | AK13: =AI13-AJ13 -> 0 | AL13: Marzo | AN13: ='INVENTARIO INICIAL'!X13 -> 0
A14: ='INVENTARIO INICIAL'!A14 -> Inventario | B14: ='INVENTARIO INICIAL'!B14 -> 0 | C14: =IF(B14=0,"",VLOOKUP(B14,Datos!$H$2:$K$39,2,FALSE)) | D14: =IF(B14=0,"",VLOOKUP(B14,Datos!$H$2:$K$39,3,FALSE)) | E14: =IF(B14=0,"",VLOOKUP(B14,Datos!$H$2:$K$39,4,FALSE)) | F14: ='INVENTARIO INICIAL'!F14 -> 0 | G14: ='INVENTARIO INICIAL'!G14 -> 0 | H14: ='INVENTARIO INICIAL'!H14 -> 0 | I14: =IF(H14=0,"",VLOOKUP(H14,Datos!$B$2:$D$908,2,FALSE)) | J14: =IF(H14=0,"",VLOOKUP(H14,Datos!$B$2:$D$908,3,FALSE)) | K14: ='INVENTARIO INICIAL'!K14 -> 0 | L14: ='INVENTARIO INICIAL'!L14 -> 0 | M14: ='INVENTARIO INICIAL'!M14 -> 0 | N14: ='INVENTARIO INICIAL'!N14 -> 0 | O14: ='INVENTARIO INICIAL'!O14 -> 0 | P14: ='INVENTARIO INICIAL'!P14 -> 0 | Q14: ='INVENTARIO INICIAL'!Q14 -> 0 | R14: ='INVENTARIO INICIAL'!R14 -> 0 | S14: ='INVENTARIO INICIAL'!S14 -> 0 | AF14: =IF(AI14>=AJ14,IF(AK14>=0,IF(AJ14>=0,AK14,"Error"))) -> 0 | AG14: ='INVENTARIO INICIAL'!T14 -> 0 | AH14: =AF14*AG14 -> 0 | AI14: =S14+T14 -> 0 | AJ14: =U14+V14+W14+X14+Y14+AB14 -> 0 | AK14: =AI14-AJ14 -> 0 | AL14: Marzo | AN14: ='INVENTARIO INICIAL'!X14 -> 0
A15: ='INVENTARIO INICIAL'!A15 -> Inventario | B15: ='INVENTARIO INICIAL'!B15 -> 0 | C15: =IF(B15=0,"",VLOOKUP(B15,Datos!$H$2:$K$39,2,FALSE)) | D15: =IF(B15=0,"",VLOOKUP(B15,Datos!$H$2:$K$39,3,FALSE)) | E15: =IF(B15=0,"",VLOOKUP(B15,Datos!$H$2:$K$39,4,FALSE)) | F15: ='INVENTARIO INICIAL'!F15 -> 0 | G15: ='INVENTARIO INICIAL'!G15 -> 0 | H15: ='INVENTARIO INICIAL'!H15 -> 0 | I15: =IF(H15=0,"",VLOOKUP(H15,Datos!$B$2:$D$908,2,FALSE)) | J15: =IF(H15=0,"",VLOOKUP(H15,Datos!$B$2:$D$908,3,FALSE)) | K15: ='INVENTARIO INICIAL'!K15 -> 0 | L15: ='INVENTARIO INICIAL'!L15 -> 0 | M15: ='INVENTARIO INICIAL'!M15 -> 0 | N15: ='INVENTARIO INICIAL'!N15 -> 0 | O15: ='INVENTARIO INICIAL'!O15 -> 0 | P15: ='INVENTARIO INICIAL'!P15 -> 0 | Q15: ='INVENTARIO INICIAL'!Q15 -> 0 | R15: ='INVENTARIO INICIAL'!R15 -> 0 | S15: ='INVENTARIO INICIAL'!S15 -> 0 | AF15: =IF(AI15>=AJ15,IF(AK15>=0,IF(AJ15>=0,AK15,"Error"))) -> 0 | AG15: ='INVENTARIO INICIAL'!T15 -> 0 | AH15: =AF15*AG15 -> 0 | AI15: =S15+T15 -> 0 | AJ15: =U15+V15+W15+X15+Y15+AB15 -> 0 | AK15: =AI15-AJ15 -> 0 | AL15: Marzo | AN15: ='INVENTARIO INICIAL'!X15 -> 0
A16: ='INVENTARIO INICIAL'!A16 -> Inventario | B16: ='INVENTARIO INICIAL'!B16 -> 0 | C16: =IF(B16=0,"",VLOOKUP(B16,Datos!$H$2:$K$39,2,FALSE)) | D16: =IF(B16=0,"",VLOOKUP(B16,Datos!$H$2:$K$39,3,FALSE)) | E16: =IF(B16=0,"",VLOOKUP(B16,Datos!$H$2:$K$39,4,FALSE)) | F16: ='INVENTARIO INICIAL'!F16 -> 0 | G16: ='INVENTARIO INICIAL'!G16 -> 0 | H16: ='INVENTARIO INICIAL'!H16 -> 0 | I16: =IF(H16=0,"",VLOOKUP(H16,Datos!$B$2:$D$908,2,FALSE)) | J16: =IF(H16=0,"",VLOOKUP(H16,Datos!$B$2:$D$908,3,FALSE)) | K16: ='INVENTARIO INICIAL'!K16 -> 0 | L16: ='INVENTARIO INICIAL'!L16 -> 0 | M16: ='INVENTARIO INICIAL'!M16 -> 0 | N16: ='INVENTARIO INICIAL'!N16 -> 0 | O16: ='INVENTARIO INICIAL'!O16 -> 0 | P16: ='INVENTARIO INICIAL'!P16 -> 0 | Q16: ='INVENTARIO INICIAL'!Q16 -> 0 | R16: ='INVENTARIO INICIAL'!R16 -> 0 | S16: ='INVENTARIO INICIAL'!S16 -> 0 | AF16: =IF(AI16>=AJ16,IF(AK16>=0,IF(AJ16>=0,AK16,"Error"))) -> 0 | AG16: ='INVENTARIO INICIAL'!T16 -> 0 | AH16: =AF16*AG16 -> 0 | AI16: =S16+T16 -> 0 | AJ16: =U16+V16+W16+X16+Y16+AB16 -> 0 | AK16: =AI16-AJ16 -> 0 | AL16: Marzo | AN16: ='INVENTARIO INICIAL'!X16 -> 0
A17: ='INVENTARIO INICIAL'!A17 -> Inventario | B17: ='INVENTARIO INICIAL'!B17 -> 0 | C17: =IF(B17=0,"",VLOOKUP(B17,Datos!$H$2:$K$39,2,FALSE)) | D17: =IF(B17=0,"",VLOOKUP(B17,Datos!$H$2:$K$39,3,FALSE)) | E17: =IF(B17=0,"",VLOOKUP(B17,Datos!$H$2:$K$39,4,FALSE)) | F17: ='INVENTARIO INICIAL'!F17 -> 0 | G17: ='INVENTARIO INICIAL'!G17 -> 0 | H17: ='INVENTARIO INICIAL'!H17 -> 0 | I17: =IF(H17=0,"",VLOOKUP(H17,Datos!$B$2:$D$908,2,FALSE)) | J17: =IF(H17=0,"",VLOOKUP(H17,Datos!$B$2:$D$908,3,FALSE)) | K17: ='INVENTARIO INICIAL'!K17 -> 0 | L17: ='INVENTARIO INICIAL'!L17 -> 0 | M17: ='INVENTARIO INICIAL'!M17 -> 0 | N17: ='INVENTARIO INICIAL'!N17 -> 0 | O17: ='INVENTARIO INICIAL'!O17 -> 0 | P17: ='INVENTARIO INICIAL'!P17 -> 0 | Q17: ='INVENTARIO INICIAL'!Q17 -> 0 | R17: ='INVENTARIO INICIAL'!R17 -> 0 | S17: ='INVENTARIO INICIAL'!S17 -> 0 | AF17: =IF(AI17>=AJ17,IF(AK17>=0,IF(AJ17>=0,AK17,"Error"))) -> 0 | AG17: ='INVENTARIO INICIAL'!T17 -> 0 | AH17: =AF17*AG17 -> 0 | AI17: =S17+T17 -> 0 | AJ17: =U17+V17+W17+X17+Y17+AB17 -> 0 | AK17: =AI17-AJ17 -> 0 | AL17: Marzo | AN17: ='INVENTARIO INICIAL'!X17 -> 0
A18: ='INVENTARIO INICIAL'!A18 -> Inventario | B18: ='INVENTARIO INICIAL'!B18 -> 0 | C18: =IF(B18=0,"",VLOOKUP(B18,Datos!$H$2:$K$39,2,FALSE)) | D18: =IF(B18=0,"",VLOOKUP(B18,Datos!$H$2:$K$39,3,FALSE)) | E18: =IF(B18=0,"",VLOOKUP(B18,Datos!$H$2:$K$39,4,FALSE)) | F18: ='INVENTARIO INICIAL'!F18 -> 0 | G18: ='INVENTARIO INICIAL'!G18 -> 0 | H18: ='INVENTARIO INICIAL'!H18 -> 0 | I18: =IF(H18=0,"",VLOOKUP(H18,Datos!$B$2:$D$908,2,FALSE)) | J18: =IF(H18=0,"",VLOOKUP(H18,Datos!$B$2:$D$908,3,FALSE)) | K18: ='INVENTARIO INICIAL'!K18 -> 0 | L18: ='INVENTARIO INICIAL'!L18 -> 0 | M18: ='INVENTARIO INICIAL'!M18 -> 0 | N18: ='INVENTARIO INICIAL'!N18 -> 0 | O18: ='INVENTARIO INICIAL'!O18 -> 0 | P18: ='INVENTARIO INICIAL'!P18 -> 0 | Q18: ='INVENTARIO INICIAL'!Q18 -> 0 | R18: ='INVENTARIO INICIAL'!R18 -> 0 | S18: ='INVENTARIO INICIAL'!S18 -> 0 | AF18: =IF(AI18>=AJ18,IF(AK18>=0,IF(AJ18>=0,AK18,"Error"))) -> 0 | AG18: ='INVENTARIO INICIAL'!T18 -> 0 | AH18: =AF18*AG18 -> 0 | AI18: =S18+T18 -> 0 | AJ18: =U18+V18+W18+X18+Y18+AB18 -> 0 | AK18: =AI18-AJ18 -> 0 | AL18: Marzo | AN18: ='INVENTARIO INICIAL'!X18 -> 0
... A360: ='INVENTARIO INICIAL'!A360 -> Inventario | B360: ='INVENTARIO INICIAL'!B360 -> 0 | C360: =IF(B360=0,"",VLOOKUP(B360,Datos!$H$2:$K$39,2,FALSE)) | D360: =IF(B360=0,"",VLOOKUP(B360,Datos!$H$2:$K$39,3,FALSE)) | E360: =IF(B360=0,"",VLOOKUP(B360,Datos!$H$2:$K$39,4,FALSE)) | F360: ='INVENTARIO INICIAL'!F360 -> 0 | G360: ='INVENTARIO INICIAL'!G360 -> 0 | H360: ='INVENTARIO INICIAL'!H360 -> 0 | I360: =IF(H360=0,"",VLOOKUP(H360,Datos!$B$2:$D$908,2,FALSE)) | J360: =IF(H360=0,"",VLOOKUP(H360,Datos!$B$2:$D$908,3,FALSE)) | K360: ='INVENTARIO INICIAL'!K360 -> 0 | L360: ='INVENTARIO INICIAL'!L360 -> 0 | M360: ='INVENTARIO INICIAL'!M360 -> 0 | N360: ='INVENTARIO INICIAL'!N360 -> 0 | O360: ='INVENTARIO INICIAL'!O360 -> 0 | P360: ='INVENTARIO INICIAL'!P360 -> 0 | Q360: ='INVENTARIO INICIAL'!Q360 -> 0 | R360: ='INVENTARIO INICIAL'!R360 -> 0 | S360: ='INVENTARIO INICIAL'!S360 -> 0 | AF360: =IF(AI360>=AJ360,IF(AK360>=0,IF(AJ360>=0,AK360,"Error"))) -> 0 | AG360: ='INVENTARIO INICIAL'!T360 -> 0 | AH360: =AF360*AG360 -> 0 | AI360: =S360+T360 -> 0 | AJ360: =U360+V360+W360+X360+Y360+AB360 -> 0 | AK360: =AI360-AJ360 -> 0 | AL360: Marzo | AN360: ='INVENTARIO INICIAL'!X360 -> 0
A361: Ingresos | C361: =IF(B361=0,"",VLOOKUP(B361,Datos!$H$2:$K$39,2,FALSE)) | D361: =IF(B361=0,"",VLOOKUP(B361,Datos!$H$2:$K$39,3,FALSE)) | E361: =IF(B361=0,"",VLOOKUP(B361,Datos!$H$2:$K$39,4,FALSE)) | I361: =IF(H361=0,"",VLOOKUP(H361,Datos!$B$2:$D$908,2,FALSE)) | J361: =IF(H361=0,"",VLOOKUP(H361,Datos!$B$2:$D$908,3,FALSE)) | AF361: =IF(AI361>=AJ361,IF(AK361>=0,IF(AJ361>=0,AK361,"Error"))) -> 0 | AG361: 0 | AH361: =AF361*AG361 -> 0 | AI361: =S361+T361 -> 0 | AJ361: =U361+V361+W361+X361+Y361+AB361 -> 0 | AK361: =AI361-AJ361 -> 0 | AL361: Marzo
A362: Ingresos | C362: =IF(B362=0,"",VLOOKUP(B362,Datos!$H$2:$K$39,2,FALSE)) | D362: =IF(B362=0,"",VLOOKUP(B362,Datos!$H$2:$K$39,3,FALSE)) | E362: =IF(B362=0,"",VLOOKUP(B362,Datos!$H$2:$K$39,4,FALSE)) | I362: =IF(H362=0,"",VLOOKUP(H362,Datos!$B$2:$D$908,2,FALSE)) | J362: =IF(H362=0,"",VLOOKUP(H362,Datos!$B$2:$D$908,3,FALSE)) | AF362: =IF(AI362>=AJ362,IF(AK362>=0,IF(AJ362>=0,AK362,"Error"))) -> 0 | AG362: 0 | AH362: =AF362*AG362 -> 0 | AI362: =S362+T362 -> 0 | AJ362: =U362+V362+W362+X362+Y362+AB362 -> 0 | AK362: =AI362-AJ362 -> 0 | AL362: Marzo
A363: Ingresos | C363: =IF(B363=0,"",VLOOKUP(B363,Datos!$H$2:$K$39,2,FALSE)) | D363: =IF(B363=0,"",VLOOKUP(B363,Datos!$H$2:$K$39,3,FALSE)) | E363: =IF(B363=0,"",VLOOKUP(B363,Datos!$H$2:$K$39,4,FALSE)) | I363: =IF(H363=0,"",VLOOKUP(H363,Datos!$B$2:$D$908,2,FALSE)) | J363: =IF(H363=0,"",VLOOKUP(H363,Datos!$B$2:$D$908,3,FALSE)) | AF363: =IF(AI363>=AJ363,IF(AK363>=0,IF(AJ363>=0,AK363,"Error"))) -> 0 | AG363: 0 | AH363: =AF363*AG363 -> 0 | AI363: =S363+T363 -> 0 | AJ363: =U363+V363+W363+X363+Y363+AB363 -> 0 | AK363: =AI363-AJ363 -> 0 | AL363: Marzo
A364: Ingresos | C364: =IF(B364=0,"",VLOOKUP(B364,Datos!$H$2:$K$39,2,FALSE)) | D364: =IF(B364=0,"",VLOOKUP(B364,Datos!$H$2:$K$39,3,FALSE)) | E364: =IF(B364=0,"",VLOOKUP(B364,Datos!$H$2:$K$39,4,FALSE)) | I364: =IF(H364=0,"",VLOOKUP(H364,Datos!$B$2:$D$908,2,FALSE)) | J364: =IF(H364=0,"",VLOOKUP(H364,Datos!$B$2:$D$908,3,FALSE)) | AF364: =IF(AI364>=AJ364,IF(AK364>=0,IF(AJ364>=0,AK364,"Error"))) -> 0 | AG364: 0 | AH364: =AF364*AG364 -> 0 | AI364: =S364+T364 -> 0 | AJ364: =U364+V364+W364+X364+Y364+AB364 -> 0 | AK364: =AI364-AJ364 -> 0 | AL364: Marzo
A365: Ingresos | C365: =IF(B365=0,"",VLOOKUP(B365,Datos!$H$2:$K$39,2,FALSE)) | D365: =IF(B365=0,"",VLOOKUP(B365,Datos!$H$2:$K$39,3,FALSE)) | E365: =IF(B365=0,"",VLOOKUP(B365,Datos!$H$2:$K$39,4,FALSE)) | I365: =IF(H365=0,"",VLOOKUP(H365,Datos!$B$2:$D$908,2,FALSE)) | J365: =IF(H365=0,"",VLOOKUP(H365,Datos!$B$2:$D$908,3,FALSE)) | AF365: =IF(AI365>=AJ365,IF(AK365>=0,IF(AJ365>=0,AK365,"Error"))) -> 0 | AG365: 0 | AH365: =AF365*AG365 -> 0 | AI365: =S365+T365 -> 0 | AJ365: =U365+V365+W365+X365+Y365+AB365 -> 0 | AK365: =AI365-AJ365 -> 0 | AL365: Marzo
A366: Ingresos | C366: =IF(B366=0,"",VLOOKUP(B366,Datos!$H$2:$K$39,2,FALSE)) | D366: =IF(B366=0,"",VLOOKUP(B366,Datos!$H$2:$K$39,3,FALSE)) | E366: =IF(B366=0,"",VLOOKUP(B366,Datos!$H$2:$K$39,4,FALSE)) | I366: =IF(H366=0,"",VLOOKUP(H366,Datos!$B$2:$D$908,2,FALSE)) | J366: =IF(H366=0,"",VLOOKUP(H366,Datos!$B$2:$D$908,3,FALSE)) | AF366: =IF(AI366>=AJ366,IF(AK366>=0,IF(AJ366>=0,AK366,"Error"))) -> 0 | AG366: 0 | AH366: =AF366*AG366 -> 0 | AI366: =S366+T366 -> 0 | AJ366: =U366+V366+W366+X366+Y366+AB366 -> 0 | AK366: =AI366-AJ366 -> 0 | AL366: Marzo
A367: Ingresos | C367: =IF(B367=0,"",VLOOKUP(B367,Datos!$H$2:$K$39,2,FALSE)) | D367: =IF(B367=0,"",VLOOKUP(B367,Datos!$H$2:$K$39,3,FALSE)) | E367: =IF(B367=0,"",VLOOKUP(B367,Datos!$H$2:$K$39,4,FALSE)) | I367: =IF(H367=0,"",VLOOKUP(H367,Datos!$B$2:$D$908,2,FALSE)) | J367: =IF(H367=0,"",VLOOKUP(H367,Datos!$B$2:$D$908,3,FALSE)) | AF367: =IF(AI367>=AJ367,IF(AK367>=0,IF(AJ367>=0,AK367,"Error"))) -> 0 | AG367: 0 | AH367: =AF367*AG367 -> 0 | AI367: =S367+T367 -> 0 | AJ367: =U367+V367+W367+X367+Y367+AB367 -> 0 | AK367: =AI367-AJ367 -> 0 | AL367: Marzo
A368: Ingresos | C368: =IF(B368=0,"",VLOOKUP(B368,Datos!$H$2:$K$39,2,FALSE)) | D368: =IF(B368=0,"",VLOOKUP(B368,Datos!$H$2:$K$39,3,FALSE)) | E368: =IF(B368=0,"",VLOOKUP(B368,Datos!$H$2:$K$39,4,FALSE)) | I368: =IF(H368=0,"",VLOOKUP(H368,Datos!$B$2:$D$908,2,FALSE)) | J368: =IF(H368=0,"",VLOOKUP(H368,Datos!$B$2:$D$908,3,FALSE)) | AF368: =IF(AI368>=AJ368,IF(AK368>=0,IF(AJ368>=0,AK368,"Error"))) -> 0 | AG368: 0 | AH368: =AF368*AG368 -> 0 | AI368: =S368+T368 -> 0 | AJ368: =U368+V368+W368+X368+Y368+AB368 -> 0 | AK368: =AI368-AJ368 -> 0 | AL368: Marzo
A369: Ingresos | C369: =IF(B369=0,"",VLOOKUP(B369,Datos!$H$2:$K$39,2,FALSE)) | D369: =IF(B369=0,"",VLOOKUP(B369,Datos!$H$2:$K$39,3,FALSE)) | E369: =IF(B369=0,"",VLOOKUP(B369,Datos!$H$2:$K$39,4,FALSE)) | I369: =IF(H369=0,"",VLOOKUP(H369,Datos!$B$2:$D$908,2,FALSE)) | J369: =IF(H369=0,"",VLOOKUP(H369,Datos!$B$2:$D$908,3,FALSE)) | AF369: =IF(AI369>=AJ369,IF(AK369>=0,IF(AJ369>=0,AK369,"Error"))) -> 0 | AG369: 0 | AH369: =AF369*AG369 -> 0 | AI369: =S369+T369 -> 0 | AJ369: =U369+V369+W369+X369+Y369+AB369 -> 0 | AK369: =AI369-AJ369 -> 0 | AL369: Marzo
A370: Ingresos | C370: =IF(B370=0,"",VLOOKUP(B370,Datos!$H$2:$K$39,2,FALSE)) | D370: =IF(B370=0,"",VLOOKUP(B370,Datos!$H$2:$K$39,3,FALSE)) | E370: =IF(B370=0,"",VLOOKUP(B370,Datos!$H$2:$K$39,4,FALSE)) | I370: =IF(H370=0,"",VLOOKUP(H370,Datos!$B$2:$D$908,2,FALSE)) | J370: =IF(H370=0,"",VLOOKUP(H370,Datos!$B$2:$D$908,3,FALSE)) | AF370: =IF(AI370>=AJ370,IF(AK370>=0,IF(AJ370>=0,AK370,"Error"))) -> 0 | AG370: 0 | AH370: =AF370*AG370 -> 0 | AI370: =S370+T370 -> 0 | AJ370: =U370+V370+W370+X370+Y370+AB370 -> 0 | AK370: =AI370-AJ370 -> 0 | AL370: Marzo
A371: Ingresos | C371: =IF(B371=0,"",VLOOKUP(B371,Datos!$H$2:$K$39,2,FALSE)) | D371: =IF(B371=0,"",VLOOKUP(B371,Datos!$H$2:$K$39,3,FALSE)) | E371: =IF(B371=0,"",VLOOKUP(B371,Datos!$H$2:$K$39,4,FALSE)) | I371: =IF(H371=0,"",VLOOKUP(H371,Datos!$B$2:$D$908,2,FALSE)) | J371: =IF(H371=0,"",VLOOKUP(H371,Datos!$B$2:$D$908,3,FALSE)) | AF371: =IF(AI371>=AJ371,IF(AK371>=0,IF(AJ371>=0,AK371,"Error"))) -> 0 | AG371: 0 | AH371: =AF371*AG371 -> 0 | AI371: =S371+T371 -> 0 | AJ371: =U371+V371+W371+X371+Y371+AB371 -> 0 | AK371: =AI371-AJ371 -> 0 | AL371: Marzo
A372: Ingresos | C372: =IF(B372=0,"",VLOOKUP(B372,Datos!$H$2:$K$39,2,FALSE)) | D372: =IF(B372=0,"",VLOOKUP(B372,Datos!$H$2:$K$39,3,FALSE)) | E372: =IF(B372=0,"",VLOOKUP(B372,Datos!$H$2:$K$39,4,FALSE)) | I372: =IF(H372=0,"",VLOOKUP(H372,Datos!$B$2:$D$908,2,FALSE)) | J372: =IF(H372=0,"",VLOOKUP(H372,Datos!$B$2:$D$908,3,FALSE)) | AF372: =IF(AI372>=AJ372,IF(AK372>=0,IF(AJ372>=0,AK372,"Error"))) -> 0 | AG372: 0 | AH372: =AF372*AG372 -> 0 | AI372: =S372+T372 -> 0 | AJ372: =U372+V372+W372+X372+Y372+AB372 -> 0 | AK372: =AI372-AJ372 -> 0 | AL372: Marzo
... A490: Ingresos | C490: =IF(B490=0,"",VLOOKUP(B490,Datos!$H$2:$K$39,2,FALSE)) | D490: =IF(B490=0,"",VLOOKUP(B490,Datos!$H$2:$K$39,3,FALSE)) | E490: =IF(B490=0,"",VLOOKUP(B490,Datos!$H$2:$K$39,4,FALSE)) | I490: =IF(H490=0,"",VLOOKUP(H490,Datos!$B$2:$D$908,2,FALSE)) | J490: =IF(H490=0,"",VLOOKUP(H490,Datos!$B$2:$D$908,3,FALSE)) | AF490: =IF(AI490>=AJ490,IF(AK490>=0,IF(AJ490>=0,AK490,"Error"))) -> 0 | AG490: 0 | AH490: =AF490*AG490 -> 0 | AI490: =S490+T490 -> 0 | AJ490: =U490+V490+W490+X490+Y490+AB490 -> 0 | AK490: =AI490-AJ490 -> 0 | AL490: Marzo
A491: Total Marzo | R491: Total | S491: =SUM(S7:S490) -> 0 | T491: =SUM(T7:T490) -> 0 | U491: =SUM(U7:U490) -> 0 | V491: =SUM(V7:V490) -> 0 | W491: =SUM(W7:W490) -> 0 | X491: =SUM(X7:X490) -> 0 | Y491: =SUM(Y7:Y490) -> 0 | AB491: =SUM(AB7:AB490) -> 0 | AF491: =SUM(AF7:AF490) -> 0 | AH491: =SUM(AH7:AH490) -> 0

Sheet Reporte Junio 2026
B1: Control Inventario de Plantas SIGI GBCC 8 | 2026
B2: Viveros, centros de acopio y acondicionamiento CONAF
B3: Reporte Junio 2026
T4: INGRESOS Y EGRESOS DE PLANTAS EN EL SEGUNDO TRIMESTRE (ABRIL A JUNIO)
A5: ANTECEDENTES DEL VIVERO | H5: ANTECEDENTES DE LA ESPECIE | T5: N° DE PLANTAS NUEVAS | U5: N° DE PLANTAS ENTREGADAS Y/O VENDIDAS | X5: Movimientos Internos (Cambios Rango de Altura o Contenedor) | Y5: TRASLADOS INTERNOS A OTRAS UNIDADES CONAF | AB5: BAJA DE PLANTAS DE INVENTARIO | AF5: STOCK | AG5: VALORIZACIÓN
A6: Ítems | B6: Unidad Productiva | C6: Unidad Administrativa | D6: Provincia | E6: Comuna | F6: Encargado | G6: Teléfono de Contacto | H6: Nombre Científico | I6: Nombre Común | J6: Origen | K6: Fuente de Abastecimiento | L6: Destino de la Planta | M6: Tipo de Reproducción | N6: Tipo de Contenedor | O6: Fecha Ingreso a Inventario (Día/Mes/Año) | P6: Tiempo de Viverización (años) | Q6: Rango de Altura | R6: Sectores del Vivero | S6: N° Total Plantas Control Inventario Marzo 2026 | T6: N° Plantas NUEVAS Ingresadas a Inventario | U6: N° Entregas por Difusión | V6: N° Entregas a Programas | W6: N° Plantas Venta | X6: N° Plantas (M.I.) | Y6: N° Plantas Trasladadas | Z6: Unidades Recepción de Traslado | AA6: N° de Documento, Factura o Guía de Despacho | AB6: N° Plantas de Baja | AC6: Causas | AD6: N° Resolución | AE6: Fecha de Resolución | AF6: N° TOTAL DE PLANTAS EN INVENTARIO JUNIO 2026 | AG6: Valor Neto ($) por planta | AH6: Valor Total ($) por lote | AI6: Ingresos | AJ6: Egresos | AK6: stock Junio | AL6: MES REPORTE | AN6: Código de planta para Guía de Despacho
A7: ='Reporte Marzo 2026'!A7 -> Inventario | B7: ='INVENTARIO INICIAL'!B7 -> 0 | C7: =IF(B7=0,"",VLOOKUP(B7,Datos!$H$2:$K$39,2,FALSE)) | D7: =IF(B7=0,"",VLOOKUP(B7,Datos!$H$2:$K$39,3,FALSE)) | E7: =IF(B7=0,"",VLOOKUP(B7,Datos!$H$2:$K$39,4,FALSE)) | F7: ='INVENTARIO INICIAL'!F7 -> 0 | G7: ='INVENTARIO INICIAL'!G7 -> 0 | H7: ='INVENTARIO INICIAL'!H7 -> 0 | I7: =IF(H7=0,"",VLOOKUP(H7,Datos!$B$2:$D$908,2,FALSE)) | J7: =IF(H7=0,"",VLOOKUP(H7,Datos!$B$2:$D$908,3,FALSE)) | K7: ='INVENTARIO INICIAL'!K7 -> 0 | L7: ='INVENTARIO INICIAL'!L7 -> 0 | M7: ='INVENTARIO INICIAL'!M7 -> 0 | N7: ='INVENTARIO INICIAL'!N7 -> 0 | O7: ='INVENTARIO INICIAL'!O7 -> 0 | P7: ='INVENTARIO INICIAL'!P7 -> 0 | Q7: ='INVENTARIO INICIAL'!Q7 -> 0 | R7: ='INVENTARIO INICIAL'!R7 -> 0 | S7: ='Reporte Marzo 2026'!AF7 -> 0 | AF7: =IF(AI7>=AJ7,IF(AK7>=0,IF(AJ7>=0,AK7,"Error"))) -> 0 | AG7: ='Reporte Marzo 2026'!AG7 -> 0 | AH7: =AF7*AG7 -> 0 | AI7: =S7+T7 -> 0 | AJ7: =U7+V7+W7+X7+Y7+AB7 -> 0 | AK7: =AI7-AJ7 -> 0 | AL7: Junio | AN7: ='INVENTARIO INICIAL'!X7 -> 0
A8: ='Reporte Marzo 2026'!A8 -> Inventario | B8: ='INVENTARIO INICIAL'!B8 -> 0 | C8: =IF(B8=0,"",VLOOKUP(B8,Datos!$H$2:$K$39,2,FALSE)) | D8: =IF(B8=0,"",VLOOKUP(B8,Datos!$H$2:$K$39,3,FALSE)) | E8: =IF(B8=0,"",VLOOKUP(B8,Datos!$H$2:$K$39,4,FALSE)) | F8: ='INVENTARIO INICIAL'!F8 -> 0 | G8: ='INVENTARIO INICIAL'!G8 -> 0 | H8: ='INVENTARIO INICIAL'!H8 -> 0 | I8: =IF(H8=0,"",VLOOKUP(H8,Datos!$B$2:$D$908,2,FALSE)) | J8: =IF(H8=0,"",VLOOKUP(H8,Datos!$B$2:$D$908,3,FALSE)) | K8: ='INVENTARIO INICIAL'!K8 -> 0 | L8: ='INVENTARIO INICIAL'!L8 -> 0 | M8: ='INVENTARIO INICIAL'!M8 -> 0 | N8: ='INVENTARIO INICIAL'!N8 -> 0 | O8: ='INVENTARIO INICIAL'!O8 -> 0 | P8: ='INVENTARIO INICIAL'!P8 -> 0 | Q8: ='INVENTARIO INICIAL'!Q8 -> 0 | R8: ='INVENTARIO INICIAL'!R8 -> 0 | S8: ='Reporte Marzo 2026'!AF8 -> 0 | AF8: =IF(AI8>=AJ8,IF(AK8>=0,IF(AJ8>=0,AK8,"Error"))) -> 0 | AG8: ='Reporte Marzo 2026'!AG8 -> 0 | AH8: =AF8*AG8 -> 0 | AI8: =S8+T8 -> 0 | AJ8: =U8+V8+W8+X8+Y8+AB8 -> 0 | AK8: =AI8-AJ8 -> 0 | AL8: Junio | AN8: ='INVENTARIO INICIAL'!X8 -> 0
A9: ='Reporte Marzo 2026'!A9 -> Inventario | B9: ='INVENTARIO INICIAL'!B9 -> 0 | C9: =IF(B9=0,"",VLOOKUP(B9,Datos!$H$2:$K$39,2,FALSE)) | D9: =IF(B9=0,"",VLOOKUP(B9,Datos!$H$2:$K$39,3,FALSE)) | E9: =IF(B9=0,"",VLOOKUP(B9,Datos!$H$2:$K$39,4,FALSE)) | F9: ='INVENTARIO INICIAL'!F9 -> 0 | G9: ='INVENTARIO INICIAL'!G9 -> 0 | H9: ='INVENTARIO INICIAL'!H9 -> 0 | I9: =IF(H9=0,"",VLOOKUP(H9,Datos!$B$2:$D$908,2,FALSE)) | J9: =IF(H9=0,"",VLOOKUP(H9,Datos!$B$2:$D$908,3,FALSE)) | K9: ='INVENTARIO INICIAL'!K9 -> 0 | L9: ='INVENTARIO INICIAL'!L9 -> 0 | M9: ='INVENTARIO INICIAL'!M9 -> 0 | N9: ='INVENTARIO INICIAL'!N9 -> 0 | O9: ='INVENTARIO INICIAL'!O9 -> 0 | P9: ='INVENTARIO INICIAL'!P9 -> 0 | Q9: ='INVENTARIO INICIAL'!Q9 -> 0 | R9: ='INVENTARIO INICIAL'!R9 -> 0 | S9: ='Reporte Marzo 2026'!AF9 -> 0 | AF9: =IF(AI9>=AJ9,IF(AK9>=0,IF(AJ9>=0,AK9,"Error"))) -> 0 | AG9: ='Reporte Marzo 2026'!AG9 -> 0 | AH9: =AF9*AG9 -> 0 | AI9: =S9+T9 -> 0 | AJ9: =U9+V9+W9+X9+Y9+AB9 -> 0 | AK9: =AI9-AJ9 -> 0 | AL9: Junio | AN9: ='INVENTARIO INICIAL'!X9 -> 0
A10: ='Reporte Marzo 2026'!A10 -> Inventario | B10: ='INVENTARIO INICIAL'!B10 -> 0 | C10: =IF(B10=0,"",VLOOKUP(B10,Datos!$H$2:$K$39,2,FALSE)) | D10: =IF(B10=0,"",VLOOKUP(B10,Datos!$H$2:$K$39,3,FALSE)) | E10: =IF(B10=0,"",VLOOKUP(B10,Datos!$H$2:$K$39,4,FALSE)) | F10: ='INVENTARIO INICIAL'!F10 -> 0 | G10: ='INVENTARIO INICIAL'!G10 -> 0 | H10: ='INVENTARIO INICIAL'!H10 -> 0 | I10: =IF(H10=0,"",VLOOKUP(H10,Datos!$B$2:$D$908,2,FALSE)) | J10: =IF(H10=0,"",VLOOKUP(H10,Datos!$B$2:$D$908,3,FALSE)) | K10: ='INVENTARIO INICIAL'!K10 -> 0 | L10: ='INVENTARIO INICIAL'!L10 -> 0 | M10: ='INVENTARIO INICIAL'!M10 -> 0 | N10: ='INVENTARIO INICIAL'!N10 -> 0 | O10: ='INVENTARIO INICIAL'!O10 -> 0 | P10: ='INVENTARIO INICIAL'!P10 -> 0 | Q10: ='INVENTARIO INICIAL'!Q10 -> 0 | R10: ='INVENTARIO INICIAL'!R10 -> 0 | S10: ='Reporte Marzo 2026'!AF10 -> 0 | AF10: =IF(AI10>=AJ10,IF(AK10>=0,IF(AJ10>=0,AK10,"Error"))) -> 0 | AG10: ='Reporte Marzo 2026'!AG10 -> 0 | AH10: =AF10*AG10 -> 0 | AI10: =S10+T10 -> 0 | AJ10: =U10+V10+W10+X10+Y10+AB10 -> 0 | AK10: =AI10-AJ10 -> 0 | AL10: Junio | AN10: ='INVENTARIO INICIAL'!X10 -> 0
A11: ='Reporte Marzo 2026'!A11 -> Inventario | B11: ='INVENTARIO INICIAL'!B11 -> 0 | C11: =IF(B11=0,"",VLOOKUP(B11,Datos!$H$2:$K$39,2,FALSE)) | D11: =IF(B11=0,"",VLOOKUP(B11,Datos!$H$2:$K$39,3,FALSE)) | E11: =IF(B11=0,"",VLOOKUP(B11,Datos!$H$2:$K$39,4,FALSE)) | F11: ='INVENTARIO INICIAL'!F11 -> 0 | G11: ='INVENTARIO INICIAL'!G11 -> 0 | H11: ='INVENTARIO INICIAL'!H11 -> 0 | I11: =IF(H11=0,"",VLOOKUP(H11,Datos!$B$2:$D$908,2,FALSE)) | J11: =IF(H11=0,"",VLOOKUP(H11,Datos!$B$2:$D$908,3,FALSE)) | K11: ='INVENTARIO INICIAL'!K11 -> 0 | L11: ='INVENTARIO INICIAL'!L11 -> 0 | M11: ='INVENTARIO INICIAL'!M11 -> 0 | N11: ='INVENTARIO INICIAL'!N11 -> 0 | O11: ='INVENTARIO INICIAL'!O11 -> 0 | P11: ='INVENTARIO INICIAL'!P11 -> 0 | Q11: ='INVENTARIO INICIAL'!Q11 -> 0 | R11: ='INVENTARIO INICIAL'!R11 -> 0 | S11: ='Reporte Marzo 2026'!AF11 -> 0 | AF11: =IF(AI11>=AJ11,IF(AK11>=0,IF(AJ11>=0,AK11,"Error"))) -> 0 | AG11: ='Reporte Marzo 2026'!AG11 -> 0 | AH11: =AF11*AG11 -> 0 | AI11: =S11+T11 -> 0 | AJ11: =U11+V11+W11+X11+Y11+AB11 -> 0 | AK11: =AI11-AJ11 -> 0 | AL11: Junio | AN11: ='INVENTARIO INICIAL'!X11 -> 0
A12: ='Reporte Marzo 2026'!A12 -> Inventario | B12: ='INVENTARIO INICIAL'!B12 -> 0 | C12: =IF(B12=0,"",VLOOKUP(B12,Datos!$H$2:$K$39,2,FALSE)) | D12: =IF(B12=0,"",VLOOKUP(B12,Datos!$H$2:$K$39,3,FALSE)) | E12: =IF(B12=0,"",VLOOKUP(B12,Datos!$H$2:$K$39,4,FALSE)) | F12: ='INVENTARIO INICIAL'!F12 -> 0 | G12: ='INVENTARIO INICIAL'!G12 -> 0 | H12: ='INVENTARIO INICIAL'!H12 -> 0 | I12: =IF(H12=0,"",VLOOKUP(H12,Datos!$B$2:$D$908,2,FALSE)) | J12: =IF(H12=0,"",VLOOKUP(H12,Datos!$B$2:$D$908,3,FALSE)) | K12: ='INVENTARIO INICIAL'!K12 -> 0 | L12: ='INVENTARIO INICIAL'!L12 -> 0 | M12: ='INVENTARIO INICIAL'!M12 -> 0 | N12: ='INVENTARIO INICIAL'!N12 -> 0 | O12: ='INVENTARIO INICIAL'!O12 -> 0 | P12: ='INVENTARIO INICIAL'!P12 -> 0 | Q12: ='INVENTARIO INICIAL'!Q12 -> 0 | R12: ='INVENTARIO INICIAL'!R12 -> 0 | S12: ='Reporte Marzo 2026'!AF12 -> 0 | AF12: =IF(AI12>=AJ12,IF(AK12>=0,IF(AJ12>=0,AK12,"Error"))) -> 0 | AG12: ='Reporte Marzo 2026'!AG12 -> 0 | AH12: =AF12*AG12 -> 0 | AI12: =S12+T12 -> 0 | AJ12: =U12+V12+W12+X12+Y12+AB12 -> 0 | AK12: =AI12-AJ12 -> 0 | AL12: Junio | AN12: ='INVENTARIO INICIAL'!X12 -> 0
A13: ='Reporte Marzo 2026'!A13 -> Inventario | B13: ='INVENTARIO INICIAL'!B13 -> 0 | C13: =IF(B13=0,"",VLOOKUP(B13,Datos!$H$2:$K$39,2,FALSE)) | D13: =IF(B13=0,"",VLOOKUP(B13,Datos!$H$2:$K$39,3,FALSE)) | E13: =IF(B13=0,"",VLOOKUP(B13,Datos!$H$2:$K$39,4,FALSE)) | F13: ='INVENTARIO INICIAL'!F13 -> 0 | G13: ='INVENTARIO INICIAL'!G13 -> 0 | H13: ='INVENTARIO INICIAL'!H13 -> 0 | I13: =IF(H13=0,"",VLOOKUP(H13,Datos!$B$2:$D$908,2,FALSE)) | J13: =IF(H13=0,"",VLOOKUP(H13,Datos!$B$2:$D$908,3,FALSE)) | K13: ='INVENTARIO INICIAL'!K13 -> 0 | L13: ='INVENTARIO INICIAL'!L13 -> 0 | M13: ='INVENTARIO INICIAL'!M13 -> 0 | N13: ='INVENTARIO INICIAL'!N13 -> 0 | O13: ='INVENTARIO INICIAL'!O13 -> 0 | P13: ='INVENTARIO INICIAL'!P13 -> 0 | Q13: ='INVENTARIO INICIAL'!Q13 -> 0 | R13: ='INVENTARIO INICIAL'!R13 -> 0 | S13: ='Reporte Marzo 2026'!AF13 -> 0 | AF13: =IF(AI13>=AJ13,IF(AK13>=0,IF(AJ13>=0,AK13,"Error"))) -> 0 | AG13: ='Reporte Marzo 2026'!AG13 -> 0 | AH13: =AF13*AG13 -> 0 | AI13: =S13+T13 -> 0 | AJ13: =U13+V13+W13+X13+Y13+AB13 -> 0 | AK13: =AI13-AJ13 -> 0 | AL13: Junio | AN13: ='INVENTARIO INICIAL'!X13 -> 0
A14: ='Reporte Marzo 2026'!A14 -> Inventario | B14: ='INVENTARIO INICIAL'!B14 -> 0 | C14: =IF(B14=0,"",VLOOKUP(B14,Datos!$H$2:$K$39,2,FALSE)) | D14: =IF(B14=0,"",VLOOKUP(B14,Datos!$H$2:$K$39,3,FALSE)) | E14: =IF(B14=0,"",VLOOKUP(B14,Datos!$H$2:$K$39,4,FALSE)) | F14: ='INVENTARIO INICIAL'!F14 -> 0 | G14: ='INVENTARIO INICIAL'!G14 -> 0 | H14: ='INVENTARIO INICIAL'!H14 -> 0 | I14: =IF(H14=0,"",VLOOKUP(H14,Datos!$B$2:$D$908,2,FALSE)) | J14: =IF(H14=0,"",VLOOKUP(H14,Datos!$B$2:$D$908,3,FALSE)) | K14: ='INVENTARIO INICIAL'!K14 -> 0 | L14: ='INVENTARIO INICIAL'!L14 -> 0 | M14: ='INVENTARIO INICIAL'!M14 -> 0 | N14: ='INVENTARIO INICIAL'!N14 -> 0 | O14: ='INVENTARIO INICIAL'!O14 -> 0 | P14: ='INVENTARIO INICIAL'!P14 -> 0 | Q14: ='INVENTARIO INICIAL'!Q14 -> 0 | R14: ='INVENTARIO INICIAL'!R14 -> 0 | S14: ='Reporte Marzo 2026'!AF14 -> 0 | AF14: =IF(AI14>=AJ14,IF(AK14>=0,IF(AJ14>=0,AK14,"Error"))) -> 0 | AG14: ='Reporte Marzo 2026'!AG14 -> 0 | AH14: =AF14*AG14 -> 0 | AI14: =S14+T14 -> 0 | AJ14: =U14+V14+W14+X14+Y14+AB14 -> 0 | AK14: =AI14-AJ14 -> 0 | AL14: Junio | AN14: ='INVENTARIO INICIAL'!X14 -> 0
A15: ='Reporte Marzo 2026'!A15 -> Inventario | B15: ='INVENTARIO INICIAL'!B15 -> 0 | C15: =IF(B15=0,"",VLOOKUP(B15,Datos!$H$2:$K$39,2,FALSE)) | D15: =IF(B15=0,"",VLOOKUP(B15,Datos!$H$2:$K$39,3,FALSE)) | E15: =IF(B15=0,"",VLOOKUP(B15,Datos!$H$2:$K$39,4,FALSE)) | F15: ='INVENTARIO INICIAL'!F15 -> 0 | G15: ='INVENTARIO INICIAL'!G15 -> 0 | H15: ='INVENTARIO INICIAL'!H15 -> 0 | I15: =IF(H15=0,"",VLOOKUP(H15,Datos!$B$2:$D$908,2,FALSE)) | J15: =IF(H15=0,"",VLOOKUP(H15,Datos!$B$2:$D$908,3,FALSE)) | K15: ='INVENTARIO INICIAL'!K15 -> 0 | L15: ='INVENTARIO INICIAL'!L15 -> 0 | M15: ='INVENTARIO INICIAL'!M15 -> 0 | N15: ='INVENTARIO INICIAL'!N15 -> 0 | O15: ='INVENTARIO INICIAL'!O15 -> 0 | P15: ='INVENTARIO INICIAL'!P15 -> 0 | Q15: ='INVENTARIO INICIAL'!Q15 -> 0 | R15: ='INVENTARIO INICIAL'!R15 -> 0 | S15: ='Reporte Marzo 2026'!AF15 -> 0 | AF15: =IF(AI15>=AJ15,IF(AK15>=0,IF(AJ15>=0,AK15,"Error"))) -> 0 | AG15: ='Reporte Marzo 2026'!AG15 -> 0 | AH15: =AF15*AG15 -> 0 | AI15: =S15+T15 -> 0 | AJ15: =U15+V15+W15+X15+Y15+AB15 -> 0 | AK15: =AI15-AJ15 -> 0 | AL15: Junio | AN15: ='INVENTARIO INICIAL'!X15 -> 0
A16: ='Reporte Marzo 2026'!A16 -> Inventario | B16: ='INVENTARIO INICIAL'!B16 -> 0 | C16: =IF(B16=0,"",VLOOKUP(B16,Datos!$H$2:$K$39,2,FALSE)) | D16: =IF(B16=0,"",VLOOKUP(B16,Datos!$H$2:$K$39,3,FALSE)) | E16: =IF(B16=0,"",VLOOKUP(B16,Datos!$H$2:$K$39,4,FALSE)) | F16: ='INVENTARIO INICIAL'!F16 -> 0 | G16: ='INVENTARIO INICIAL'!G16 -> 0 | H16: ='INVENTARIO INICIAL'!H16 -> 0 | I16: =IF(H16=0,"",VLOOKUP(H16,Datos!$B$2:$D$908,2,FALSE)) | J16: =IF(H16=0,"",VLOOKUP(H16,Datos!$B$2:$D$908,3,FALSE)) | K16: ='INVENTARIO INICIAL'!K16 -> 0 | L16: ='INVENTARIO INICIAL'!L16 -> 0 | M16: ='INVENTARIO INICIAL'!M16 -> 0 | N16: ='INVENTARIO INICIAL'!N16 -> 0 | O16: ='INVENTARIO INICIAL'!O16 -> 0 | P16: ='INVENTARIO INICIAL'!P16 -> 0 | Q16: ='INVENTARIO INICIAL'!Q16 -> 0 | R16: ='INVENTARIO INICIAL'!R16 -> 0 | S16: ='Reporte Marzo 2026'!AF16 -> 0 | AF16: =IF(AI16>=AJ16,IF(AK16>=0,IF(AJ16>=0,AK16,"Error"))) -> 0 | AG16: ='Reporte Marzo 2026'!AG16 -> 0 | AH16: =AF16*AG16 -> 0 | AI16: =S16+T16 -> 0 | AJ16: =U16+V16+W16+X16+Y16+AB16 -> 0 | AK16: =AI16-AJ16 -> 0 | AL16: Junio | AN16: ='INVENTARIO INICIAL'!X16 -> 0
A17: ='Reporte Marzo 2026'!A17 -> Inventario | B17: ='INVENTARIO INICIAL'!B17 -> 0 | C17: =IF(B17=0,"",VLOOKUP(B17,Datos!$H$2:$K$39,2,FALSE)) | D17: =IF(B17=0,"",VLOOKUP(B17,Datos!$H$2:$K$39,3,FALSE)) | E17: =IF(B17=0,"",VLOOKUP(B17,Datos!$H$2:$K$39,4,FALSE)) | F17: ='INVENTARIO INICIAL'!F17 -> 0 | G17: ='INVENTARIO INICIAL'!G17 -> 0 | H17: ='INVENTARIO INICIAL'!H17 -> 0 | I17: =IF(H17=0,"",VLOOKUP(H17,Datos!$B$2:$D$908,2,FALSE)) | J17: =IF(H17=0,"",VLOOKUP(H17,Datos!$B$2:$D$908,3,FALSE)) | K17: ='INVENTARIO INICIAL'!K17 -> 0 | L17: ='INVENTARIO INICIAL'!L17 -> 0 | M17: ='INVENTARIO INICIAL'!M17 -> 0 | N17: ='INVENTARIO INICIAL'!N17 -> 0 | O17: ='INVENTARIO INICIAL'!O17 -> 0 | P17: ='INVENTARIO INICIAL'!P17 -> 0 | Q17: ='INVENTARIO INICIAL'!Q17 -> 0 | R17: ='INVENTARIO INICIAL'!R17 -> 0 | S17: ='Reporte Marzo 2026'!AF17 -> 0 | AF17: =IF(AI17>=AJ17,IF(AK17>=0,IF(AJ17>=0,AK17,"Error"))) -> 0 | AG17: ='Reporte Marzo 2026'!AG17 -> 0 | AH17: =AF17*AG17 -> 0 | AI17: =S17+T17 -> 0 | AJ17: =U17+V17+W17+X17+Y17+AB17 -> 0 | AK17: =AI17-AJ17 -> 0 | AL17: Junio | AN17: ='INVENTARIO INICIAL'!X17 -> 0
A18: ='Reporte Marzo 2026'!A18 -> Inventario | B18: ='INVENTARIO INICIAL'!B18 -> 0 | C18: =IF(B18=0,"",VLOOKUP(B18,Datos!$H$2:$K$39,2,FALSE)) | D18: =IF(B18=0,"",VLOOKUP(B18,Datos!$H$2:$K$39,3,FALSE)) | E18: =IF(B18=0,"",VLOOKUP(B18,Datos!$H$2:$K$39,4,FALSE)) | F18: ='INVENTARIO INICIAL'!F18 -> 0 | G18: ='INVENTARIO INICIAL'!G18 -> 0 | H18: ='INVENTARIO INICIAL'!H18 -> 0 | I18: =IF(H18=0,"",VLOOKUP(H18,Datos!$B$2:$D$908,2,FALSE)) | J18: =IF(H18=0,"",VLOOKUP(H18,Datos!$B$2:$D$908,3,FALSE)) | K18: ='INVENTARIO INICIAL'!K18 -> 0 | L18: ='INVENTARIO INICIAL'!L18 -> 0 | M18: ='INVENTARIO INICIAL'!M18 -> 0 | N18: ='INVENTARIO INICIAL'!N18 -> 0 | O18: ='INVENTARIO INICIAL'!O18 -> 0 | P18: ='INVENTARIO INICIAL'!P18 -> 0 | Q18: ='INVENTARIO INICIAL'!Q18 -> 0 | R18: ='INVENTARIO INICIAL'!R18 -> 0 | S18: ='Reporte Marzo 2026'!AF18 -> 0 | AF18: =IF(AI18>=AJ18,IF(AK18>=0,IF(AJ18>=0,AK18,"Error"))) -> 0 | AG18: ='Reporte Marzo 2026'!AG18 -> 0 | AH18: =AF18*AG18 -> 0 | AI18: =S18+T18 -> 0 | AJ18: =U18+V18+W18+X18+Y18+AB18 -> 0 | AK18: =AI18-AJ18 -> 0 | AL18: Junio | AN18: ='INVENTARIO INICIAL'!X18 -> 0
... A360: ='Reporte Marzo 2026'!A360 -> Inventario | B360: ='INVENTARIO INICIAL'!B360 -> 0 | C360: =IF(B360=0,"",VLOOKUP(B360,Datos!$H$2:$K$39,2,FALSE)) | D360: =IF(B360=0,"",VLOOKUP(B360,Datos!$H$2:$K$39,3,FALSE)) | E360: =IF(B360=0,"",VLOOKUP(B360,Datos!$H$2:$K$39,4,FALSE)) | F360: ='INVENTARIO INICIAL'!F360 -> 0 | G360: ='INVENTARIO INICIAL'!G360 -> 0 | H360: ='INVENTARIO INICIAL'!H360 -> 0 | I360: =IF(H360=0,"",VLOOKUP(H360,Datos!$B$2:$D$908,2,FALSE)) | J360: =IF(H360=0,"",VLOOKUP(H360,Datos!$B$2:$D$908,3,FALSE)) | K360: ='INVENTARIO INICIAL'!K360 -> 0 | L360: ='INVENTARIO INICIAL'!L360 -> 0 | M360: ='INVENTARIO INICIAL'!M360 -> 0 | N360: ='INVENTARIO INICIAL'!N360 -> 0 | O360: ='INVENTARIO INICIAL'!O360 -> 0 | P360: ='INVENTARIO INICIAL'!P360 -> 0 | Q360: ='INVENTARIO INICIAL'!Q360 -> 0 | R360: ='INVENTARIO INICIAL'!R360 -> 0 | S360: ='Reporte Marzo 2026'!AF360 -> 0 | AF360: =IF(AI360>=AJ360,IF(AK360>=0,IF(AJ360>=0,AK360,"Error"))) -> 0 | AG360: ='Reporte Marzo 2026'!AG360 -> 0 | AH360: =AF360*AG360 -> 0 | AI360: =S360+T360 -> 0 | AJ360: =U360+V360+W360+X360+Y360+AB360 -> 0 | AK360: =AI360-AJ360 -> 0 | AL360: Junio | AN360: ='INVENTARIO INICIAL'!X360 -> 0
A361: ='Reporte Marzo 2026'!A361 -> Ingresos | B361: ='Reporte Marzo 2026'!B361 -> 0 | C361: =IF(B361=0,"",VLOOKUP(B361,Datos!$H$2:$K$39,2,FALSE)) | D361: =IF(B361=0,"",VLOOKUP(B361,Datos!$H$2:$K$39,3,FALSE)) | E361: =IF(B361=0,"",VLOOKUP(B361,Datos!$H$2:$K$39,4,FALSE)) | F361: ='Reporte Marzo 2026'!F361 -> 0 | G361: ='Reporte Marzo 2026'!G361 -> 0 | H361: ='Reporte Marzo 2026'!H361 -> 0 | I361: =IF(H361=0,"",VLOOKUP(H361,Datos!$B$2:$D$891,2,FALSE)) | J361: =IF(H361=0,"",VLOOKUP(H361,Datos!$B$2:$D$891,3,FALSE)) | K361: ='Reporte Marzo 2026'!K361 -> 0 | L361: ='Reporte Marzo 2026'!L361 -> 0 | M361: ='Reporte Marzo 2026'!M361 -> 0 | N361: ='Reporte Marzo 2026'!N361 -> 0 | O361: ='Reporte Marzo 2026'!O361 -> 0 | P361: ='Reporte Marzo 2026'!P361 -> 0 | Q361: ='Reporte Marzo 2026'!Q361 -> 0 | R361: ='Reporte Marzo 2026'!R361 -> 0 | S361: ='Reporte Marzo 2026'!AF361 -> 0 | AF361: =IF(AI361>=AJ361,IF(AK361>=0,IF(AJ361>=0,AK361,"Error"))) -> 0 | AG361: ='Reporte Marzo 2026'!AG361 -> 0 | AH361: =AF361*AG361 -> 0 | AI361: =S361+T361 -> 0 | AJ361: =U361+V361+W361+X361+Y361+AB361 -> 0 | AK361: =AI361-AJ361 -> 0 | AL361: Junio | AN361: ='Reporte Marzo 2026'!AN361 -> 0
A362: ='Reporte Marzo 2026'!A362 -> Ingresos | B362: ='Reporte Marzo 2026'!B362 -> 0 | C362: =IF(B362=0,"",VLOOKUP(B362,Datos!$H$2:$K$39,2,FALSE)) | D362: =IF(B362=0,"",VLOOKUP(B362,Datos!$H$2:$K$39,3,FALSE)) | E362: =IF(B362=0,"",VLOOKUP(B362,Datos!$H$2:$K$39,4,FALSE)) | F362: ='Reporte Marzo 2026'!F362 -> 0 | G362: ='Reporte Marzo 2026'!G362 -> 0 | H362: ='Reporte Marzo 2026'!H362 -> 0 | I362: =IF(H362=0,"",VLOOKUP(H362,Datos!$B$2:$D$891,2,FALSE)) | J362: =IF(H362=0,"",VLOOKUP(H362,Datos!$B$2:$D$891,3,FALSE)) | K362: ='Reporte Marzo 2026'!K362 -> 0 | L362: ='Reporte Marzo 2026'!L362 -> 0 | M362: ='Reporte Marzo 2026'!M362 -> 0 | N362: ='Reporte Marzo 2026'!N362 -> 0 | O362: ='Reporte Marzo 2026'!O362 -> 0 | P362: ='Reporte Marzo 2026'!P362 -> 0 | Q362: ='Reporte Marzo 2026'!Q362 -> 0 | R362: ='Reporte Marzo 2026'!R362 -> 0 | S362: ='Reporte Marzo 2026'!AF362 -> 0 | AF362: =IF(AI362>=AJ362,IF(AK362>=0,IF(AJ362>=0,AK362,"Error"))) -> 0 | AG362: ='Reporte Marzo 2026'!AG362 -> 0 | AH362: =AF362*AG362 -> 0 | AI362: =S362+T362 -> 0 | AJ362: =U362+V362+W362+X362+Y362+AB362 -> 0 | AK362: =AI362-AJ362 -> 0 | AL362: Junio | AN362: ='Reporte Marzo 2026'!AN362 -> 0
A363: ='Reporte Marzo 2026'!A363 -> Ingresos | B363: ='Reporte Marzo 2026'!B363 -> 0 | C363: =IF(B363=0,"",VLOOKUP(B363,Datos!$H$2:$K$39,2,FALSE)) | D363: =IF(B363=0,"",VLOOKUP(B363,Datos!$H$2:$K$39,3,FALSE)) | E363: =IF(B363=0,"",VLOOKUP(B363,Datos!$H$2:$K$39,4,FALSE)) | F363: ='Reporte Marzo 2026'!F363 -> 0 | G363: ='Reporte Marzo 2026'!G363 -> 0 | H363: ='Reporte Marzo 2026'!H363 -> 0 | I363: =IF(H363=0,"",VLOOKUP(H363,Datos!$B$2:$D$891,2,FALSE)) | J363: =IF(H363=0,"",VLOOKUP(H363,Datos!$B$2:$D$891,3,FALSE)) | K363: ='Reporte Marzo 2026'!K363 -> 0 | L363: ='Reporte Marzo 2026'!L363 -> 0 | M363: ='Reporte Marzo 2026'!M363 -> 0 | N363: ='Reporte Marzo 2026'!N363 -> 0 | O363: ='Reporte Marzo 2026'!O363 -> 0 | P363: ='Reporte Marzo 2026'!P363 -> 0 | Q363: ='Reporte Marzo 2026'!Q363 -> 0 | R363: ='Reporte Marzo 2026'!R363 -> 0 | S363: ='Reporte Marzo 2026'!AF363 -> 0 | AF363: =IF(AI363>=AJ363,IF(AK363>=0,IF(AJ363>=0,AK363,"Error"))) -> 0 | AG363: ='Reporte Marzo 2026'!AG363 -> 0 | AH363: =AF363*AG363 -> 0 | AI363: =S363+T363 -> 0 | AJ363: =U363+V363+W363+X363+Y363+AB363 -> 0 | AK363: =AI363-AJ363 -> 0 | AL363: Junio | AN363: ='Reporte Marzo 2026'!AN363 -> 0
A364: ='Reporte Marzo 2026'!A364 -> Ingresos | B364: ='Reporte Marzo 2026'!B364 -> 0 | C364: =IF(B364=0,"",VLOOKUP(B364,Datos!$H$2:$K$39,2,FALSE)) | D364: =IF(B364=0,"",VLOOKUP(B364,Datos!$H$2:$K$39,3,FALSE)) | E364: =IF(B364=0,"",VLOOKUP(B364,Datos!$H$2:$K$39,4,FALSE)) | F364: ='Reporte Marzo 2026'!F364 -> 0 | G364: ='Reporte Marzo 2026'!G364 -> 0 | H364: ='Reporte Marzo 2026'!H364 -> 0 | I364: =IF(H364=0,"",VLOOKUP(H364,Datos!$B$2:$D$891,2,FALSE)) | J364: =IF(H364=0,"",VLOOKUP(H364,Datos!$B$2:$D$891,3,FALSE)) | K364: ='Reporte Marzo 2026'!K364 -> 0 | L364: ='Reporte Marzo 2026'!L364 -> 0 | M364: ='Reporte Marzo 2026'!M364 -> 0 | N364: ='Reporte Marzo 2026'!N364 -> 0 | O364: ='Reporte Marzo 2026'!O364 -> 0 | P364: ='Reporte Marzo 2026'!P364 -> 0 | Q364: ='Reporte Marzo 2026'!Q364 -> 0 | R364: ='Reporte Marzo 2026'!R364 -> 0 | S364: ='Reporte Marzo 2026'!AF364 -> 0 | AF364: =IF(AI364>=AJ364,IF(AK364>=0,IF(AJ364>=0,AK364,"Error"))) -> 0 | AG364: ='Reporte Marzo 2026'!AG364 -> 0 | AH364: =AF364*AG364 -> 0 | AI364: =S364+T364 -> 0 | AJ364: =U364+V364+W364+X364+Y364+AB364 -> 0 | AK364: =AI364-AJ364 -> 0 | AL364: Junio | AN364: ='Reporte Marzo 2026'!AN364 -> 0
A365: ='Reporte Marzo 2026'!A365 -> Ingresos | B365: ='Reporte Marzo 2026'!B365 -> 0 | C365: =IF(B365=0,"",VLOOKUP(B365,Datos!$H$2:$K$39,2,FALSE)) | D365: =IF(B365=0,"",VLOOKUP(B365,Datos!$H$2:$K$39,3,FALSE)) | E365: =IF(B365=0,"",VLOOKUP(B365,Datos!$H$2:$K$39,4,FALSE)) | F365: ='Reporte Marzo 2026'!F365 -> 0 | G365: ='Reporte Marzo 2026'!G365 -> 0 | H365: ='Reporte Marzo 2026'!H365 -> 0 | I365: =IF(H365=0,"",VLOOKUP(H365,Datos!$B$2:$D$891,2,FALSE)) | J365: =IF(H365=0,"",VLOOKUP(H365,Datos!$B$2:$D$891,3,FALSE)) | K365: ='Reporte Marzo 2026'!K365 -> 0 | L365: ='Reporte Marzo 2026'!L365 -> 0 | M365: ='Reporte Marzo 2026'!M365 -> 0 | N365: ='Reporte Marzo 2026'!N365 -> 0 | O365: ='Reporte Marzo 2026'!O365 -> 0 | P365: ='Reporte Marzo 2026'!P365 -> 0 | Q365: ='Reporte Marzo 2026'!Q365 -> 0 | R365: ='Reporte Marzo 2026'!R365 -> 0 | S365: ='Reporte Marzo 2026'!AF365 -> 0 | AF365: =IF(AI365>=AJ365,IF(AK365>=0,IF(AJ365>=0,AK365,"Error"))) -> 0 | AG365: ='Reporte Marzo 2026'!AG365 -> 0 | AH365: =AF365*AG365 -> 0 | AI365: =S365+T365 -> 0 | AJ365: =U365+V365+W365+X365+Y365+AB365 -> 0 | AK365: =AI365-AJ365 -> 0 | AL365: Junio | AN365: ='Reporte Marzo 2026'!AN365 -> 0
A366: ='Reporte Marzo 2026'!A366 -> Ingresos | B366: ='Reporte Marzo 2026'!B366 -> 0 | C366: =IF(B366=0,"",VLOOKUP(B366,Datos!$H$2:$K$39,2,FALSE)) | D366: =IF(B366=0,"",VLOOKUP(B366,Datos!$H$2:$K$39,3,FALSE)) | E366: =IF(B366=0,"",VLOOKUP(B366,Datos!$H$2:$K$39,4,FALSE)) | F366: ='Reporte Marzo 2026'!F366 -> 0 | G366: ='Reporte Marzo 2026'!G366 -> 0 | H366: ='Reporte Marzo 2026'!H366 -> 0 | I366: =IF(H366=0,"",VLOOKUP(H366,Datos!$B$2:$D$891,2,FALSE)) | J366: =IF(H366=0,"",VLOOKUP(H366,Datos!$B$2:$D$891,3,FALSE)) | K366: ='Reporte Marzo 2026'!K366 -> 0 | L366: ='Reporte Marzo 2026'!L366 -> 0 | M366: ='Reporte Marzo 2026'!M366 -> 0 | N366: ='Reporte Marzo 2026'!N366 -> 0 | O366: ='Reporte Marzo 2026'!O366 -> 0 | P366: ='Reporte Marzo 2026'!P366 -> 0 | Q366: ='Reporte Marzo 2026'!Q366 -> 0 | R366: ='Reporte Marzo 2026'!R366 -> 0 | S366: ='Reporte Marzo 2026'!AF366 -> 0 | AF366: =IF(AI366>=AJ366,IF(AK366>=0,IF(AJ366>=0,AK366,"Error"))) -> 0 | AG366: ='Reporte Marzo 2026'!AG366 -> 0 | AH366: =AF366*AG366 -> 0 | AI366: =S366+T366 -> 0 | AJ366: =U366+V366+W366+X366+Y366+AB366 -> 0 | AK366: =AI366-AJ366 -> 0 | AL366: Junio | AN366: ='Reporte Marzo 2026'!AN366 -> 0
A367: ='Reporte Marzo 2026'!A367 -> Ingresos | B367: ='Reporte Marzo 2026'!B367 -> 0 | C367: =IF(B367=0,"",VLOOKUP(B367,Datos!$H$2:$K$39,2,FALSE)) | D367: =IF(B367=0,"",VLOOKUP(B367,Datos!$H$2:$K$39,3,FALSE)) | E367: =IF(B367=0,"",VLOOKUP(B367,Datos!$H$2:$K$39,4,FALSE)) | F367: ='Reporte Marzo 2026'!F367 -> 0 | G367: ='Reporte Marzo 2026'!G367 -> 0 | H367: ='Reporte Marzo 2026'!H367 -> 0 | I367: =IF(H367=0,"",VLOOKUP(H367,Datos!$B$2:$D$891,2,FALSE)) | J367: =IF(H367=0,"",VLOOKUP(H367,Datos!$B$2:$D$891,3,FALSE)) | K367: ='Reporte Marzo 2026'!K367 -> 0 | L367: ='Reporte Marzo 2026'!L367 -> 0 | M367: ='Reporte Marzo 2026'!M367 -> 0 | N367: ='Reporte Marzo 2026'!N367 -> 0 | O367: ='Reporte Marzo 2026'!O367 -> 0 | P367: ='Reporte Marzo 2026'!P367 -> 0 | Q367: ='Reporte Marzo 2026'!Q367 -> 0 | R367: ='Reporte Marzo 2026'!R367 -> 0 | S367: ='Reporte Marzo 2026'!AF367 -> 0 | AF367: =IF(AI367>=AJ367,IF(AK367>=0,IF(AJ367>=0,AK367,"Error"))) -> 0 | AG367: ='Reporte Marzo 2026'!AG367 -> 0 | AH367: =AF367*AG367 -> 0 | AI367: =S367+T367 -> 0 | AJ367: =U367+V367+W367+X367+Y367+AB367 -> 0 | AK367: =AI367-AJ367 -> 0 | AL367: Junio | AN367: ='Reporte Marzo 2026'!AN367 -> 0
A368: ='Reporte Marzo 2026'!A368 -> Ingresos | B368: ='Reporte Marzo 2026'!B368 -> 0 | C368: =IF(B368=0,"",VLOOKUP(B368,Datos!$H$2:$K$39,2,FALSE)) | D368: =IF(B368=0,"",VLOOKUP(B368,Datos!$H$2:$K$39,3,FALSE)) | E368: =IF(B368=0,"",VLOOKUP(B368,Datos!$H$2:$K$39,4,FALSE)) | F368: ='Reporte Marzo 2026'!F368 -> 0 | G368: ='Reporte Marzo 2026'!G368 -> 0 | H368: ='Reporte Marzo 2026'!H368 -> 0 | I368: =IF(H368=0,"",VLOOKUP(H368,Datos!$B$2:$D$891,2,FALSE)) | J368: =IF(H368=0,"",VLOOKUP(H368,Datos!$B$2:$D$891,3,FALSE)) | K368: ='Reporte Marzo 2026'!K368 -> 0 | L368: ='Reporte Marzo 2026'!L368 -> 0 | M368: ='Reporte Marzo 2026'!M368 -> 0 | N368: ='Reporte Marzo 2026'!N368 -> 0 | O368: ='Reporte Marzo 2026'!O368 -> 0 | P368: ='Reporte Marzo 2026'!P368 -> 0 | Q368: ='Reporte Marzo 2026'!Q368 -> 0 | R368: ='Reporte Marzo 2026'!R368 -> 0 | S368: ='Reporte Marzo 2026'!AF368 -> 0 | AF368: =IF(AI368>=AJ368,IF(AK368>=0,IF(AJ368>=0,AK368,"Error"))) -> 0 | AG368: ='Reporte Marzo 2026'!AG368 -> 0 | AH368: =AF368*AG368 -> 0 | AI368: =S368+T368 -> 0 | AJ368: =U368+V368+W368+X368+Y368+AB368 -> 0 | AK368: =AI368-AJ368 -> 0 | AL368: Junio | AN368: ='Reporte Marzo 2026'!AN368 -> 0
A369: ='Reporte Marzo 2026'!A369 -> Ingresos | B369: ='Reporte Marzo 2026'!B369 -> 0 | C369: =IF(B369=0,"",VLOOKUP(B369,Datos!$H$2:$K$39,2,FALSE)) | D369: =IF(B369=0,"",VLOOKUP(B369,Datos!$H$2:$K$39,3,FALSE)) | E369: =IF(B369=0,"",VLOOKUP(B369,Datos!$H$2:$K$39,4,FALSE)) | F369: ='Reporte Marzo 2026'!F369 -> 0 | G369: ='Reporte Marzo 2026'!G369 -> 0 | H369: ='Reporte Marzo 2026'!H369 -> 0 | I369: =IF(H369=0,"",VLOOKUP(H369,Datos!$B$2:$D$891,2,FALSE)) | J369: =IF(H369=0,"",VLOOKUP(H369,Datos!$B$2:$D$891,3,FALSE)) | K369: ='Reporte Marzo 2026'!K369 -> 0 | L369: ='Reporte Marzo 2026'!L369 -> 0 | M369: ='Reporte Marzo 2026'!M369 -> 0 | N369: ='Reporte Marzo 2026'!N369 -> 0 | O369: ='Reporte Marzo 2026'!O369 -> 0 | P369: ='Reporte Marzo 2026'!P369 -> 0 | Q369: ='Reporte Marzo 2026'!Q369 -> 0 | R369: ='Reporte Marzo 2026'!R369 -> 0 | S369: ='Reporte Marzo 2026'!AF369 -> 0 | AF369: =IF(AI369>=AJ369,IF(AK369>=0,IF(AJ369>=0,AK369,"Error"))) -> 0 | AG369: ='Reporte Marzo 2026'!AG369 -> 0 | AH369: =AF369*AG369 -> 0 | AI369: =S369+T369 -> 0 | AJ369: =U369+V369+W369+X369+Y369+AB369 -> 0 | AK369: =AI369-AJ369 -> 0 | AL369: Junio | AN369: ='Reporte Marzo 2026'!AN369 -> 0
A370: ='Reporte Marzo 2026'!A370 -> Ingresos | B370: ='Reporte Marzo 2026'!B370 -> 0 | C370: =IF(B370=0,"",VLOOKUP(B370,Datos!$H$2:$K$39,2,FALSE)) | D370: =IF(B370=0,"",VLOOKUP(B370,Datos!$H$2:$K$39,3,FALSE)) | E370: =IF(B370=0,"",VLOOKUP(B370,Datos!$H$2:$K$39,4,FALSE)) | F370: ='Reporte Marzo 2026'!F370 -> 0 | G370: ='Reporte Marzo 2026'!G370 -> 0 | H370: ='Reporte Marzo 2026'!H370 -> 0 | I370: =IF(H370=0,"",VLOOKUP(H370,Datos!$B$2:$D$891,2,FALSE)) | J370: =IF(H370=0,"",VLOOKUP(H370,Datos!$B$2:$D$891,3,FALSE)) | K370: ='Reporte Marzo 2026'!K370 -> 0 | L370: ='Reporte Marzo 2026'!L370 -> 0 | M370: ='Reporte Marzo 2026'!M370 -> 0 | N370: ='Reporte Marzo 2026'!N370 -> 0 | O370: ='Reporte Marzo 2026'!O370 -> 0 | P370: ='Reporte Marzo 2026'!P370 -> 0 | Q370: ='Reporte Marzo 2026'!Q370 -> 0 | R370: ='Reporte Marzo 2026'!R370 -> 0 | S370: ='Reporte Marzo 2026'!AF370 -> 0 | AF370: =IF(AI370>=AJ370,IF(AK370>=0,IF(AJ370>=0,AK370,"Error"))) -> 0 | AG370: ='Reporte Marzo 2026'!AG370 -> 0 | AH370: =AF370*AG370 -> 0 | AI370: =S370+T370 -> 0 | AJ370: =U370+V370+W370+X370+Y370+AB370 -> 0 | AK370: =AI370-AJ370 -> 0 | AL370: Junio | AN370: ='Reporte Marzo 2026'!AN370 -> 0
A371: ='Reporte Marzo 2026'!A371 -> Ingresos | B371: ='Reporte Marzo 2026'!B371 -> 0 | C371: =IF(B371=0,"",VLOOKUP(B371,Datos!$H$2:$K$39,2,FALSE)) | D371: =IF(B371=0,"",VLOOKUP(B371,Datos!$H$2:$K$39,3,FALSE)) | E371: =IF(B371=0,"",VLOOKUP(B371,Datos!$H$2:$K$39,4,FALSE)) | F371: ='Reporte Marzo 2026'!F371 -> 0 | G371: ='Reporte Marzo 2026'!G371 -> 0 | H371: ='Reporte Marzo 2026'!H371 -> 0 | I371: =IF(H371=0,"",VLOOKUP(H371,Datos!$B$2:$D$891,2,FALSE)) | J371: =IF(H371=0,"",VLOOKUP(H371,Datos!$B$2:$D$891,3,FALSE)) | K371: ='Reporte Marzo 2026'!K371 -> 0 | L371: ='Reporte Marzo 2026'!L371 -> 0 | M371: ='Reporte Marzo 2026'!M371 -> 0 | N371: ='Reporte Marzo 2026'!N371 -> 0 | O371: ='Reporte Marzo 2026'!O371 -> 0 | P371: ='Reporte Marzo 2026'!P371 -> 0 | Q371: ='Reporte Marzo 2026'!Q371 -> 0 | R371: ='Reporte Marzo 2026'!R371 -> 0 | S371: ='Reporte Marzo 2026'!AF371 -> 0 | AF371: =IF(AI371>=AJ371,IF(AK371>=0,IF(AJ371>=0,AK371,"Error"))) -> 0 | AG371: ='Reporte Marzo 2026'!AG371 -> 0 | AH371: =AF371*AG371 -> 0 | AI371: =S371+T371 -> 0 | AJ371: =U371+V371+W371+X371+Y371+AB371 -> 0 | AK371: =AI371-AJ371 -> 0 | AL371: Junio | AN371: ='Reporte Marzo 2026'!AN371 -> 0
A372: ='Reporte Marzo 2026'!A372 -> Ingresos | B372: ='Reporte Marzo 2026'!B372 -> 0 | C372: =IF(B372=0,"",VLOOKUP(B372,Datos!$H$2:$K$39,2,FALSE)) | D372: =IF(B372=0,"",VLOOKUP(B372,Datos!$H$2:$K$39,3,FALSE)) | E372: =IF(B372=0,"",VLOOKUP(B372,Datos!$H$2:$K$39,4,FALSE)) | F372: ='Reporte Marzo 2026'!F372 -> 0 | G372: ='Reporte Marzo 2026'!G372 -> 0 | H372: ='Reporte Marzo 2026'!H372 -> 0 | I372: =IF(H372=0,"",VLOOKUP(H372,Datos!$B$2:$D$891,2,FALSE)) | J372: =IF(H372=0,"",VLOOKUP(H372,Datos!$B$2:$D$891,3,FALSE)) | K372: ='Reporte Marzo 2026'!K372 -> 0 | L372: ='Reporte Marzo 2026'!L372 -> 0 | M372: ='Reporte Marzo 2026'!M372 -> 0 | N372: ='Reporte Marzo 2026'!N372 -> 0 | O372: ='Reporte Marzo 2026'!O372 -> 0 | P372: ='Reporte Marzo 2026'!P372 -> 0 | Q372: ='Reporte Marzo 2026'!Q372 -> 0 | R372: ='Reporte Marzo 2026'!R372 -> 0 | S372: ='Reporte Marzo 2026'!AF372 -> 0 | AF372: =IF(AI372>=AJ372,IF(AK372>=0,IF(AJ372>=0,AK372,"Error"))) -> 0 | AG372: ='Reporte Marzo 2026'!AG372 -> 0 | AH372: =AF372*AG372 -> 0 | AI372: =S372+T372 -> 0 | AJ372: =U372+V372+W372+X372+Y372+AB372 -> 0 | AK372: =AI372-AJ372 -> 0 | AL372: Junio | AN372: ='Reporte Marzo 2026'!AN372 -> 0
... A490: ='Reporte Marzo 2026'!A490 -> Ingresos | B490: ='Reporte Marzo 2026'!B490 -> 0 | C490: =IF(B490=0,"",VLOOKUP(B490,Datos!$H$2:$K$39,2,FALSE)) | D490: =IF(B490=0,"",VLOOKUP(B490,Datos!$H$2:$K$39,3,FALSE)) | E490: =IF(B490=0,"",VLOOKUP(B490,Datos!$H$2:$K$39,4,FALSE)) | F490: ='Reporte Marzo 2026'!F490 -> 0 | G490: ='Reporte Marzo 2026'!G490 -> 0 | H490: ='Reporte Marzo 2026'!H490 -> 0 | I490: =IF(H490=0,"",VLOOKUP(H490,Datos!$B$2:$D$891,2,FALSE)) | J490: =IF(H490=0,"",VLOOKUP(H490,Datos!$B$2:$D$891,3,FALSE)) | K490: ='Reporte Marzo 2026'!K490 -> 0 | L490: ='Reporte Marzo 2026'!L490 -> 0 | M490: ='Reporte Marzo 2026'!M490 -> 0 | N490: ='Reporte Marzo 2026'!N490 -> 0 | O490: ='Reporte Marzo 2026'!O490 -> 0 | P490: ='Reporte Marzo 2026'!P490 -> 0 | Q490: ='Reporte Marzo 2026'!Q490 -> 0 | R490: ='Reporte Marzo 2026'!R490 -> 0 | S490: ='Reporte Marzo 2026'!AF490 -> 0 | AF490: =IF(AI490>=AJ490,IF(AK490>=0,IF(AJ490>=0,AK490,"Error"))) -> 0 | AG490: ='Reporte Marzo 2026'!AG490 -> 0 | AH490: =AF490*AG490 -> 0 | AI490: =S490+T490 -> 0 | AJ490: =U490+V490+W490+X490+Y490+AB490 -> 0 | AK490: =AI490-AJ490 -> 0 | AL490: Junio | AN490: ='Reporte Marzo 2026'!AN490 -> 0
A491: TOTAL JUNIO | R491: TOTAL | S491: =SUM(S7:S490) -> 0 | T491: =SUM(T7:T490) -> 0 | U491: =SUM(U7:U490) -> 0 | V491: =SUM(V7:V490) -> 0 | W491: =SUM(W7:W490) -> 0 | X491: =SUM(X7:X490) -> 0 | Y491: =SUM(Y7:Y490) -> 0 | AB491: =SUM(AB7:AB490) -> 0 | AF491: =SUM(AF7:AF490) -> 0 | AH491: =SUM(AH7:AH490) -> 0

Sheet Reporte Septiembre 2026
B1: Control Inventario de Plantas SIGI GBCC 8 | 2026
B2: Viveros, centros de acopio y acondicionamiento CONAF
B3: Reporte Septiembre 2026
T4: INGRESOS Y EGRESOS DE PLANTAS EN EL TERCVER TRIMESTRE (JULIO A SEPTIEMBRE)
A5: ANTECEDENTES DEL VIVERO | H5: ANTECEDENTES DE LA ESPECIE | T5: N° DE PLANTAS NUEVAS | U5: N° DE PLANTAS ENTREGADAS Y/O VENDIDAS | X5: Movimientos Internos (Cambios Rango de Altura o Contenedor) | Y5: TRASLADOS INTERNOS A OTRAS UNIDADES CONAF | AB5: BAJA DE PLANTAS DE INVENTARIO | AF5: STOCK | AG5: VALORIZACIÓN
A6: Ítems | B6: Unidad Productiva | C6: Unidad Administrativa | D6: Provincia | E6: Comuna | F6: Encargado | G6: Teléfono de Contacto | H6: Nombre Científico | I6: Nombre Común | J6: Origen | K6: Fuente de Abastecimiento | L6: Destino de la Planta | M6: Tipo de Reproducción | N6: Tipo de Contenedor | O6: Fecha Ingreso a Inventario (Día/Mes/Año) | P6: Tiempo de Viverización (años) | Q6: Rango de Altura | R6: Sectores del Vivero | S6: N° Total Plantas Control Inventario Junio 2026 | T6: N° Plantas NUEVAS Ingresadas a Inventario | U6: N° Entregas por Difusión | V6: N° Entregas a Programas | W6: N° Plantas Venta | X6: N° Plantas (M.I.) | Y6: N° Plantas Trasladadas | Z6: Unidades Recepción de Traslado | AA6: N° de Documento, Factura o Guía de Despacho | AB6: N° Plantas de Baja | AC6: Causas | AD6: N° Resolución | AE6: Fecha de Resolución | AF6: N° TOTAL DE PLANTAS EN INVENTARIO SEPTIEMBRE 2026 | AG6: Valor Neto ($) por planta | AH6: Valor Total ($) por lote | AI6: Ingresos | AJ6: Egresos | AK6: stock Septiembre | AL6: MES REPORTE | AN6: Código de planta para Guía de Despacho
A7: ='Reporte Junio 2026'!A7 -> Inventario | B7: ='INVENTARIO INICIAL'!B7 -> 0 | C7: =IF(B7=0,"",VLOOKUP(B7,Datos!$H$2:$K$39,2,FALSE)) | D7: =IF(B7=0,"",VLOOKUP(B7,Datos!$H$2:$K$39,3,FALSE)) | E7: =IF(B7=0,"",VLOOKUP(B7,Datos!$H$2:$K$39,4,FALSE)) | F7: ='INVENTARIO INICIAL'!F7 -> 0 | G7: ='INVENTARIO INICIAL'!G7 -> 0 | H7: ='INVENTARIO INICIAL'!H7 -> 0 | I7: =IF(H7=0,"",VLOOKUP(H7,Datos!$B$2:$D$908,2,FALSE)) | J7: =IF(H7=0,"",VLOOKUP(H7,Datos!$B$2:$D$908,3,FALSE)) | K7: ='INVENTARIO INICIAL'!K7 -> 0 | L7: ='INVENTARIO INICIAL'!L7 -> 0 | M7: ='INVENTARIO INICIAL'!M7 -> 0 | N7: ='INVENTARIO INICIAL'!N7 -> 0 | O7: ='INVENTARIO INICIAL'!O7 -> 0 | P7: ='INVENTARIO INICIAL'!P7 -> 0 | Q7: ='INVENTARIO INICIAL'!Q7 -> 0 | R7: ='INVENTARIO INICIAL'!R7 -> 0 | S7: ='Reporte Junio 2026'!AF7 -> 0 | AF7: =IF(AI7>=AJ7,IF(AK7>=0,IF(AJ7>=0,AK7,"Error"))) -> 0 | AG7: ='Reporte Junio 2026'!AG7 -> 0 | AH7: =AF7*AG7 -> 0 | AI7: =S7+T7 -> 0 | AJ7: =U7+V7+W7+X7+Y7+AB7 -> 0 | AK7: =AI7-AJ7 -> 0 | AL7: Septiembre | AN7: ='INVENTARIO INICIAL'!X7 -> 0
A8: ='Reporte Junio 2026'!A8 -> Inventario | B8: ='INVENTARIO INICIAL'!B8 -> 0 | C8: =IF(B8=0,"",VLOOKUP(B8,Datos!$H$2:$K$39,2,FALSE)) | D8: =IF(B8=0,"",VLOOKUP(B8,Datos!$H$2:$K$39,3,FALSE)) | E8: =IF(B8=0,"",VLOOKUP(B8,Datos!$H$2:$K$39,4,FALSE)) | F8: ='INVENTARIO INICIAL'!F8 -> 0 | G8: ='INVENTARIO INICIAL'!G8 -> 0 | H8: ='INVENTARIO INICIAL'!H8 -> 0 | I8: =IF(H8=0,"",VLOOKUP(H8,Datos!$B$2:$D$908,2,FALSE)) | J8: =IF(H8=0,"",VLOOKUP(H8,Datos!$B$2:$D$908,3,FALSE)) | K8: ='INVENTARIO INICIAL'!K8 -> 0 | L8: ='INVENTARIO INICIAL'!L8 -> 0 | M8: ='INVENTARIO INICIAL'!M8 -> 0 | N8: ='INVENTARIO INICIAL'!N8 -> 0 | O8: ='INVENTARIO INICIAL'!O8 -> 0 | P8: ='INVENTARIO INICIAL'!P8 -> 0 | Q8: ='INVENTARIO INICIAL'!Q8 -> 0 | R8: ='INVENTARIO INICIAL'!R8 -> 0 | S8: ='Reporte Junio 2026'!AF8 -> 0 | AF8: =IF(AI8>=AJ8,IF(AK8>=0,IF(AJ8>=0,AK8,"Error"))) -> 0 | AG8: ='Reporte Junio 2026'!AG8 -> 0 | AH8: =AF8*AG8 -> 0 | AI8: =S8+T8 -> 0 | AJ8: =U8+V8+W8+X8+Y8+AB8 -> 0 | AK8: =AI8-AJ8 -> 0 | AL8: Septiembre | AN8: ='INVENTARIO INICIAL'!X8 -> 0
A9: ='Reporte Junio 2026'!A9 -> Inventario | B9: ='INVENTARIO INICIAL'!B9 -> 0 | C9: =IF(B9=0,"",VLOOKUP(B9,Datos!$H$2:$K$39,2,FALSE)) | D9: =IF(B9=0,"",VLOOKUP(B9,Datos!$H$2:$K$39,3,FALSE)) | E9: =IF(B9=0,"",VLOOKUP(B9,Datos!$H$2:$K$39,4,FALSE)) | F9: ='INVENTARIO INICIAL'!F9 -> 0 | G9: ='INVENTARIO INICIAL'!G9 -> 0 | H9: ='INVENTARIO INICIAL'!H9 -> 0 | I9: =IF(H9=0,"",VLOOKUP(H9,Datos!$B$2:$D$908,2,FALSE)) | J9: =IF(H9=0,"",VLOOKUP(H9,Datos!$B$2:$D$908,3,FALSE)) | K9: ='INVENTARIO INICIAL'!K9 -> 0 | L9: ='INVENTARIO INICIAL'!L9 -> 0 | M9: ='INVENTARIO INICIAL'!M9 -> 0 | N9: ='INVENTARIO INICIAL'!N9 -> 0 | O9: ='INVENTARIO INICIAL'!O9 -> 0 | P9: ='INVENTARIO INICIAL'!P9 -> 0 | Q9: ='INVENTARIO INICIAL'!Q9 -> 0 | R9: ='INVENTARIO INICIAL'!R9 -> 0 | S9: ='Reporte Junio 2026'!AF9 -> 0 | AF9: =IF(AI9>=AJ9,IF(AK9>=0,IF(AJ9>=0,AK9,"Error"))) -> 0 | AG9: ='Reporte Junio 2026'!AG9 -> 0 | AH9: =AF9*AG9 -> 0 | AI9: =S9+T9 -> 0 | AJ9: =U9+V9+W9+X9+Y9+AB9 -> 0 | AK9: =AI9-AJ9 -> 0 | AL9: Septiembre | AN9: ='INVENTARIO INICIAL'!X9 -> 0
A10: ='Reporte Junio 2026'!A10 -> Inventario | B10: ='INVENTARIO INICIAL'!B10 -> 0 | C10: =IF(B10=0,"",VLOOKUP(B10,Datos!$H$2:$K$39,2,FALSE)) | D10: =IF(B10=0,"",VLOOKUP(B10,Datos!$H$2:$K$39,3,FALSE)) | E10: =IF(B10=0,"",VLOOKUP(B10,Datos!$H$2:$K$39,4,FALSE)) | F10: ='INVENTARIO INICIAL'!F10 -> 0 | G10: ='INVENTARIO INICIAL'!G10 -> 0 | H10: ='INVENTARIO INICIAL'!H10 -> 0 | I10: =IF(H10=0,"",VLOOKUP(H10,Datos!$B$2:$D$908,2,FALSE)) | J10: =IF(H10=0,"",VLOOKUP(H10,Datos!$B$2:$D$908,3,FALSE)) | K10: ='INVENTARIO INICIAL'!K10 -> 0 | L10: ='INVENTARIO INICIAL'!L10 -> 0 | M10: ='INVENTARIO INICIAL'!M10 -> 0 | N10: ='INVENTARIO INICIAL'!N10 -> 0 | O10: ='INVENTARIO INICIAL'!O10 -> 0 | P10: ='INVENTARIO INICIAL'!P10 -> 0 | Q10: ='INVENTARIO INICIAL'!Q10 -> 0 | R10: ='INVENTARIO INICIAL'!R10 -> 0 | S10: ='Reporte Junio 2026'!AF10 -> 0 | AF10: =IF(AI10>=AJ10,IF(AK10>=0,IF(AJ10>=0,AK10,"Error"))) -> 0 | AG10: ='Reporte Junio 2026'!AG10 -> 0 | AH10: =AF10*AG10 -> 0 | AI10: =S10+T10 -> 0 | AJ10: =U10+V10+W10+X10+Y10+AB10 -> 0 | AK10: =AI10-AJ10 -> 0 | AL10: Septiembre | AN10: ='INVENTARIO INICIAL'!X10 -> 0
A11: ='Reporte Junio 2026'!A11 -> Inventario | B11: ='INVENTARIO INICIAL'!B11 -> 0 | C11: =IF(B11=0,"",VLOOKUP(B11,Datos!$H$2:$K$39,2,FALSE)) | D11: =IF(B11=0,"",VLOOKUP(B11,Datos!$H$2:$K$39,3,FALSE)) | E11: =IF(B11=0,"",VLOOKUP(B11,Datos!$H$2:$K$39,4,FALSE)) | F11: ='INVENTARIO INICIAL'!F11 -> 0 | G11: ='INVENTARIO INICIAL'!G11 -> 0 | H11: ='INVENTARIO INICIAL'!H11 -> 0 | I11: =IF(H11=0,"",VLOOKUP(H11,Datos!$B$2:$D$908,2,FALSE)) | J11: =IF(H11=0,"",VLOOKUP(H11,Datos!$B$2:$D$908,3,FALSE)) | K11: ='INVENTARIO INICIAL'!K11 -> 0 | L11: ='INVENTARIO INICIAL'!L11 -> 0 | M11: ='INVENTARIO INICIAL'!M11 -> 0 | N11: ='INVENTARIO INICIAL'!N11 -> 0 | O11: ='INVENTARIO INICIAL'!O11 -> 0 | P11: ='INVENTARIO INICIAL'!P11 -> 0 | Q11: ='INVENTARIO INICIAL'!Q11 -> 0 | R11: ='INVENTARIO INICIAL'!R11 -> 0 | S11: ='Reporte Junio 2026'!AF11 -> 0 | AF11: =IF(AI11>=AJ11,IF(AK11>=0,IF(AJ11>=0,AK11,"Error"))) -> 0 | AG11: ='Reporte Junio 2026'!AG11 -> 0 | AH11: =AF11*AG11 -> 0 | AI11: =S11+T11 -> 0 | AJ11: =U11+V11+W11+X11+Y11+AB11 -> 0 | AK11: =AI11-AJ11 -> 0 | AL11: Septiembre | AN11: ='INVENTARIO INICIAL'!X11 -> 0
A12: ='Reporte Junio 2026'!A12 -> Inventario | B12: ='INVENTARIO INICIAL'!B12 -> 0 | C12: =IF(B12=0,"",VLOOKUP(B12,Datos!$H$2:$K$39,2,FALSE)) | D12: =IF(B12=0,"",VLOOKUP(B12,Datos!$H$2:$K$39,3,FALSE)) | E12: =IF(B12=0,"",VLOOKUP(B12,Datos!$H$2:$K$39,4,FALSE)) | F12: ='INVENTARIO INICIAL'!F12 -> 0 | G12: ='INVENTARIO INICIAL'!G12 -> 0 | H12: ='INVENTARIO INICIAL'!H12 -> 0 | I12: =IF(H12=0,"",VLOOKUP(H12,Datos!$B$2:$D$908,2,FALSE)) | J12: =IF(H12=0,"",VLOOKUP(H12,Datos!$B$2:$D$908,3,FALSE)) | K12: ='INVENTARIO INICIAL'!K12 -> 0 | L12: ='INVENTARIO INICIAL'!L12 -> 0 | M12: ='INVENTARIO INICIAL'!M12 -> 0 | N12: ='INVENTARIO INICIAL'!N12 -> 0 | O12: ='INVENTARIO INICIAL'!O12 -> 0 | P12: ='INVENTARIO INICIAL'!P12 -> 0 | Q12: ='INVENTARIO INICIAL'!Q12 -> 0 | R12: ='INVENTARIO INICIAL'!R12 -> 0 | S12: ='Reporte Junio 2026'!AF12 -> 0 | AF12: =IF(AI12>=AJ12,IF(AK12>=0,IF(AJ12>=0,AK12,"Error"))) -> 0 | AG12: ='Reporte Junio 2026'!AG12 -> 0 | AH12: =AF12*AG12 -> 0 | AI12: =S12+T12 -> 0 | AJ12: =U12+V12+W12+X12+Y12+AB12 -> 0 | AK12: =AI12-AJ12 -> 0 | AL12: Septiembre | AN12: ='INVENTARIO INICIAL'!X12 -> 0
A13: ='Reporte Junio 2026'!A13 -> Inventario | B13: ='INVENTARIO INICIAL'!B13 -> 0 | C13: =IF(B13=0,"",VLOOKUP(B13,Datos!$H$2:$K$39,2,FALSE)) | D13: =IF(B13=0,"",VLOOKUP(B13,Datos!$H$2:$K$39,3,FALSE)) | E13: =IF(B13=0,"",VLOOKUP(B13,Datos!$H$2:$K$39,4,FALSE)) | F13: ='INVENTARIO INICIAL'!F13 -> 0 | G13: ='INVENTARIO INICIAL'!G13 -> 0 | H13: ='INVENTARIO INICIAL'!H13 -> 0 | I13: =IF(H13=0,"",VLOOKUP(H13,Datos!$B$2:$D$908,2,FALSE)) | J13: =IF(H13=0,"",VLOOKUP(H13,Datos!$B$2:$D$908,3,FALSE)) | K13: ='INVENTARIO INICIAL'!K13 -> 0 | L13: ='INVENTARIO INICIAL'!L13 -> 0 | M13: ='INVENTARIO INICIAL'!M13 -> 0 | N13: ='INVENTARIO INICIAL'!N13 -> 0 | O13: ='INVENTARIO INICIAL'!O13 -> 0 | P13: ='INVENTARIO INICIAL'!P13 -> 0 | Q13: ='INVENTARIO INICIAL'!Q13 -> 0 | R13: ='INVENTARIO INICIAL'!R13 -> 0 | S13: ='Reporte Junio 2026'!AF13 -> 0 | AF13: =IF(AI13>=AJ13,IF(AK13>=0,IF(AJ13>=0,AK13,"Error"))) -> 0 | AG13: ='Reporte Junio 2026'!AG13 -> 0 | AH13: =AF13*AG13 -> 0 | AI13: =S13+T13 -> 0 | AJ13: =U13+V13+W13+X13+Y13+AB13 -> 0 | AK13: =AI13-AJ13 -> 0 | AL13: Septiembre | AN13: ='INVENTARIO INICIAL'!X13 -> 0
A14: ='Reporte Junio 2026'!A14 -> Inventario | B14: ='INVENTARIO INICIAL'!B14 -> 0 | C14: =IF(B14=0,"",VLOOKUP(B14,Datos!$H$2:$K$39,2,FALSE)) | D14: =IF(B14=0,"",VLOOKUP(B14,Datos!$H$2:$K$39,3,FALSE)) | E14: =IF(B14=0,"",VLOOKUP(B14,Datos!$H$2:$K$39,4,FALSE)) | F14: ='INVENTARIO INICIAL'!F14 -> 0 | G14: ='INVENTARIO INICIAL'!G14 -> 0 | H14: ='INVENTARIO INICIAL'!H14 -> 0 | I14: =IF(H14=0,"",VLOOKUP(H14,Datos!$B$2:$D$908,2,FALSE)) | J14: =IF(H14=0,"",VLOOKUP(H14,Datos!$B$2:$D$908,3,FALSE)) | K14: ='INVENTARIO INICIAL'!K14 -> 0 | L14: ='INVENTARIO INICIAL'!L14 -> 0 | M14: ='INVENTARIO INICIAL'!M14 -> 0 | N14: ='INVENTARIO INICIAL'!N14 -> 0 | O14: ='INVENTARIO INICIAL'!O14 -> 0 | P14: ='INVENTARIO INICIAL'!P14 -> 0 | Q14: ='INVENTARIO INICIAL'!Q14 -> 0 | R14: ='INVENTARIO INICIAL'!R14 -> 0 | S14: ='Reporte Junio 2026'!AF14 -> 0 | AF14: =IF(AI14>=AJ14,IF(AK14>=0,IF(AJ14>=0,AK14,"Error"))) -> 0 | AG14: ='Reporte Junio 2026'!AG14 -> 0 | AH14: =AF14*AG14 -> 0 | AI14: =S14+T14 -> 0 | AJ14: =U14+V14+W14+X14+Y14+AB14 -> 0 | AK14: =AI14-AJ14 -> 0 | AL14: Septiembre | AN14: ='INVENTARIO INICIAL'!X14 -> 0
A15: ='Reporte Junio 2026'!A15 -> Inventario | B15: ='INVENTARIO INICIAL'!B15 -> 0 | C15: =IF(B15=0,"",VLOOKUP(B15,Datos!$H$2:$K$39,2,FALSE)) | D15: =IF(B15=0,"",VLOOKUP(B15,Datos!$H$2:$K$39,3,FALSE)) | E15: =IF(B15=0,"",VLOOKUP(B15,Datos!$H$2:$K$39,4,FALSE)) | F15: ='INVENTARIO INICIAL'!F15 -> 0 | G15: ='INVENTARIO INICIAL'!G15 -> 0 | H15: ='INVENTARIO INICIAL'!H15 -> 0 | I15: =IF(H15=0,"",VLOOKUP(H15,Datos!$B$2:$D$908,2,FALSE)) | J15: =IF(H15=0,"",VLOOKUP(H15,Datos!$B$2:$D$908,3,FALSE)) | K15: ='INVENTARIO INICIAL'!K15 -> 0 | L15: ='INVENTARIO INICIAL'!L15 -> 0 | M15: ='INVENTARIO INICIAL'!M15 -> 0 | N15: ='INVENTARIO INICIAL'!N15 -> 0 | O15: ='INVENTARIO INICIAL'!O15 -> 0 | P15: ='INVENTARIO INICIAL'!P15 -> 0 | Q15: ='INVENTARIO INICIAL'!Q15 -> 0 | R15: ='INVENTARIO INICIAL'!R15 -> 0 | S15: ='Reporte Junio 2026'!AF15 -> 0 | AF15: =IF(AI15>=AJ15,IF(AK15>=0,IF(AJ15>=0,AK15,"Error"))) -> 0 | AG15: ='Reporte Junio 2026'!AG15 -> 0 | AH15: =AF15*AG15 -> 0 | AI15: =S15+T15 -> 0 | AJ15: =U15+V15+W15+X15+Y15+AB15 -> 0 | AK15: =AI15-AJ15 -> 0 | AL15: Septiembre | AN15: ='INVENTARIO INICIAL'!X15 -> 0
A16: ='Reporte Junio 2026'!A16 -> Inventario | B16: ='INVENTARIO INICIAL'!B16 -> 0 | C16: =IF(B16=0,"",VLOOKUP(B16,Datos!$H$2:$K$39,2,FALSE)) | D16: =IF(B16=0,"",VLOOKUP(B16,Datos!$H$2:$K$39,3,FALSE)) | E16: =IF(B16=0,"",VLOOKUP(B16,Datos!$H$2:$K$39,4,FALSE)) | F16: ='INVENTARIO INICIAL'!F16 -> 0 | G16: ='INVENTARIO INICIAL'!G16 -> 0 | H16: ='INVENTARIO INICIAL'!H16 -> 0 | I16: =IF(H16=0,"",VLOOKUP(H16,Datos!$B$2:$D$908,2,FALSE)) | J16: =IF(H16=0,"",VLOOKUP(H16,Datos!$B$2:$D$908,3,FALSE)) | K16: ='INVENTARIO INICIAL'!K16 -> 0 | L16: ='INVENTARIO INICIAL'!L16 -> 0 | M16: ='INVENTARIO INICIAL'!M16 -> 0 | N16: ='INVENTARIO INICIAL'!N16 -> 0 | O16: ='INVENTARIO INICIAL'!O16 -> 0 | P16: ='INVENTARIO INICIAL'!P16 -> 0 | Q16: ='INVENTARIO INICIAL'!Q16 -> 0 | R16: ='INVENTARIO INICIAL'!R16 -> 0 | S16: ='Reporte Junio 2026'!AF16 -> 0 | AF16: =IF(AI16>=AJ16,IF(AK16>=0,IF(AJ16>=0,AK16,"Error"))) -> 0 | AG16: ='Reporte Junio 2026'!AG16 -> 0 | AH16: =AF16*AG16 -> 0 | AI16: =S16+T16 -> 0 | AJ16: =U16+V16+W16+X16+Y16+AB16 -> 0 | AK16: =AI16-AJ16 -> 0 | AL16: Septiembre | AN16: ='INVENTARIO INICIAL'!X16 -> 0
A17: ='Reporte Junio 2026'!A17 -> Inventario | B17: ='INVENTARIO INICIAL'!B17 -> 0 | C17: =IF(B17=0,"",VLOOKUP(B17,Datos!$H$2:$K$39,2,FALSE)) | D17: =IF(B17=0,"",VLOOKUP(B17,Datos!$H$2:$K$39,3,FALSE)) | E17: =IF(B17=0,"",VLOOKUP(B17,Datos!$H$2:$K$39,4,FALSE)) | F17: ='INVENTARIO INICIAL'!F17 -> 0 | G17: ='INVENTARIO INICIAL'!G17 -> 0 | H17: ='INVENTARIO INICIAL'!H17 -> 0 | I17: =IF(H17=0,"",VLOOKUP(H17,Datos!$B$2:$D$908,2,FALSE)) | J17: =IF(H17=0,"",VLOOKUP(H17,Datos!$B$2:$D$908,3,FALSE)) | K17: ='INVENTARIO INICIAL'!K17 -> 0 | L17: ='INVENTARIO INICIAL'!L17 -> 0 | M17: ='INVENTARIO INICIAL'!M17 -> 0 | N17: ='INVENTARIO INICIAL'!N17 -> 0 | O17: ='INVENTARIO INICIAL'!O17 -> 0 | P17: ='INVENTARIO INICIAL'!P17 -> 0 | Q17: ='INVENTARIO INICIAL'!Q17 -> 0 | R17: ='INVENTARIO INICIAL'!R17 -> 0 | S17: ='Reporte Junio 2026'!AF17 -> 0 | AF17: =IF(AI17>=AJ17,IF(AK17>=0,IF(AJ17>=0,AK17,"Error"))) -> 0 | AG17: ='Reporte Junio 2026'!AG17 -> 0 | AH17: =AF17*AG17 -> 0 | AI17: =S17+T17 -> 0 | AJ17: =U17+V17+W17+X17+Y17+AB17 -> 0 | AK17: =AI17-AJ17 -> 0 | AL17: Septiembre | AN17: ='INVENTARIO INICIAL'!X17 -> 0
A18: ='Reporte Junio 2026'!A18 -> Inventario | B18: ='INVENTARIO INICIAL'!B18 -> 0 | C18: =IF(B18=0,"",VLOOKUP(B18,Datos!$H$2:$K$39,2,FALSE)) | D18: =IF(B18=0,"",VLOOKUP(B18,Datos!$H$2:$K$39,3,FALSE)) | E18: =IF(B18=0,"",VLOOKUP(B18,Datos!$H$2:$K$39,4,FALSE)) | F18: ='INVENTARIO INICIAL'!F18 -> 0 | G18: ='INVENTARIO INICIAL'!G18 -> 0 | H18: ='INVENTARIO INICIAL'!H18 -> 0 | I18: =IF(H18=0,"",VLOOKUP(H18,Datos!$B$2:$D$908,2,FALSE)) | J18: =IF(H18=0,"",VLOOKUP(H18,Datos!$B$2:$D$908,3,FALSE)) | K18: ='INVENTARIO INICIAL'!K18 -> 0 | L18: ='INVENTARIO INICIAL'!L18 -> 0 | M18: ='INVENTARIO INICIAL'!M18 -> 0 | N18: ='INVENTARIO INICIAL'!N18 -> 0 | O18: ='INVENTARIO INICIAL'!O18 -> 0 | P18: ='INVENTARIO INICIAL'!P18 -> 0 | Q18: ='INVENTARIO INICIAL'!Q18 -> 0 | R18: ='INVENTARIO INICIAL'!R18 -> 0 | S18: ='Reporte Junio 2026'!AF18 -> 0 | AF18: =IF(AI18>=AJ18,IF(AK18>=0,IF(AJ18>=0,AK18,"Error"))) -> 0 | AG18: ='Reporte Junio 2026'!AG18 -> 0 | AH18: =AF18*AG18 -> 0 | AI18: =S18+T18 -> 0 | AJ18: =U18+V18+W18+X18+Y18+AB18 -> 0 | AK18: =AI18-AJ18 -> 0 | AL18: Septiembre | AN18: ='INVENTARIO INICIAL'!X18 -> 0
... A360: ='Reporte Junio 2026'!A360 -> Inventario | B360: ='INVENTARIO INICIAL'!B360 -> 0 | C360: =IF(B360=0,"",VLOOKUP(B360,Datos!$H$2:$K$39,2,FALSE)) | D360: =IF(B360=0,"",VLOOKUP(B360,Datos!$H$2:$K$39,3,FALSE)) | E360: =IF(B360=0,"",VLOOKUP(B360,Datos!$H$2:$K$39,4,FALSE)) | F360: ='INVENTARIO INICIAL'!F360 -> 0 | G360: ='INVENTARIO INICIAL'!G360 -> 0 | H360: ='INVENTARIO INICIAL'!H360 -> 0 | I360: =IF(H360=0,"",VLOOKUP(H360,Datos!$B$2:$D$908,2,FALSE)) | J360: =IF(H360=0,"",VLOOKUP(H360,Datos!$B$2:$D$908,3,FALSE)) | K360: ='INVENTARIO INICIAL'!K360 -> 0 | L360: ='INVENTARIO INICIAL'!L360 -> 0 | M360: ='INVENTARIO INICIAL'!M360 -> 0 | N360: ='INVENTARIO INICIAL'!N360 -> 0 | O360: ='INVENTARIO INICIAL'!O360 -> 0 | P360: ='INVENTARIO INICIAL'!P360 -> 0 | Q360: ='INVENTARIO INICIAL'!Q360 -> 0 | R360: ='INVENTARIO INICIAL'!R360 -> 0 | S360: ='Reporte Junio 2026'!AF360 -> 0 | AF360: =IF(AI360>=AJ360,IF(AK360>=0,IF(AJ360>=0,AK360,"Error"))) -> 0 | AG360: ='Reporte Junio 2026'!AG360 -> 0 | AH360: =AF360*AG360 -> 0 | AI360: =S360+T360 -> 0 | AJ360: =U360+V360+W360+X360+Y360+AB360 -> 0 | AK360: =AI360-AJ360 -> 0 | AL360: Septiembre | AN360: ='INVENTARIO INICIAL'!X360 -> 0
A361: ='Reporte Junio 2026'!A361 -> Ingresos | B361: ='Reporte Junio 2026'!B361 -> 0 | C361: =IF(B361=0,"",VLOOKUP(B361,Datos!$H$2:$K$39,2,FALSE)) | D361: =IF(B361=0,"",VLOOKUP(B361,Datos!$H$2:$K$39,3,FALSE)) | E361: =IF(B361=0,"",VLOOKUP(B361,Datos!$H$2:$K$39,4,FALSE)) | F361: ='Reporte Junio 2026'!F361 -> 0 | G361: ='Reporte Junio 2026'!G361 -> 0 | H361: ='Reporte Junio 2026'!H361 -> 0 | I361: =IF(H361=0,"",VLOOKUP(H361,Datos!$B$2:$D$891,2,FALSE)) | J361: =IF(H361=0,"",VLOOKUP(H361,Datos!$B$2:$D$891,3,FALSE)) | K361: ='Reporte Junio 2026'!K361 -> 0 | L361: ='Reporte Junio 2026'!L361 -> 0 | M361: ='Reporte Junio 2026'!M361 -> 0 | N361: ='Reporte Junio 2026'!N361 -> 0 | O361: ='Reporte Junio 2026'!O361 -> 0 | P361: ='Reporte Junio 2026'!P361 -> 0 | Q361: ='Reporte Junio 2026'!Q361 -> 0 | R361: ='Reporte Junio 2026'!R361 -> 0 | S361: ='Reporte Junio 2026'!AF361 -> 0 | AF361: =IF(AI361>=AJ361,IF(AK361>=0,IF(AJ361>=0,AK361,"Error"))) -> 0 | AG361: ='Reporte Junio 2026'!AG361 -> 0 | AH361: =AF361*AG361 -> 0 | AI361: =S361+T361 -> 0 | AJ361: =U361+V361+W361+X361+Y361+AB361 -> 0 | AK361: =AI361-AJ361 -> 0 | AL361: Septiembre | AN361: ='Reporte Junio 2026'!AN361 -> 0
A362: ='Reporte Junio 2026'!A362 -> Ingresos | B362: ='Reporte Junio 2026'!B362 -> 0 | C362: =IF(B362=0,"",VLOOKUP(B362,Datos!$H$2:$K$39,2,FALSE)) | D362: =IF(B362=0,"",VLOOKUP(B362,Datos!$H$2:$K$39,3,FALSE)) | E362: =IF(B362=0,"",VLOOKUP(B362,Datos!$H$2:$K$39,4,FALSE)) | F362: ='Reporte Junio 2026'!F362 -> 0 | G362: ='Reporte Junio 2026'!G362 -> 0 | H362: ='Reporte Junio 2026'!H362 -> 0 | I362: =IF(H362=0,"",VLOOKUP(H362,Datos!$B$2:$D$891,2,FALSE)) | J362: =IF(H362=0,"",VLOOKUP(H362,Datos!$B$2:$D$891,3,FALSE)) | K362: ='Reporte Junio 2026'!K362 -> 0 | L362: ='Reporte Junio 2026'!L362 -> 0 | M362: ='Reporte Junio 2026'!M362 -> 0 | N362: ='Reporte Junio 2026'!N362 -> 0 | O362: ='Reporte Junio 2026'!O362 -> 0 | P362: ='Reporte Junio 2026'!P362 -> 0 | Q362: ='Reporte Junio 2026'!Q362 -> 0 | R362: ='Reporte Junio 2026'!R362 -> 0 | S362: ='Reporte Junio 2026'!AF362 -> 0 | AF362: =IF(AI362>=AJ362,IF(AK362>=0,IF(AJ362>=0,AK362,"Error"))) -> 0 | AG362: ='Reporte Junio 2026'!AG362 -> 0 | AH362: =AF362*AG362 -> 0 | AI362: =S362+T362 -> 0 | AJ362: =U362+V362+W362+X362+Y362+AB362 -> 0 | AK362: =AI362-AJ362 -> 0 | AL362: Septiembre | AN362: ='Reporte Junio 2026'!AN362 -> 0
A363: ='Reporte Junio 2026'!A363 -> Ingresos | B363: ='Reporte Junio 2026'!B363 -> 0 | C363: =IF(B363=0,"",VLOOKUP(B363,Datos!$H$2:$K$39,2,FALSE)) | D363: =IF(B363=0,"",VLOOKUP(B363,Datos!$H$2:$K$39,3,FALSE)) | E363: =IF(B363=0,"",VLOOKUP(B363,Datos!$H$2:$K$39,4,FALSE)) | F363: ='Reporte Junio 2026'!F363 -> 0 | G363: ='Reporte Junio 2026'!G363 -> 0 | H363: ='Reporte Junio 2026'!H363 -> 0 | I363: =IF(H363=0,"",VLOOKUP(H363,Datos!$B$2:$D$891,2,FALSE)) | J363: =IF(H363=0,"",VLOOKUP(H363,Datos!$B$2:$D$891,3,FALSE)) | K363: ='Reporte Junio 2026'!K363 -> 0 | L363: ='Reporte Junio 2026'!L363 -> 0 | M363: ='Reporte Junio 2026'!M363 -> 0 | N363: ='Reporte Junio 2026'!N363 -> 0 | O363: ='Reporte Junio 2026'!O363 -> 0 | P363: ='Reporte Junio 2026'!P363 -> 0 | Q363: ='Reporte Junio 2026'!Q363 -> 0 | R363: ='Reporte Junio 2026'!R363 -> 0 | S363: ='Reporte Junio 2026'!AF363 -> 0 | AF363: =IF(AI363>=AJ363,IF(AK363>=0,IF(AJ363>=0,AK363,"Error"))) -> 0 | AG363: ='Reporte Junio 2026'!AG363 -> 0 | AH363: =AF363*AG363 -> 0 | AI363: =S363+T363 -> 0 | AJ363: =U363+V363+W363+X363+Y363+AB363 -> 0 | AK363: =AI363-AJ363 -> 0 | AL363: Septiembre | AN363: ='Reporte Junio 2026'!AN363 -> 0
A364: ='Reporte Junio 2026'!A364 -> Ingresos | B364: ='Reporte Junio 2026'!B364 -> 0 | C364: =IF(B364=0,"",VLOOKUP(B364,Datos!$H$2:$K$39,2,FALSE)) | D364: =IF(B364=0,"",VLOOKUP(B364,Datos!$H$2:$K$39,3,FALSE)) | E364: =IF(B364=0,"",VLOOKUP(B364,Datos!$H$2:$K$39,4,FALSE)) | F364: ='Reporte Junio 2026'!F364 -> 0 | G364: ='Reporte Junio 2026'!G364 -> 0 | H364: ='Reporte Junio 2026'!H364 -> 0 | I364: =IF(H364=0,"",VLOOKUP(H364,Datos!$B$2:$D$891,2,FALSE)) | J364: =IF(H364=0,"",VLOOKUP(H364,Datos!$B$2:$D$891,3,FALSE)) | K364: ='Reporte Junio 2026'!K364 -> 0 | L364: ='Reporte Junio 2026'!L364 -> 0 | M364: ='Reporte Junio 2026'!M364 -> 0 | N364: ='Reporte Junio 2026'!N364 -> 0 | O364: ='Reporte Junio 2026'!O364 -> 0 | P364: ='Reporte Junio 2026'!P364 -> 0 | Q364: ='Reporte Junio 2026'!Q364 -> 0 | R364: ='Reporte Junio 2026'!R364 -> 0 | S364: ='Reporte Junio 2026'!AF364 -> 0 | AF364: =IF(AI364>=AJ364,IF(AK364>=0,IF(AJ364>=0,AK364,"Error"))) -> 0 | AG364: ='Reporte Junio 2026'!AG364 -> 0 | AH364: =AF364*AG364 -> 0 | AI364: =S364+T364 -> 0 | AJ364: =U364+V364+W364+X364+Y364+AB364 -> 0 | AK364: =AI364-AJ364 -> 0 | AL364: Septiembre | AN364: ='Reporte Junio 2026'!AN364 -> 0
A365: ='Reporte Junio 2026'!A365 -> Ingresos | B365: ='Reporte Junio 2026'!B365 -> 0 | C365: =IF(B365=0,"",VLOOKUP(B365,Datos!$H$2:$K$39,2,FALSE)) | D365: =IF(B365=0,"",VLOOKUP(B365,Datos!$H$2:$K$39,3,FALSE)) | E365: =IF(B365=0,"",VLOOKUP(B365,Datos!$H$2:$K$39,4,FALSE)) | F365: ='Reporte Junio 2026'!F365 -> 0 | G365: ='Reporte Junio 2026'!G365 -> 0 | H365: ='Reporte Junio 2026'!H365 -> 0 | I365: =IF(H365=0,"",VLOOKUP(H365,Datos!$B$2:$D$891,2,FALSE)) | J365: =IF(H365=0,"",VLOOKUP(H365,Datos!$B$2:$D$891,3,FALSE)) | K365: ='Reporte Junio 2026'!K365 -> 0 | L365: ='Reporte Junio 2026'!L365 -> 0 | M365: ='Reporte Junio 2026'!M365 -> 0 | N365: ='Reporte Junio 2026'!N365 -> 0 | O365: ='Reporte Junio 2026'!O365 -> 0 | P365: ='Reporte Junio 2026'!P365 -> 0 | Q365: ='Reporte Junio 2026'!Q365 -> 0 | R365: ='Reporte Junio 2026'!R365 -> 0 | S365: ='Reporte Junio 2026'!AF365 -> 0 | AF365: =IF(AI365>=AJ365,IF(AK365>=0,IF(AJ365>=0,AK365,"Error"))) -> 0 | AG365: ='Reporte Junio 2026'!AG365 -> 0 | AH365: =AF365*AG365 -> 0 | AI365: =S365+T365 -> 0 | AJ365: =U365+V365+W365+X365+Y365+AB365 -> 0 | AK365: =AI365-AJ365 -> 0 | AL365: Septiembre | AN365: ='Reporte Junio 2026'!AN365 -> 0
A366: ='Reporte Junio 2026'!A366 -> Ingresos | B366: ='Reporte Junio 2026'!B366 -> 0 | C366: =IF(B366=0,"",VLOOKUP(B366,Datos!$H$2:$K$39,2,FALSE)) | D366: =IF(B366=0,"",VLOOKUP(B366,Datos!$H$2:$K$39,3,FALSE)) | E366: =IF(B366=0,"",VLOOKUP(B366,Datos!$H$2:$K$39,4,FALSE)) | F366: ='Reporte Junio 2026'!F366 -> 0 | G366: ='Reporte Junio 2026'!G366 -> 0 | H366: ='Reporte Junio 2026'!H366 -> 0 | I366: =IF(H366=0,"",VLOOKUP(H366,Datos!$B$2:$D$891,2,FALSE)) | J366: =IF(H366=0,"",VLOOKUP(H366,Datos!$B$2:$D$891,3,FALSE)) | K366: ='Reporte Junio 2026'!K366 -> 0 | L366: ='Reporte Junio 2026'!L366 -> 0 | M366: ='Reporte Junio 2026'!M366 -> 0 | N366: ='Reporte Junio 2026'!N366 -> 0 | O366: ='Reporte Junio 2026'!O366 -> 0 | P366: ='Reporte Junio 2026'!P366 -> 0 | Q366: ='Reporte Junio 2026'!Q366 -> 0 | R366: ='Reporte Junio 2026'!R366 -> 0 | S366: ='Reporte Junio 2026'!AF366 -> 0 | AF366: =IF(AI366>=AJ366,IF(AK366>=0,IF(AJ366>=0,AK366,"Error"))) -> 0 | AG366: ='Reporte Junio 2026'!AG366 -> 0 | AH366: =AF366*AG366 -> 0 | AI366: =S366+T366 -> 0 | AJ366: =U366+V366+W366+X366+Y366+AB366 -> 0 | AK366: =AI366-AJ366 -> 0 | AL366: Septiembre | AN366: ='Reporte Junio 2026'!AN366 -> 0
A367: ='Reporte Junio 2026'!A367 -> Ingresos | B367: ='Reporte Junio 2026'!B367 -> 0 | C367: =IF(B367=0,"",VLOOKUP(B367,Datos!$H$2:$K$39,2,FALSE)) | D367: =IF(B367=0,"",VLOOKUP(B367,Datos!$H$2:$K$39,3,FALSE)) | E367: =IF(B367=0,"",VLOOKUP(B367,Datos!$H$2:$K$39,4,FALSE)) | F367: ='Reporte Junio 2026'!F367 -> 0 | G367: ='Reporte Junio 2026'!G367 -> 0 | H367: ='Reporte Junio 2026'!H367 -> 0 | I367: =IF(H367=0,"",VLOOKUP(H367,Datos!$B$2:$D$891,2,FALSE)) | J367: =IF(H367=0,"",VLOOKUP(H367,Datos!$B$2:$D$891,3,FALSE)) | K367: ='Reporte Junio 2026'!K367 -> 0 | L367: ='Reporte Junio 2026'!L367 -> 0 | M367: ='Reporte Junio 2026'!M367 -> 0 | N367: ='Reporte Junio 2026'!N367 -> 0 | O367: ='Reporte Junio 2026'!O367 -> 0 | P367: ='Reporte Junio 2026'!P367 -> 0 | Q367: ='Reporte Junio 2026'!Q367 -> 0 | R367: ='Reporte Junio 2026'!R367 -> 0 | S367: ='Reporte Junio 2026'!AF367 -> 0 | AF367: =IF(AI367>=AJ367,IF(AK367>=0,IF(AJ367>=0,AK367,"Error"))) -> 0 | AG367: ='Reporte Junio 2026'!AG367 -> 0 | AH367: =AF367*AG367 -> 0 | AI367: =S367+T367 -> 0 | AJ367: =U367+V367+W367+X367+Y367+AB367 -> 0 | AK367: =AI367-AJ367 -> 0 | AL367: Septiembre | AN367: ='Reporte Junio 2026'!AN367 -> 0
A368: ='Reporte Junio 2026'!A368 -> Ingresos | B368: ='Reporte Junio 2026'!B368 -> 0 | C368: =IF(B368=0,"",VLOOKUP(B368,Datos!$H$2:$K$39,2,FALSE)) | D368: =IF(B368=0,"",VLOOKUP(B368,Datos!$H$2:$K$39,3,FALSE)) | E368: =IF(B368=0,"",VLOOKUP(B368,Datos!$H$2:$K$39,4,FALSE)) | F368: ='Reporte Junio 2026'!F368 -> 0 | G368: ='Reporte Junio 2026'!G368 -> 0 | H368: ='Reporte Junio 2026'!H368 -> 0 | I368: =IF(H368=0,"",VLOOKUP(H368,Datos!$B$2:$D$891,2,FALSE)) | J368: =IF(H368=0,"",VLOOKUP(H368,Datos!$B$2:$D$891,3,FALSE)) | K368: ='Reporte Junio 2026'!K368 -> 0 | L368: ='Reporte Junio 2026'!L368 -> 0 | M368: ='Reporte Junio 2026'!M368 -> 0 | N368: ='Reporte Junio 2026'!N368 -> 0 | O368: ='Reporte Junio 2026'!O368 -> 0 | P368: ='Reporte Junio 2026'!P368 -> 0 | Q368: ='Reporte Junio 2026'!Q368 -> 0 | R368: ='Reporte Junio 2026'!R368 -> 0 | S368: ='Reporte Junio 2026'!AF368 -> 0 | AF368: =IF(AI368>=AJ368,IF(AK368>=0,IF(AJ368>=0,AK368,"Error"))) -> 0 | AG368: ='Reporte Junio 2026'!AG368 -> 0 | AH368: =AF368*AG368 -> 0 | AI368: =S368+T368 -> 0 | AJ368: =U368+V368+W368+X368+Y368+AB368 -> 0 | AK368: =AI368-AJ368 -> 0 | AL368: Septiembre | AN368: ='Reporte Junio 2026'!AN368 -> 0
A369: ='Reporte Junio 2026'!A369 -> Ingresos | B369: ='Reporte Junio 2026'!B369 -> 0 | C369: =IF(B369=0,"",VLOOKUP(B369,Datos!$H$2:$K$39,2,FALSE)) | D369: =IF(B369=0,"",VLOOKUP(B369,Datos!$H$2:$K$39,3,FALSE)) | E369: =IF(B369=0,"",VLOOKUP(B369,Datos!$H$2:$K$39,4,FALSE)) | F369: ='Reporte Junio 2026'!F369 -> 0 | G369: ='Reporte Junio 2026'!G369 -> 0 | H369: ='Reporte Junio 2026'!H369 -> 0 | I369: =IF(H369=0,"",VLOOKUP(H369,Datos!$B$2:$D$891,2,FALSE)) | J369: =IF(H369=0,"",VLOOKUP(H369,Datos!$B$2:$D$891,3,FALSE)) | K369: ='Reporte Junio 2026'!K369 -> 0 | L369: ='Reporte Junio 2026'!L369 -> 0 | M369: ='Reporte Junio 2026'!M369 -> 0 | N369: ='Reporte Junio 2026'!N369 -> 0 | O369: ='Reporte Junio 2026'!O369 -> 0 | P369: ='Reporte Junio 2026'!P369 -> 0 | Q369: ='Reporte Junio 2026'!Q369 -> 0 | R369: ='Reporte Junio 2026'!R369 -> 0 | S369: ='Reporte Junio 2026'!AF369 -> 0 | AF369: =IF(AI369>=AJ369,IF(AK369>=0,IF(AJ369>=0,AK369,"Error"))) -> 0 | AG369: ='Reporte Junio 2026'!AG369 -> 0 | AH369: =AF369*AG369 -> 0 | AI369: =S369+T369 -> 0 | AJ369: =U369+V369+W369+X369+Y369+AB369 -> 0 | AK369: =AI369-AJ369 -> 0 | AL369: Septiembre | AN369: ='Reporte Junio 2026'!AN369 -> 0
A370: ='Reporte Junio 2026'!A370 -> Ingresos | B370: ='Reporte Junio 2026'!B370 -> 0 | C370: =IF(B370=0,"",VLOOKUP(B370,Datos!$H$2:$K$39,2,FALSE)) | D370: =IF(B370=0,"",VLOOKUP(B370,Datos!$H$2:$K$39,3,FALSE)) | E370: =IF(B370=0,"",VLOOKUP(B370,Datos!$H$2:$K$39,4,FALSE)) | F370: ='Reporte Junio 2026'!F370 -> 0 | G370: ='Reporte Junio 2026'!G370 -> 0 | H370: ='Reporte Junio 2026'!H370 -> 0 | I370: =IF(H370=0,"",VLOOKUP(H370,Datos!$B$2:$D$891,2,FALSE)) | J370: =IF(H370=0,"",VLOOKUP(H370,Datos!$B$2:$D$891,3,FALSE)) | K370: ='Reporte Junio 2026'!K370 -> 0 | L370: ='Reporte Junio 2026'!L370 -> 0 | M370: ='Reporte Junio 2026'!M370 -> 0 | N370: ='Reporte Junio 2026'!N370 -> 0 | O370: ='Reporte Junio 2026'!O370 -> 0 | P370: ='Reporte Junio 2026'!P370 -> 0 | Q370: ='Reporte Junio 2026'!Q370 -> 0 | R370: ='Reporte Junio 2026'!R370 -> 0 | S370: ='Reporte Junio 2026'!AF370 -> 0 | AF370: =IF(AI370>=AJ370,IF(AK370>=0,IF(AJ370>=0,AK370,"Error"))) -> 0 | AG370: ='Reporte Junio 2026'!AG370 -> 0 | AH370: =AF370*AG370 -> 0 | AI370: =S370+T370 -> 0 | AJ370: =U370+V370+W370+X370+Y370+AB370 -> 0 | AK370: =AI370-AJ370 -> 0 | AL370: Septiembre | AN370: ='Reporte Junio 2026'!AN370 -> 0
A371: ='Reporte Junio 2026'!A371 -> Ingresos | B371: ='Reporte Junio 2026'!B371 -> 0 | C371: =IF(B371=0,"",VLOOKUP(B371,Datos!$H$2:$K$39,2,FALSE)) | D371: =IF(B371=0,"",VLOOKUP(B371,Datos!$H$2:$K$39,3,FALSE)) | E371: =IF(B371=0,"",VLOOKUP(B371,Datos!$H$2:$K$39,4,FALSE)) | F371: ='Reporte Junio 2026'!F371 -> 0 | G371: ='Reporte Junio 2026'!G371 -> 0 | H371: ='Reporte Junio 2026'!H371 -> 0 | I371: =IF(H371=0,"",VLOOKUP(H371,Datos!$B$2:$D$891,2,FALSE)) | J371: =IF(H371=0,"",VLOOKUP(H371,Datos!$B$2:$D$891,3,FALSE)) | K371: ='Reporte Junio 2026'!K371 -> 0 | L371: ='Reporte Junio 2026'!L371 -> 0 | M371: ='Reporte Junio 2026'!M371 -> 0 | N371: ='Reporte Junio 2026'!N371 -> 0 | O371: ='Reporte Junio 2026'!O371 -> 0 | P371: ='Reporte Junio 2026'!P371 -> 0 | Q371: ='Reporte Junio 2026'!Q371 -> 0 | R371: ='Reporte Junio 2026'!R371 -> 0 | S371: ='Reporte Junio 2026'!AF371 -> 0 | AF371: =IF(AI371>=AJ371,IF(AK371>=0,IF(AJ371>=0,AK371,"Error"))) -> 0 | AG371: ='Reporte Junio 2026'!AG371 -> 0 | AH371: =AF371*AG371 -> 0 | AI371: =S371+T371 -> 0 | AJ371: =U371+V371+W371+X371+Y371+AB371 -> 0 | AK371: =AI371-AJ371 -> 0 | AL371: Septiembre | AN371: ='Reporte Junio 2026'!AN371 -> 0
A372: ='Reporte Junio 2026'!A372 -> Ingresos | B372: ='Reporte Junio 2026'!B372 -> 0 | C372: =IF(B372=0,"",VLOOKUP(B372,Datos!$H$2:$K$39,2,FALSE)) | D372: =IF(B372=0,"",VLOOKUP(B372,Datos!$H$2:$K$39,3,FALSE)) | E372: =IF(B372=0,"",VLOOKUP(B372,Datos!$H$2:$K$39,4,FALSE)) | F372: ='Reporte Junio 2026'!F372 -> 0 | G372: ='Reporte Junio 2026'!G372 -> 0 | H372: ='Reporte Junio 2026'!H372 -> 0 | I372: =IF(H372=0,"",VLOOKUP(H372,Datos!$B$2:$D$891,2,FALSE)) | J372: =IF(H372=0,"",VLOOKUP(H372,Datos!$B$2:$D$891,3,FALSE)) | K372: ='Reporte Junio 2026'!K372 -> 0 | L372: ='Reporte Junio 2026'!L372 -> 0 | M372: ='Reporte Junio 2026'!M372 -> 0 | N372: ='Reporte Junio 2026'!N372 -> 0 | O372: ='Reporte Junio 2026'!O372 -> 0 | P372: ='Reporte Junio 2026'!P372 -> 0 | Q372: ='Reporte Junio 2026'!Q372 -> 0 | R372: ='Reporte Junio 2026'!R372 -> 0 | S372: ='Reporte Junio 2026'!AF372 -> 0 | AF372: =IF(AI372>=AJ372,IF(AK372>=0,IF(AJ372>=0,AK372,"Error"))) -> 0 | AG372: ='Reporte Junio 2026'!AG372 -> 0 | AH372: =AF372*AG372 -> 0 | AI372: =S372+T372 -> 0 | AJ372: =U372+V372+W372+X372+Y372+AB372 -> 0 | AK372: =AI372-AJ372 -> 0 | AL372: Septiembre | AN372: ='Reporte Junio 2026'!AN372 -> 0
... A490: ='Reporte Junio 2026'!A490 -> Ingresos | B490: ='Reporte Junio 2026'!B490 -> 0 | C490: =IF(B490=0,"",VLOOKUP(B490,Datos!$H$2:$K$39,2,FALSE)) | D490: =IF(B490=0,"",VLOOKUP(B490,Datos!$H$2:$K$39,3,FALSE)) | E490: =IF(B490=0,"",VLOOKUP(B490,Datos!$H$2:$K$39,4,FALSE)) | F490: ='Reporte Junio 2026'!F490 -> 0 | G490: ='Reporte Junio 2026'!G490 -> 0 | H490: ='Reporte Junio 2026'!H490 -> 0 | I490: =IF(H490=0,"",VLOOKUP(H490,Datos!$B$2:$D$891,2,FALSE)) | J490: =IF(H490=0,"",VLOOKUP(H490,Datos!$B$2:$D$891,3,FALSE)) | K490: ='Reporte Junio 2026'!K490 -> 0 | L490: ='Reporte Junio 2026'!L490 -> 0 | M490: ='Reporte Junio 2026'!M490 -> 0 | N490: ='Reporte Junio 2026'!N490 -> 0 | O490: ='Reporte Junio 2026'!O490 -> 0 | P490: ='Reporte Junio 2026'!P490 -> 0 | Q490: ='Reporte Junio 2026'!Q490 -> 0 | R490: ='Reporte Junio 2026'!R490 -> 0 | S490: ='Reporte Junio 2026'!AF490 -> 0 | AF490: =IF(AI490>=AJ490,IF(AK490>=0,IF(AJ490>=0,AK490,"Error"))) -> 0 | AG490: ='Reporte Junio 2026'!AG490 -> 0 | AH490: =AF490*AG490 -> 0 | AI490: =S490+T490 -> 0 | AJ490: =U490+V490+W490+X490+Y490+AB490 -> 0 | AK490: =AI490-AJ490 -> 0 | AL490: Septiembre | AN490: ='Reporte Junio 2026'!AN490 -> 0
A491: TOTAL SEPTIEMBRE | R491: TOTAL | S491: =SUM(S7:S490) -> 0 | T491: =SUM(T7:T490) -> 0 | U491: =SUM(U7:U490) -> 0 | V491: =SUM(V7:V490) -> 0 | W491: =SUM(W7:W490) -> 0 | X491: =SUM(X7:X490) -> 0 | Y491: =SUM(Y7:Y490) -> 0 | AB491: =SUM(AB7:AB490) -> 0 | AF491: =SUM(AF7:AF490) -> 0 | AH491: =SUM(AH7:AH490) -> 0 | AI491: =SUM(AI7:AI490) -> 0 | AJ491: =SUM(AJ7:AJ490) -> 0 | AK491: =SUM(AK7:AK490) -> 0 | AL491: Septiembre

Sheet Reporte Diciembre 2026
B1: Control Inventario de Plantas SIGI GBCC 8 | 2026
B2: Viveros, centros de acopio y acondicionamiento CONAF
B3: Reporte Diciembre 2026
T4: INGRESOS Y EGRESOS DE PLANTAS EN EL CUARTO TRIMESTRE (OCTUBRE A DICIEMBRE)
A5: ANTECEDENTES DEL VIVERO | H5: ANTECEDENTES DE LA ESPECIE | T5: N° DE PLANTAS NUEVAS | U5: N° DE PLANTAS ENTREGADAS Y/O VENDIDAS | X5: Movimientos Internos (Cambios Rango de Altura o Contenedor) | Y5: TRASLADOS INTERNOS A OTRAS UNIDADES CONAF | AB5: BAJA DE PLANTAS DE INVENTARIO | AF5: STOCK | AG5: VALORIZACIÓN
A6: Ítems | B6: Unidad Productiva | C6: Unidad Administrativa | D6: Provincia | E6: Comuna | F6: Encargado | G6: Teléfono de Contacto | H6: Nombre Científico | I6: Nombre Común | J6: Origen | K6: Fuente de Abastecimiento | L6: Destino de la Planta | M6: Tipo de Reproducción | N6: Tipo de Contenedor | O6: Fecha Ingreso a Inventario (Día/Mes/Año) | P6: Tiempo de Viverización (años) | Q6: Rango de Altura | R6: Sectores del Vivero | S6: N° Total Plantas Control Inventario Septiembre 2026 | T6: N° Plantas NUEVAS Ingresadas a Inventario | U6: N° Entregas por Difusión | V6: N° Entregas a Programas | W6: N° Plantas Venta | X6: N° Plantas (M.I.) | Y6: N° Plantas Trasladadas | Z6: Unidades Recepción de Traslado | AA6: N° de Documento, Factura o Guía de Despacho | AB6: N° Plantas de Baja | AC6: Causas | AD6: N° Resolución | AE6: Fecha de Resolución | AF6: N° TOTAL DE PLANTAS EN INVENTARIO DICIEMBRE 2026 | AG6: Valor Neto ($) por planta | AH6: Valor Total ($) por lote | AI6: Ingresos | AJ6: Egresos | AK6: Stock Diciembre | AL6: MES REPORTE | AN6: Código de planta para Guía de Despacho
A7: ='INVENTARIO INICIAL'!A7 -> Inventario | B7: ='INVENTARIO INICIAL'!B7 -> 0 | C7: =IF(B7=0,"",VLOOKUP(B7,Datos!$H$2:$K$39,2,FALSE)) | D7: =IF(B7=0,"",VLOOKUP(B7,Datos!$H$2:$K$39,3,FALSE)) | E7: =IF(B7=0,"",VLOOKUP(B7,Datos!$H$2:$K$39,4,FALSE)) | F7: ='INVENTARIO INICIAL'!F7 -> 0 | G7: ='INVENTARIO INICIAL'!G7 -> 0 | H7: ='INVENTARIO INICIAL'!H7 -> 0 | I7: =IF(H7=0,"",VLOOKUP(H7,Datos!$B$2:$D$908,2,FALSE)) | J7: =IF(H7=0,"",VLOOKUP(H7,Datos!$B$2:$D$908,3,FALSE)) | K7: ='INVENTARIO INICIAL'!K7 -> 0 | L7: ='INVENTARIO INICIAL'!L7 -> 0 | M7: ='INVENTARIO INICIAL'!M7 -> 0 | N7: ='INVENTARIO INICIAL'!N7 -> 0 | O7: ='INVENTARIO INICIAL'!O7 -> 0 | P7: ='INVENTARIO INICIAL'!P7 -> 0 | Q7: ='INVENTARIO INICIAL'!Q7 -> 0 | R7: ='INVENTARIO INICIAL'!R7 -> 0 | S7: ='Reporte Septiembre 2026'!AF7 -> 0 | AF7: =IF(AI7>=AJ7,IF(AK7>=0,IF(AJ7>=0,AK7,"Error"))) -> 0 | AG7: ='Reporte Septiembre 2026'!AG7 -> 0 | AH7: =AF7*AG7 -> 0 | AI7: =S7+T7 -> 0 | AJ7: =U7+V7+W7+X7+Y7+AB7 -> 0 | AK7: =AI7-AJ7 -> 0 | AL7: Diciembre | AN7: ='INVENTARIO INICIAL'!X7 -> 0
A8: ='INVENTARIO INICIAL'!A8 -> Inventario | B8: ='INVENTARIO INICIAL'!B8 -> 0 | C8: =IF(B8=0,"",VLOOKUP(B8,Datos!$H$2:$K$39,2,FALSE)) | D8: =IF(B8=0,"",VLOOKUP(B8,Datos!$H$2:$K$39,3,FALSE)) | E8: =IF(B8=0,"",VLOOKUP(B8,Datos!$H$2:$K$39,4,FALSE)) | F8: ='INVENTARIO INICIAL'!F8 -> 0 | G8: ='INVENTARIO INICIAL'!G8 -> 0 | H8: ='INVENTARIO INICIAL'!H8 -> 0 | I8: =IF(H8=0,"",VLOOKUP(H8,Datos!$B$2:$D$908,2,FALSE)) | J8: =IF(H8=0,"",VLOOKUP(H8,Datos!$B$2:$D$908,3,FALSE)) | K8: ='INVENTARIO INICIAL'!K8 -> 0 | L8: ='INVENTARIO INICIAL'!L8 -> 0 | M8: ='INVENTARIO INICIAL'!M8 -> 0 | N8: ='INVENTARIO INICIAL'!N8 -> 0 | O8: ='INVENTARIO INICIAL'!O8 -> 0 | P8: ='INVENTARIO INICIAL'!P8 -> 0 | Q8: ='INVENTARIO INICIAL'!Q8 -> 0 | R8: ='INVENTARIO INICIAL'!R8 -> 0 | S8: ='Reporte Septiembre 2026'!AF8 -> 0 | AF8: =IF(AI8>=AJ8,IF(AK8>=0,IF(AJ8>=0,AK8,"Error"))) -> 0 | AG8: ='Reporte Septiembre 2026'!AG8 -> 0 | AH8: =AF8*AG8 -> 0 | AI8: =S8+T8 -> 0 | AJ8: =U8+V8+W8+X8+Y8+AB8 -> 0 | AK8: =AI8-AJ8 -> 0 | AL8: Diciembre | AN8: ='INVENTARIO INICIAL'!X8 -> 0
A9: ='INVENTARIO INICIAL'!A9 -> Inventario | B9: ='INVENTARIO INICIAL'!B9 -> 0 | C9: =IF(B9=0,"",VLOOKUP(B9,Datos!$H$2:$K$39,2,FALSE)) | D9: =IF(B9=0,"",VLOOKUP(B9,Datos!$H$2:$K$39,3,FALSE)) | E9: =IF(B9=0,"",VLOOKUP(B9,Datos!$H$2:$K$39,4,FALSE)) | F9: ='INVENTARIO INICIAL'!F9 -> 0 | G9: ='INVENTARIO INICIAL'!G9 -> 0 | H9: ='INVENTARIO INICIAL'!H9 -> 0 | I9: =IF(H9=0,"",VLOOKUP(H9,Datos!$B$2:$D$908,2,FALSE)) | J9: =IF(H9=0,"",VLOOKUP(H9,Datos!$B$2:$D$908,3,FALSE)) | K9: ='INVENTARIO INICIAL'!K9 -> 0 | L9: ='INVENTARIO INICIAL'!L9 -> 0 | M9: ='INVENTARIO INICIAL'!M9 -> 0 | N9: ='INVENTARIO INICIAL'!N9 -> 0 | O9: ='INVENTARIO INICIAL'!O9 -> 0 | P9: ='INVENTARIO INICIAL'!P9 -> 0 | Q9: ='INVENTARIO INICIAL'!Q9 -> 0 | R9: ='INVENTARIO INICIAL'!R9 -> 0 | S9: ='Reporte Septiembre 2026'!AF9 -> 0 | AF9: =IF(AI9>=AJ9,IF(AK9>=0,IF(AJ9>=0,AK9,"Error"))) -> 0 | AG9: ='Reporte Septiembre 2026'!AG9 -> 0 | AH9: =AF9*AG9 -> 0 | AI9: =S9+T9 -> 0 | AJ9: =U9+V9+W9+X9+Y9+AB9 -> 0 | AK9: =AI9-AJ9 -> 0 | AL9: Diciembre | AN9: ='INVENTARIO INICIAL'!X9 -> 0
A10: ='INVENTARIO INICIAL'!A10 -> Inventario | B10: ='INVENTARIO INICIAL'!B10 -> 0 | C10: =IF(B10=0,"",VLOOKUP(B10,Datos!$H$2:$K$39,2,FALSE)) | D10: =IF(B10=0,"",VLOOKUP(B10,Datos!$H$2:$K$39,3,FALSE)) | E10: =IF(B10=0,"",VLOOKUP(B10,Datos!$H$2:$K$39,4,FALSE)) | F10: ='INVENTARIO INICIAL'!F10 -> 0 | G10: ='INVENTARIO INICIAL'!G10 -> 0 | H10: ='INVENTARIO INICIAL'!H10 -> 0 | I10: =IF(H10=0,"",VLOOKUP(H10,Datos!$B$2:$D$908,2,FALSE)) | J10: =IF(H10=0,"",VLOOKUP(H10,Datos!$B$2:$D$908,3,FALSE)) | K10: ='INVENTARIO INICIAL'!K10 -> 0 | L10: ='INVENTARIO INICIAL'!L10 -> 0 | M10: ='INVENTARIO INICIAL'!M10 -> 0 | N10: ='INVENTARIO INICIAL'!N10 -> 0 | O10: ='INVENTARIO INICIAL'!O10 -> 0 | P10: ='INVENTARIO INICIAL'!P10 -> 0 | Q10: ='INVENTARIO INICIAL'!Q10 -> 0 | R10: ='INVENTARIO INICIAL'!R10 -> 0 | S10: ='Reporte Septiembre 2026'!AF10 -> 0 | AF10: =IF(AI10>=AJ10,IF(AK10>=0,IF(AJ10>=0,AK10,"Error"))) -> 0 | AG10: ='Reporte Septiembre 2026'!AG10 -> 0 | AH10: =AF10*AG10 -> 0 | AI10: =S10+T10 -> 0 | AJ10: =U10+V10+W10+X10+Y10+AB10 -> 0 | AK10: =AI10-AJ10 -> 0 | AL10: Diciembre | AN10: ='INVENTARIO INICIAL'!X10 -> 0
A11: ='INVENTARIO INICIAL'!A11 -> Inventario | B11: ='INVENTARIO INICIAL'!B11 -> 0 | C11: =IF(B11=0,"",VLOOKUP(B11,Datos!$H$2:$K$39,2,FALSE)) | D11: =IF(B11=0,"",VLOOKUP(B11,Datos!$H$2:$K$39,3,FALSE)) | E11: =IF(B11=0,"",VLOOKUP(B11,Datos!$H$2:$K$39,4,FALSE)) | F11: ='INVENTARIO INICIAL'!F11 -> 0 | G11: ='INVENTARIO INICIAL'!G11 -> 0 | H11: ='INVENTARIO INICIAL'!H11 -> 0 | I11: =IF(H11=0,"",VLOOKUP(H11,Datos!$B$2:$D$908,2,FALSE)) | J11: =IF(H11=0,"",VLOOKUP(H11,Datos!$B$2:$D$908,3,FALSE)) | K11: ='INVENTARIO INICIAL'!K11 -> 0 | L11: ='INVENTARIO INICIAL'!L11 -> 0 | M11: ='INVENTARIO INICIAL'!M11 -> 0 | N11: ='INVENTARIO INICIAL'!N11 -> 0 | O11: ='INVENTARIO INICIAL'!O11 -> 0 | P11: ='INVENTARIO INICIAL'!P11 -> 0 | Q11: ='INVENTARIO INICIAL'!Q11 -> 0 | R11: ='INVENTARIO INICIAL'!R11 -> 0 | S11: ='Reporte Septiembre 2026'!AF11 -> 0 | AF11: =IF(AI11>=AJ11,IF(AK11>=0,IF(AJ11>=0,AK11,"Error"))) -> 0 | AG11: ='Reporte Septiembre 2026'!AG11 -> 0 | AH11: =AF11*AG11 -> 0 | AI11: =S11+T11 -> 0 | AJ11: =U11+V11+W11+X11+Y11+AB11 -> 0 | AK11: =AI11-AJ11 -> 0 | AL11: Diciembre | AN11: ='INVENTARIO INICIAL'!X11 -> 0
A12: ='INVENTARIO INICIAL'!A12 -> Inventario | B12: ='INVENTARIO INICIAL'!B12 -> 0 | C12: =IF(B12=0,"",VLOOKUP(B12,Datos!$H$2:$K$39,2,FALSE)) | D12: =IF(B12=0,"",VLOOKUP(B12,Datos!$H$2:$K$39,3,FALSE)) | E12: =IF(B12=0,"",VLOOKUP(B12,Datos!$H$2:$K$39,4,FALSE)) | F12: ='INVENTARIO INICIAL'!F12 -> 0 | G12: ='INVENTARIO INICIAL'!G12 -> 0 | H12: ='INVENTARIO INICIAL'!H12 -> 0 | I12: =IF(H12=0,"",VLOOKUP(H12,Datos!$B$2:$D$908,2,FALSE)) | J12: =IF(H12=0,"",VLOOKUP(H12,Datos!$B$2:$D$908,3,FALSE)) | K12: ='INVENTARIO INICIAL'!K12 -> 0 | L12: ='INVENTARIO INICIAL'!L12 -> 0 | M12: ='INVENTARIO INICIAL'!M12 -> 0 | N12: ='INVENTARIO INICIAL'!N12 -> 0 | O12: ='INVENTARIO INICIAL'!O12 -> 0 | P12: ='INVENTARIO INICIAL'!P12 -> 0 | Q12: ='INVENTARIO INICIAL'!Q12 -> 0 | R12: ='INVENTARIO INICIAL'!R12 -> 0 | S12: ='Reporte Septiembre 2026'!AF12 -> 0 | AF12: =IF(AI12>=AJ12,IF(AK12>=0,IF(AJ12>=0,AK12,"Error"))) -> 0 | AG12: ='Reporte Septiembre 2026'!AG12 -> 0 | AH12: =AF12*AG12 -> 0 | AI12: =S12+T12 -> 0 | AJ12: =U12+V12+W12+X12+Y12+AB12 -> 0 | AK12: =AI12-AJ12 -> 0 | AL12: Diciembre | AN12: ='INVENTARIO INICIAL'!X12 -> 0
A13: ='INVENTARIO INICIAL'!A13 -> Inventario | B13: ='INVENTARIO INICIAL'!B13 -> 0 | C13: =IF(B13=0,"",VLOOKUP(B13,Datos!$H$2:$K$39,2,FALSE)) | D13: =IF(B13=0,"",VLOOKUP(B13,Datos!$H$2:$K$39,3,FALSE)) | E13: =IF(B13=0,"",VLOOKUP(B13,Datos!$H$2:$K$39,4,FALSE)) | F13: ='INVENTARIO INICIAL'!F13 -> 0 | G13: ='INVENTARIO INICIAL'!G13 -> 0 | H13: ='INVENTARIO INICIAL'!H13 -> 0 | I13: =IF(H13=0,"",VLOOKUP(H13,Datos!$B$2:$D$908,2,FALSE)) | J13: =IF(H13=0,"",VLOOKUP(H13,Datos!$B$2:$D$908,3,FALSE)) | K13: ='INVENTARIO INICIAL'!K13 -> 0 | L13: ='INVENTARIO INICIAL'!L13 -> 0 | M13: ='INVENTARIO INICIAL'!M13 -> 0 | N13: ='INVENTARIO INICIAL'!N13 -> 0 | O13: ='INVENTARIO INICIAL'!O13 -> 0 | P13: ='INVENTARIO INICIAL'!P13 -> 0 | Q13: ='INVENTARIO INICIAL'!Q13 -> 0 | R13: ='INVENTARIO INICIAL'!R13 -> 0 | S13: ='Reporte Septiembre 2026'!AF13 -> 0 | AF13: =IF(AI13>=AJ13,IF(AK13>=0,IF(AJ13>=0,AK13,"Error"))) -> 0 | AG13: ='Reporte Septiembre 2026'!AG13 -> 0 | AH13: =AF13*AG13 -> 0 | AI13: =S13+T13 -> 0 | AJ13: =U13+V13+W13+X13+Y13+AB13 -> 0 | AK13: =AI13-AJ13 -> 0 | AL13: Diciembre | AN13: ='INVENTARIO INICIAL'!X13 -> 0
A14: ='INVENTARIO INICIAL'!A14 -> Inventario | B14: ='INVENTARIO INICIAL'!B14 -> 0 | C14: =IF(B14=0,"",VLOOKUP(B14,Datos!$H$2:$K$39,2,FALSE)) | D14: =IF(B14=0,"",VLOOKUP(B14,Datos!$H$2:$K$39,3,FALSE)) | E14: =IF(B14=0,"",VLOOKUP(B14,Datos!$H$2:$K$39,4,FALSE)) | F14: ='INVENTARIO INICIAL'!F14 -> 0 | G14: ='INVENTARIO INICIAL'!G14 -> 0 | H14: ='INVENTARIO INICIAL'!H14 -> 0 | I14: =IF(H14=0,"",VLOOKUP(H14,Datos!$B$2:$D$908,2,FALSE)) | J14: =IF(H14=0,"",VLOOKUP(H14,Datos!$B$2:$D$908,3,FALSE)) | K14: ='INVENTARIO INICIAL'!K14 -> 0 | L14: ='INVENTARIO INICIAL'!L14 -> 0 | M14: ='INVENTARIO INICIAL'!M14 -> 0 | N14: ='INVENTARIO INICIAL'!N14 -> 0 | O14: ='INVENTARIO INICIAL'!O14 -> 0 | P14: ='INVENTARIO INICIAL'!P14 -> 0 | Q14: ='INVENTARIO INICIAL'!Q14 -> 0 | R14: ='INVENTARIO INICIAL'!R14 -> 0 | S14: ='Reporte Septiembre 2026'!AF14 -> 0 | AF14: =IF(AI14>=AJ14,IF(AK14>=0,IF(AJ14>=0,AK14,"Error"))) -> 0 | AG14: ='Reporte Septiembre 2026'!AG14 -> 0 | AH14: =AF14*AG14 -> 0 | AI14: =S14+T14 -> 0 | AJ14: =U14+V14+W14+X14+Y14+AB14 -> 0 | AK14: =AI14-AJ14 -> 0 | AL14: Diciembre | AN14: ='INVENTARIO INICIAL'!X14 -> 0
A15: ='INVENTARIO INICIAL'!A15 -> Inventario | B15: ='INVENTARIO INICIAL'!B15 -> 0 | C15: =IF(B15=0,"",VLOOKUP(B15,Datos!$H$2:$K$39,2,FALSE)) | D15: =IF(B15=0,"",VLOOKUP(B15,Datos!$H$2:$K$39,3,FALSE)) | E15: =IF(B15=0,"",VLOOKUP(B15,Datos!$H$2:$K$39,4,FALSE)) | F15: ='INVENTARIO INICIAL'!F15 -> 0 | G15: ='INVENTARIO INICIAL'!G15 -> 0 | H15: ='INVENTARIO INICIAL'!H15 -> 0 | I15: =IF(H15=0,"",VLOOKUP(H15,Datos!$B$2:$D$908,2,FALSE)) | J15: =IF(H15=0,"",VLOOKUP(H15,Datos!$B$2:$D$908,3,FALSE)) | K15: ='INVENTARIO INICIAL'!K15 -> 0 | L15: ='INVENTARIO INICIAL'!L15 -> 0 | M15: ='INVENTARIO INICIAL'!M15 -> 0 | N15: ='INVENTARIO INICIAL'!N15 -> 0 | O15: ='INVENTARIO INICIAL'!O15 -> 0 | P15: ='INVENTARIO INICIAL'!P15 -> 0 | Q15: ='INVENTARIO INICIAL'!Q15 -> 0 | R15: ='INVENTARIO INICIAL'!R15 -> 0 | S15: ='Reporte Septiembre 2026'!AF15 -> 0 | AF15: =IF(AI15>=AJ15,IF(AK15>=0,IF(AJ15>=0,AK15,"Error"))) -> 0 | AG15: ='Reporte Septiembre 2026'!AG15 -> 0 | AH15: =AF15*AG15 -> 0 | AI15: =S15+T15 -> 0 | AJ15: =U15+V15+W15+X15+Y15+AB15 -> 0 | AK15: =AI15-AJ15 -> 0 | AL15: Diciembre | AN15: ='INVENTARIO INICIAL'!X15 -> 0
A16: ='INVENTARIO INICIAL'!A16 -> Inventario | B16: ='INVENTARIO INICIAL'!B16 -> 0 | C16: =IF(B16=0,"",VLOOKUP(B16,Datos!$H$2:$K$39,2,FALSE)) | D16: =IF(B16=0,"",VLOOKUP(B16,Datos!$H$2:$K$39,3,FALSE)) | E16: =IF(B16=0,"",VLOOKUP(B16,Datos!$H$2:$K$39,4,FALSE)) | F16: ='INVENTARIO INICIAL'!F16 -> 0 | G16: ='INVENTARIO INICIAL'!G16 -> 0 | H16: ='INVENTARIO INICIAL'!H16 -> 0 | I16: =IF(H16=0,"",VLOOKUP(H16,Datos!$B$2:$D$908,2,FALSE)) | J16: =IF(H16=0,"",VLOOKUP(H16,Datos!$B$2:$D$908,3,FALSE)) | K16: ='INVENTARIO INICIAL'!K16 -> 0 | L16: ='INVENTARIO INICIAL'!L16 -> 0 | M16: ='INVENTARIO INICIAL'!M16 -> 0 | N16: ='INVENTARIO INICIAL'!N16 -> 0 | O16: ='INVENTARIO INICIAL'!O16 -> 0 | P16: ='INVENTARIO INICIAL'!P16 -> 0 | Q16: ='INVENTARIO INICIAL'!Q16 -> 0 | R16: ='INVENTARIO INICIAL'!R16 -> 0 | S16: ='Reporte Septiembre 2026'!AF16 -> 0 | AF16: =IF(AI16>=AJ16,IF(AK16>=0,IF(AJ16>=0,AK16,"Error"))) -> 0 | AG16: ='Reporte Septiembre 2026'!AG16 -> 0 | AH16: =AF16*AG16 -> 0 | AI16: =S16+T16 -> 0 | AJ16: =U16+V16+W16+X16+Y16+AB16 -> 0 | AK16: =AI16-AJ16 -> 0 | AL16: Diciembre | AN16: ='INVENTARIO INICIAL'!X16 -> 0
A17: ='INVENTARIO INICIAL'!A17 -> Inventario | B17: ='INVENTARIO INICIAL'!B17 -> 0 | C17: =IF(B17=0,"",VLOOKUP(B17,Datos!$H$2:$K$39,2,FALSE)) | D17: =IF(B17=0,"",VLOOKUP(B17,Datos!$H$2:$K$39,3,FALSE)) | E17: =IF(B17=0,"",VLOOKUP(B17,Datos!$H$2:$K$39,4,FALSE)) | F17: ='INVENTARIO INICIAL'!F17 -> 0 | G17: ='INVENTARIO INICIAL'!G17 -> 0 | H17: ='INVENTARIO INICIAL'!H17 -> 0 | I17: =IF(H17=0,"",VLOOKUP(H17,Datos!$B$2:$D$908,2,FALSE)) | J17: =IF(H17=0,"",VLOOKUP(H17,Datos!$B$2:$D$908,3,FALSE)) | K17: ='INVENTARIO INICIAL'!K17 -> 0 | L17: ='INVENTARIO INICIAL'!L17 -> 0 | M17: ='INVENTARIO INICIAL'!M17 -> 0 | N17: ='INVENTARIO INICIAL'!N17 -> 0 | O17: ='INVENTARIO INICIAL'!O17 -> 0 | P17: ='INVENTARIO INICIAL'!P17 -> 0 | Q17: ='INVENTARIO INICIAL'!Q17 -> 0 | R17: ='INVENTARIO INICIAL'!R17 -> 0 | S17: ='Reporte Septiembre 2026'!AF17 -> 0 | AF17: =IF(AI17>=AJ17,IF(AK17>=0,IF(AJ17>=0,AK17,"Error"))) -> 0 | AG17: ='Reporte Septiembre 2026'!AG17 -> 0 | AH17: =AF17*AG17 -> 0 | AI17: =S17+T17 -> 0 | AJ17: =U17+V17+W17+X17+Y17+AB17 -> 0 | AK17: =AI17-AJ17 -> 0 | AL17: Diciembre | AN17: ='INVENTARIO INICIAL'!X17 -> 0
A18: ='INVENTARIO INICIAL'!A18 -> Inventario | B18: ='INVENTARIO INICIAL'!B18 -> 0 | C18: =IF(B18=0,"",VLOOKUP(B18,Datos!$H$2:$K$39,2,FALSE)) | D18: =IF(B18=0,"",VLOOKUP(B18,Datos!$H$2:$K$39,3,FALSE)) | E18: =IF(B18=0,"",VLOOKUP(B18,Datos!$H$2:$K$39,4,FALSE)) | F18: ='INVENTARIO INICIAL'!F18 -> 0 | G18: ='INVENTARIO INICIAL'!G18 -> 0 | H18: ='INVENTARIO INICIAL'!H18 -> 0 | I18: =IF(H18=0,"",VLOOKUP(H18,Datos!$B$2:$D$908,2,FALSE)) | J18: =IF(H18=0,"",VLOOKUP(H18,Datos!$B$2:$D$908,3,FALSE)) | K18: ='INVENTARIO INICIAL'!K18 -> 0 | L18: ='INVENTARIO INICIAL'!L18 -> 0 | M18: ='INVENTARIO INICIAL'!M18 -> 0 | N18: ='INVENTARIO INICIAL'!N18 -> 0 | O18: ='INVENTARIO INICIAL'!O18 -> 0 | P18: ='INVENTARIO INICIAL'!P18 -> 0 | Q18: ='INVENTARIO INICIAL'!Q18 -> 0 | R18: ='INVENTARIO INICIAL'!R18 -> 0 | S18: ='Reporte Septiembre 2026'!AF18 -> 0 | AF18: =IF(AI18>=AJ18,IF(AK18>=0,IF(AJ18>=0,AK18,"Error"))) -> 0 | AG18: ='Reporte Septiembre 2026'!AG18 -> 0 | AH18: =AF18*AG18 -> 0 | AI18: =S18+T18 -> 0 | AJ18: =U18+V18+W18+X18+Y18+AB18 -> 0 | AK18: =AI18-AJ18 -> 0 | AL18: Diciembre | AN18: ='INVENTARIO INICIAL'!X18 -> 0
... A360: ='INVENTARIO INICIAL'!A360 -> Inventario | B360: ='INVENTARIO INICIAL'!B360 -> 0 | C360: =IF(B360=0,"",VLOOKUP(B360,Datos!$H$2:$K$39,2,FALSE)) | D360: =IF(B360=0,"",VLOOKUP(B360,Datos!$H$2:$K$39,3,FALSE)) | E360: =IF(B360=0,"",VLOOKUP(B360,Datos!$H$2:$K$39,4,FALSE)) | F360: ='INVENTARIO INICIAL'!F360 -> 0 | G360: ='INVENTARIO INICIAL'!G360 -> 0 | H360: ='INVENTARIO INICIAL'!H360 -> 0 | I360: =IF(H360=0,"",VLOOKUP(H360,Datos!$B$2:$D$908,2,FALSE)) | J360: =IF(H360=0,"",VLOOKUP(H360,Datos!$B$2:$D$908,3,FALSE)) | K360: ='INVENTARIO INICIAL'!K360 -> 0 | L360: ='INVENTARIO INICIAL'!L360 -> 0 | M360: ='INVENTARIO INICIAL'!M360 -> 0 | N360: ='INVENTARIO INICIAL'!N360 -> 0 | O360: ='INVENTARIO INICIAL'!O360 -> 0 | P360: ='INVENTARIO INICIAL'!P360 -> 0 | Q360: ='INVENTARIO INICIAL'!Q360 -> 0 | R360: ='INVENTARIO INICIAL'!R360 -> 0 | S360: ='Reporte Septiembre 2026'!AF360 -> 0 | AF360: =IF(AI360>=AJ360,IF(AK360>=0,IF(AJ360>=0,AK360,"Error"))) -> 0 | AG360: ='Reporte Septiembre 2026'!AG360 -> 0 | AH360: =AF360*AG360 -> 0 | AI360: =S360+T360 -> 0 | AJ360: =U360+V360+W360+X360+Y360+AB360 -> 0 | AK360: =AI360-AJ360 -> 0 | AL360: Diciembre | AN360: ='INVENTARIO INICIAL'!X360 -> 0
A361: ='Reporte Septiembre 2026'!A361 -> Ingresos | B361: ='Reporte Septiembre 2026'!B361 -> 0 | C361: =IF(B361=0,"",VLOOKUP(B361,Datos!$H$2:$K$39,2,FALSE)) | D361: =IF(B361=0,"",VLOOKUP(B361,Datos!$H$2:$K$39,3,FALSE)) | E361: =IF(B361=0,"",VLOOKUP(B361,Datos!$H$2:$K$39,4,FALSE)) | F361: ='Reporte Septiembre 2026'!F361 -> 0 | G361: ='Reporte Septiembre 2026'!G361 -> 0 | H361: ='Reporte Septiembre 2026'!H361 -> 0 | I361: =IF(H361=0,"",VLOOKUP(H361,Datos!$B$2:$D$891,2,FALSE)) | J361: =IF(H361=0,"",VLOOKUP(H361,Datos!$B$2:$D$891,3,FALSE)) | K361: ='Reporte Septiembre 2026'!K361 -> 0 | L361: ='Reporte Septiembre 2026'!L361 -> 0 | M361: ='Reporte Septiembre 2026'!M361 -> 0 | N361: ='Reporte Septiembre 2026'!N361 -> 0 | O361: ='Reporte Septiembre 2026'!O361 -> 0 | P361: ='Reporte Septiembre 2026'!P361 -> 0 | Q361: ='Reporte Septiembre 2026'!Q361 -> 0 | R361: ='Reporte Septiembre 2026'!R361 -> 0 | S361: ='Reporte Septiembre 2026'!AF361 -> 0 | AF361: =IF(AI361>=AJ361,IF(AK361>=0,IF(AJ361>=0,AK361,"Error"))) -> 0 | AG361: ='Reporte Septiembre 2026'!AG361 -> 0 | AH361: =AF361*AG361 -> 0 | AI361: =S361+T361 -> 0 | AJ361: =U361+V361+W361+X361+Y361+AB361 -> 0 | AK361: =AI361-AJ361 -> 0 | AL361: Diciembre | AN361: ='Reporte Septiembre 2026'!AN361 -> 0
A362: ='Reporte Septiembre 2026'!A362 -> Ingresos | B362: ='Reporte Septiembre 2026'!B362 -> 0 | C362: =IF(B362=0,"",VLOOKUP(B362,Datos!$H$2:$K$39,2,FALSE)) | D362: =IF(B362=0,"",VLOOKUP(B362,Datos!$H$2:$K$39,3,FALSE)) | E362: =IF(B362=0,"",VLOOKUP(B362,Datos!$H$2:$K$39,4,FALSE)) | F362: ='Reporte Septiembre 2026'!F362 -> 0 | G362: ='Reporte Septiembre 2026'!G362 -> 0 | H362: ='Reporte Septiembre 2026'!H362 -> 0 | I362: =IF(H362=0,"",VLOOKUP(H362,Datos!$B$2:$D$891,2,FALSE)) | J362: =IF(H362=0,"",VLOOKUP(H362,Datos!$B$2:$D$891,3,FALSE)) | K362: ='Reporte Septiembre 2026'!K362 -> 0 | L362: ='Reporte Septiembre 2026'!L362 -> 0 | M362: ='Reporte Septiembre 2026'!M362 -> 0 | N362: ='Reporte Septiembre 2026'!N362 -> 0 | O362: ='Reporte Septiembre 2026'!O362 -> 0 | P362: ='Reporte Septiembre 2026'!P362 -> 0 | Q362: ='Reporte Septiembre 2026'!Q362 -> 0 | R362: ='Reporte Septiembre 2026'!R362 -> 0 | S362: ='Reporte Septiembre 2026'!AF362 -> 0 | AF362: =IF(AI362>=AJ362,IF(AK362>=0,IF(AJ362>=0,AK362,"Error"))) -> 0 | AG362: ='Reporte Septiembre 2026'!AG362 -> 0 | AH362: =AF362*AG362 -> 0 | AI362: =S362+T362 -> 0 | AJ362: =U362+V362+W362+X362+Y362+AB362 -> 0 | AK362: =AI362-AJ362 -> 0 | AL362: Diciembre | AN362: ='Reporte Septiembre 2026'!AN362 -> 0
A363: ='Reporte Septiembre 2026'!A363 -> Ingresos | B363: ='Reporte Septiembre 2026'!B363 -> 0 | C363: =IF(B363=0,"",VLOOKUP(B363,Datos!$H$2:$K$39,2,FALSE)) | D363: =IF(B363=0,"",VLOOKUP(B363,Datos!$H$2:$K$39,3,FALSE)) | E363: =IF(B363=0,"",VLOOKUP(B363,Datos!$H$2:$K$39,4,FALSE)) | F363: ='Reporte Septiembre 2026'!F363 -> 0 | G363: ='Reporte Septiembre 2026'!G363 -> 0 | H363: ='Reporte Septiembre 2026'!H363 -> 0 | I363: =IF(H363=0,"",VLOOKUP(H363,Datos!$B$2:$D$891,2,FALSE)) | J363: =IF(H363=0,"",VLOOKUP(H363,Datos!$B$2:$D$891,3,FALSE)) | K363: ='Reporte Septiembre 2026'!K363 -> 0 | L363: ='Reporte Septiembre 2026'!L363 -> 0 | M363: ='Reporte Septiembre 2026'!M363 -> 0 | N363: ='Reporte Septiembre 2026'!N363 -> 0 | O363: ='Reporte Septiembre 2026'!O363 -> 0 | P363: ='Reporte Septiembre 2026'!P363 -> 0 | Q363: ='Reporte Septiembre 2026'!Q363 -> 0 | R363: ='Reporte Septiembre 2026'!R363 -> 0 | S363: ='Reporte Septiembre 2026'!AF363 -> 0 | AF363: =IF(AI363>=AJ363,IF(AK363>=0,IF(AJ363>=0,AK363,"Error"))) -> 0 | AG363: ='Reporte Septiembre 2026'!AG363 -> 0 | AH363: =AF363*AG363 -> 0 | AI363: =S363+T363 -> 0 | AJ363: =U363+V363+W363+X363+Y363+AB363 -> 0 | AK363: =AI363-AJ363 -> 0 | AL363: Diciembre | AN363: ='Reporte Septiembre 2026'!AN363 -> 0
A364: ='Reporte Septiembre 2026'!A364 -> Ingresos | B364: ='Reporte Septiembre 2026'!B364 -> 0 | C364: =IF(B364=0,"",VLOOKUP(B364,Datos!$H$2:$K$39,2,FALSE)) | D364: =IF(B364=0,"",VLOOKUP(B364,Datos!$H$2:$K$39,3,FALSE)) | E364: =IF(B364=0,"",VLOOKUP(B364,Datos!$H$2:$K$39,4,FALSE)) | F364: ='Reporte Septiembre 2026'!F364 -> 0 | G364: ='Reporte Septiembre 2026'!G364 -> 0 | H364: ='Reporte Septiembre 2026'!H364 -> 0 | I364: =IF(H364=0,"",VLOOKUP(H364,Datos!$B$2:$D$891,2,FALSE)) | J364: =IF(H364=0,"",VLOOKUP(H364,Datos!$B$2:$D$891,3,FALSE)) | K364: ='Reporte Septiembre 2026'!K364 -> 0 | L364: ='Reporte Septiembre 2026'!L364 -> 0 | M364: ='Reporte Septiembre 2026'!M364 -> 0 | N364: ='Reporte Septiembre 2026'!N364 -> 0 | O364: ='Reporte Septiembre 2026'!O364 -> 0 | P364: ='Reporte Septiembre 2026'!P364 -> 0 | Q364: ='Reporte Septiembre 2026'!Q364 -> 0 | R364: ='Reporte Septiembre 2026'!R364 -> 0 | S364: ='Reporte Septiembre 2026'!AF364 -> 0 | AF364: =IF(AI364>=AJ364,IF(AK364>=0,IF(AJ364>=0,AK364,"Error"))) -> 0 | AG364: ='Reporte Septiembre 2026'!AG364 -> 0 | AH364: =AF364*AG364 -> 0 | AI364: =S364+T364 -> 0 | AJ364: =U364+V364+W364+X364+Y364+AB364 -> 0 | AK364: =AI364-AJ364 -> 0 | AL364: Diciembre | AN364: ='Reporte Septiembre 2026'!AN364 -> 0
A365: ='Reporte Septiembre 2026'!A365 -> Ingresos | B365: ='Reporte Septiembre 2026'!B365 -> 0 | C365: =IF(B365=0,"",VLOOKUP(B365,Datos!$H$2:$K$39,2,FALSE)) | D365: =IF(B365=0,"",VLOOKUP(B365,Datos!$H$2:$K$39,3,FALSE)) | E365: =IF(B365=0,"",VLOOKUP(B365,Datos!$H$2:$K$39,4,FALSE)) | F365: ='Reporte Septiembre 2026'!F365 -> 0 | G365: ='Reporte Septiembre 2026'!G365 -> 0 | H365: ='Reporte Septiembre 2026'!H365 -> 0 | I365: =IF(H365=0,"",VLOOKUP(H365,Datos!$B$2:$D$891,2,FALSE)) | J365: =IF(H365=0,"",VLOOKUP(H365,Datos!$B$2:$D$891,3,FALSE)) | K365: ='Reporte Septiembre 2026'!K365 -> 0 | L365: ='Reporte Septiembre 2026'!L365 -> 0 | M365: ='Reporte Septiembre 2026'!M365 -> 0 | N365: ='Reporte Septiembre 2026'!N365 -> 0 | O365: ='Reporte Septiembre 2026'!O365 -> 0 | P365: ='Reporte Septiembre 2026'!P365 -> 0 | Q365: ='Reporte Septiembre 2026'!Q365 -> 0 | R365: ='Reporte Septiembre 2026'!R365 -> 0 | S365: ='Reporte Septiembre 2026'!AF365 -> 0 | AF365: =IF(AI365>=AJ365,IF(AK365>=0,IF(AJ365>=0,AK365,"Error"))) -> 0 | AG365: ='Reporte Septiembre 2026'!AG365 -> 0 | AH365: =AF365*AG365 -> 0 | AI365: =S365+T365 -> 0 | AJ365: =U365+V365+W365+X365+Y365+AB365 -> 0 | AK365: =AI365-AJ365 -> 0 | AL365: Diciembre | AN365: ='Reporte Septiembre 2026'!AN365 -> 0
A366: ='Reporte Septiembre 2026'!A366 -> Ingresos | B366: ='Reporte Septiembre 2026'!B366 -> 0 | C366: =IF(B366=0,"",VLOOKUP(B366,Datos!$H$2:$K$39,2,FALSE)) | D366: =IF(B366=0,"",VLOOKUP(B366,Datos!$H$2:$K$39,3,FALSE)) | E366: =IF(B366=0,"",VLOOKUP(B366,Datos!$H$2:$K$39,4,FALSE)) | F366: ='Reporte Septiembre 2026'!F366 -> 0 | G366: ='Reporte Septiembre 2026'!G366 -> 0 | H366: ='Reporte Septiembre 2026'!H366 -> 0 | I366: =IF(H366=0,"",VLOOKUP(H366,Datos!$B$2:$D$891,2,FALSE)) | J366: =IF(H366=0,"",VLOOKUP(H366,Datos!$B$2:$D$891,3,FALSE)) | K366: ='Reporte Septiembre 2026'!K366 -> 0 | L366: ='Reporte Septiembre 2026'!L366 -> 0 | M366: ='Reporte Septiembre 2026'!M366 -> 0 | N366: ='Reporte Septiembre 2026'!N366 -> 0 | O366: ='Reporte Septiembre 2026'!O366 -> 0 | P366: ='Reporte Septiembre 2026'!P366 -> 0 | Q366: ='Reporte Septiembre 2026'!Q366 -> 0 | R366: ='Reporte Septiembre 2026'!R366 -> 0 | S366: ='Reporte Septiembre 2026'!AF366 -> 0 | AF366: =IF(AI366>=AJ366,IF(AK366>=0,IF(AJ366>=0,AK366,"Error"))) -> 0 | AG366: ='Reporte Septiembre 2026'!AG366 -> 0 | AH366: =AF366*AG366 -> 0 | AI366: =S366+T366 -> 0 | AJ366: =U366+V366+W366+X366+Y366+AB366 -> 0 | AK366: =AI366-AJ366 -> 0 | AL366: Diciembre | AN366: ='Reporte Septiembre 2026'!AN366 -> 0
A367: ='Reporte Septiembre 2026'!A367 -> Ingresos | B367: ='Reporte Septiembre 2026'!B367 -> 0 | C367: =IF(B367=0,"",VLOOKUP(B367,Datos!$H$2:$K$39,2,FALSE)) | D367: =IF(B367=0,"",VLOOKUP(B367,Datos!$H$2:$K$39,3,FALSE)) | E367: =IF(B367=0,"",VLOOKUP(B367,Datos!$H$2:$K$39,4,FALSE)) | F367: ='Reporte Septiembre 2026'!F367 -> 0 | G367: ='Reporte Septiembre 2026'!G367 -> 0 | H367: ='Reporte Septiembre 2026'!H367 -> 0 | I367: =IF(H367=0,"",VLOOKUP(H367,Datos!$B$2:$D$891,2,FALSE)) | J367: =IF(H367=0,"",VLOOKUP(H367,Datos!$B$2:$D$891,3,FALSE)) | K367: ='Reporte Septiembre 2026'!K367 -> 0 | L367: ='Reporte Septiembre 2026'!L367 -> 0 | M367: ='Reporte Septiembre 2026'!M367 -> 0 | N367: ='Reporte Septiembre 2026'!N367 -> 0 | O367: ='Reporte Septiembre 2026'!O367 -> 0 | P367: ='Reporte Septiembre 2026'!P367 -> 0 | Q367: ='Reporte Septiembre 2026'!Q367 -> 0 | R367: ='Reporte Septiembre 2026'!R367 -> 0 | S367: ='Reporte Septiembre 2026'!AF367 -> 0 | AF367: =IF(AI367>=AJ367,IF(AK367>=0,IF(AJ367>=0,AK367,"Error"))) -> 0 | AG367: ='Reporte Septiembre 2026'!AG367 -> 0 | AH367: =AF367*AG367 -> 0 | AI367: =S367+T367 -> 0 | AJ367: =U367+V367+W367+X367+Y367+AB367 -> 0 | AK367: =AI367-AJ367 -> 0 | AL367: Diciembre | AN367: ='Reporte Septiembre 2026'!AN367 -> 0
A368: ='Reporte Septiembre 2026'!A368 -> Ingresos | B368: ='Reporte Septiembre 2026'!B368 -> 0 | C368: =IF(B368=0,"",VLOOKUP(B368,Datos!$H$2:$K$39,2,FALSE)) | D368: =IF(B368=0,"",VLOOKUP(B368,Datos!$H$2:$K$39,3,FALSE)) | E368: =IF(B368=0,"",VLOOKUP(B368,Datos!$H$2:$K$39,4,FALSE)) | F368: ='Reporte Septiembre 2026'!F368 -> 0 | G368: ='Reporte Septiembre 2026'!G368 -> 0 | H368: ='Reporte Septiembre 2026'!H368 -> 0 | I368: =IF(H368=0,"",VLOOKUP(H368,Datos!$B$2:$D$891,2,FALSE)) | J368: =IF(H368=0,"",VLOOKUP(H368,Datos!$B$2:$D$891,3,FALSE)) | K368: ='Reporte Septiembre 2026'!K368 -> 0 | L368: ='Reporte Septiembre 2026'!L368 -> 0 | M368: ='Reporte Septiembre 2026'!M368 -> 0 | N368: ='Reporte Septiembre 2026'!N368 -> 0 | O368: ='Reporte Septiembre 2026'!O368 -> 0 | P368: ='Reporte Septiembre 2026'!P368 -> 0 | Q368: ='Reporte Septiembre 2026'!Q368 -> 0 | R368: ='Reporte Septiembre 2026'!R368 -> 0 | S368: ='Reporte Septiembre 2026'!AF368 -> 0 | AF368: =IF(AI368>=AJ368,IF(AK368>=0,IF(AJ368>=0,AK368,"Error"))) -> 0 | AG368: ='Reporte Septiembre 2026'!AG368 -> 0 | AH368: =AF368*AG368 -> 0 | AI368: =S368+T368 -> 0 | AJ368: =U368+V368+W368+X368+Y368+AB368 -> 0 | AK368: =AI368-AJ368 -> 0 | AL368: Diciembre | AN368: ='Reporte Septiembre 2026'!AN368 -> 0
A369: ='Reporte Septiembre 2026'!A369 -> Ingresos | B369: ='Reporte Septiembre 2026'!B369 -> 0 | C369: =IF(B369=0,"",VLOOKUP(B369,Datos!$H$2:$K$39,2,FALSE)) | D369: =IF(B369=0,"",VLOOKUP(B369,Datos!$H$2:$K$39,3,FALSE)) | E369: =IF(B369=0,"",VLOOKUP(B369,Datos!$H$2:$K$39,4,FALSE)) | F369: ='Reporte Septiembre 2026'!F369 -> 0 | G369: ='Reporte Septiembre 2026'!G369 -> 0 | H369: ='Reporte Septiembre 2026'!H369 -> 0 | I369: =IF(H369=0,"",VLOOKUP(H369,Datos!$B$2:$D$891,2,FALSE)) | J369: =IF(H369=0,"",VLOOKUP(H369,Datos!$B$2:$D$891,3,FALSE)) | K369: ='Reporte Septiembre 2026'!K369 -> 0 | L369: ='Reporte Septiembre 2026'!L369 -> 0 | M369: ='Reporte Septiembre 2026'!M369 -> 0 | N369: ='Reporte Septiembre 2026'!N369 -> 0 | O369: ='Reporte Septiembre 2026'!O369 -> 0 | P369: ='Reporte Septiembre 2026'!P369 -> 0 | Q369: ='Reporte Septiembre 2026'!Q369 -> 0 | R369: ='Reporte Septiembre 2026'!R369 -> 0 | S369: ='Reporte Septiembre 2026'!AF369 -> 0 | AF369: =IF(AI369>=AJ369,IF(AK369>=0,IF(AJ369>=0,AK369,"Error"))) -> 0 | AG369: ='Reporte Septiembre 2026'!AG369 -> 0 | AH369: =AF369*AG369 -> 0 | AI369: =S369+T369 -> 0 | AJ369: =U369+V369+W369+X369+Y369+AB369 -> 0 | AK369: =AI369-AJ369 -> 0 | AL369: Diciembre | AN369: ='Reporte Septiembre 2026'!AN369 -> 0
A370: ='Reporte Septiembre 2026'!A370 -> Ingresos | B370: ='Reporte Septiembre 2026'!B370 -> 0 | C370: =IF(B370=0,"",VLOOKUP(B370,Datos!$H$2:$K$39,2,FALSE)) | D370: =IF(B370=0,"",VLOOKUP(B370,Datos!$H$2:$K$39,3,FALSE)) | E370: =IF(B370=0,"",VLOOKUP(B370,Datos!$H$2:$K$39,4,FALSE)) | F370: ='Reporte Septiembre 2026'!F370 -> 0 | G370: ='Reporte Septiembre 2026'!G370 -> 0 | H370: ='Reporte Septiembre 2026'!H370 -> 0 | I370: =IF(H370=0,"",VLOOKUP(H370,Datos!$B$2:$D$891,2,FALSE)) | J370: =IF(H370=0,"",VLOOKUP(H370,Datos!$B$2:$D$891,3,FALSE)) | K370: ='Reporte Septiembre 2026'!K370 -> 0 | L370: ='Reporte Septiembre 2026'!L370 -> 0 | M370: ='Reporte Septiembre 2026'!M370 -> 0 | N370: ='Reporte Septiembre 2026'!N370 -> 0 | O370: ='Reporte Septiembre 2026'!O370 -> 0 | P370: ='Reporte Septiembre 2026'!P370 -> 0 | Q370: ='Reporte Septiembre 2026'!Q370 -> 0 | R370: ='Reporte Septiembre 2026'!R370 -> 0 | S370: ='Reporte Septiembre 2026'!AF370 -> 0 | AF370: =IF(AI370>=AJ370,IF(AK370>=0,IF(AJ370>=0,AK370,"Error"))) -> 0 | AG370: ='Reporte Septiembre 2026'!AG370 -> 0 | AH370: =AF370*AG370 -> 0 | AI370: =S370+T370 -> 0 | AJ370: =U370+V370+W370+X370+Y370+AB370 -> 0 | AK370: =AI370-AJ370 -> 0 | AL370: Diciembre | AN370: ='Reporte Septiembre 2026'!AN370 -> 0
A371: ='Reporte Septiembre 2026'!A371 -> Ingresos | B371: ='Reporte Septiembre 2026'!B371 -> 0 | C371: =IF(B371=0,"",VLOOKUP(B371,Datos!$H$2:$K$39,2,FALSE)) | D371: =IF(B371=0,"",VLOOKUP(B371,Datos!$H$2:$K$39,3,FALSE)) | E371: =IF(B371=0,"",VLOOKUP(B371,Datos!$H$2:$K$39,4,FALSE)) | F371: ='Reporte Septiembre 2026'!F371 -> 0 | G371: ='Reporte Septiembre 2026'!G371 -> 0 | H371: ='Reporte Septiembre 2026'!H371 -> 0 | I371: =IF(H371=0,"",VLOOKUP(H371,Datos!$B$2:$D$891,2,FALSE)) | J371: =IF(H371=0,"",VLOOKUP(H371,Datos!$B$2:$D$891,3,FALSE)) | K371: ='Reporte Septiembre 2026'!K371 -> 0 | L371: ='Reporte Septiembre 2026'!L371 -> 0 | M371: ='Reporte Septiembre 2026'!M371 -> 0 | N371: ='Reporte Septiembre 2026'!N371 -> 0 | O371: ='Reporte Septiembre 2026'!O371 -> 0 | P371: ='Reporte Septiembre 2026'!P371 -> 0 | Q371: ='Reporte Septiembre 2026'!Q371 -> 0 | R371: ='Reporte Septiembre 2026'!R371 -> 0 | S371: ='Reporte Septiembre 2026'!AF371 -> 0 | AF371: =IF(AI371>=AJ371,IF(AK371>=0,IF(AJ371>=0,AK371,"Error"))) -> 0 | AG371: ='Reporte Septiembre 2026'!AG371 -> 0 | AH371: =AF371*AG371 -> 0 | AI371: =S371+T371 -> 0 | AJ371: =U371+V371+W371+X371+Y371+AB371 -> 0 | AK371: =AI371-AJ371 -> 0 | AL371: Diciembre | AN371: ='Reporte Septiembre 2026'!AN371 -> 0
A372: ='Reporte Septiembre 2026'!A372 -> Ingresos | B372: ='Reporte Septiembre 2026'!B372 -> 0 | C372: =IF(B372=0,"",VLOOKUP(B372,Datos!$H$2:$K$39,2,FALSE)) | D372: =IF(B372=0,"",VLOOKUP(B372,Datos!$H$2:$K$39,3,FALSE)) | E372: =IF(B372=0,"",VLOOKUP(B372,Datos!$H$2:$K$39,4,FALSE)) | F372: ='Reporte Septiembre 2026'!F372 -> 0 | G372: ='Reporte Septiembre 2026'!G372 -> 0 | H372: ='Reporte Septiembre 2026'!H372 -> 0 | I372: =IF(H372=0,"",VLOOKUP(H372,Datos!$B$2:$D$891,2,FALSE)) | J372: =IF(H372=0,"",VLOOKUP(H372,Datos!$B$2:$D$891,3,FALSE)) | K372: ='Reporte Septiembre 2026'!K372 -> 0 | L372: ='Reporte Septiembre 2026'!L372 -> 0 | M372: ='Reporte Septiembre 2026'!M372 -> 0 | N372: ='Reporte Septiembre 2026'!N372 -> 0 | O372: ='Reporte Septiembre 2026'!O372 -> 0 | P372: ='Reporte Septiembre 2026'!P372 -> 0 | Q372: ='Reporte Septiembre 2026'!Q372 -> 0 | R372: ='Reporte Septiembre 2026'!R372 -> 0 | S372: ='Reporte Septiembre 2026'!AF372 -> 0 | AF372: =IF(AI372>=AJ372,IF(AK372>=0,IF(AJ372>=0,AK372,"Error"))) -> 0 | AG372: ='Reporte Septiembre 2026'!AG372 -> 0 | AH372: =AF372*AG372 -> 0 | AI372: =S372+T372 -> 0 | AJ372: =U372+V372+W372+X372+Y372+AB372 -> 0 | AK372: =AI372-AJ372 -> 0 | AL372: Diciembre | AN372: ='Reporte Septiembre 2026'!AN372 -> 0
... A490: ='Reporte Septiembre 2026'!A490 -> Ingresos | B490: ='Reporte Septiembre 2026'!B490 -> 0 | C490: =IF(B490=0,"",VLOOKUP(B490,Datos!$H$2:$K$39,2,FALSE)) | D490: =IF(B490=0,"",VLOOKUP(B490,Datos!$H$2:$K$39,3,FALSE)) | E490: =IF(B490=0,"",VLOOKUP(B490,Datos!$H$2:$K$39,4,FALSE)) | F490: ='Reporte Septiembre 2026'!F490 -> 0 | G490: ='Reporte Septiembre 2026'!G490 -> 0 | H490: ='Reporte Septiembre 2026'!H490 -> 0 | I490: =IF(H490=0,"",VLOOKUP(H490,Datos!$B$2:$D$891,2,FALSE)) | J490: =IF(H490=0,"",VLOOKUP(H490,Datos!$B$2:$D$891,3,FALSE)) | K490: ='Reporte Septiembre 2026'!K490 -> 0 | L490: ='Reporte Septiembre 2026'!L490 -> 0 | M490: ='Reporte Septiembre 2026'!M490 -> 0 | N490: ='Reporte Septiembre 2026'!N490 -> 0 | O490: ='Reporte Septiembre 2026'!O490 -> 0 | P490: ='Reporte Septiembre 2026'!P490 -> 0 | Q490: ='Reporte Septiembre 2026'!Q490 -> 0 | R490: ='Reporte Septiembre 2026'!R490 -> 0 | S490: ='Reporte Septiembre 2026'!AF490 -> 0 | AF490: =IF(AI490>=AJ490,IF(AK490>=0,IF(AJ490>=0,AK490,"Error"))) -> 0 | AG490: ='Reporte Septiembre 2026'!AG490 -> 0 | AH490: =AF490*AG490 -> 0 | AI490: =S490+T490 -> 0 | AJ490: =U490+V490+W490+X490+Y490+AB490 -> 0 | AK490: =AI490-AJ490 -> 0 | AL490: Diciembre | AN490: ='Reporte Septiembre 2026'!AN490 -> 0
A491: TOTAL Diciembre | R491: TOTAL | S491: =SUM(S7:S490) -> 0 | T491: =SUM(T7:T490) -> 0 | U491: =SUM(U7:U490) -> 0 | V491: =SUM(V7:V490) -> 0 | W491: =SUM(W7:W490) -> 0 | X491: =SUM(X7:X490) -> 0 | Y491: =SUM(Y7:Y490) -> 0 | AB491: =SUM(AB7:AB490) -> 0 | AF491: =SUM(AF7:AF490) -> 0 | AH491: =SUM(AH7:AH490) -> 0 | AI491: =SUM(AI7:AI490) -> 0 | AJ491: =SUM(AJ7:AJ490) -> 0 | AK491: =SUM(AK7:AK490) -> 0 | AL491: Diciembre

Sheet Datos
A1: N | B1: Nombre Científico | C1: Nombre Común | D1: Origen | E1: Hábito | G1: N° | H1: VIVERO, CENTRO DE ACONDICIONAMIENTO O ACOPIO | I1: UNIDAD ADMINISTRATIVA | J1: PROVINCIA | K1: COMUNA | M1: CONTENEDORES | O1: Tipo de Movimiento
A2: 1 | B2: Abelia x grandiflora | C2: Abelia | D2: Exótico | E2: Arbustivo | G2: 1 | H2: Vivero Las Maitas | I2: Región de Arica y Parinacota | J2: Arica | K2: Arica | M2: Bandeja_Speedling | O2: Baja de plantas
A3: 2 | B3: Abies alba | C3: Abeto blanco / Abeto común | D3: Exótico | E3: Arbóreo | G3: 2 | H3: Vivero Putre | I3: Región de Arica y Parinacota | J3: Parinacota | K3: Putre | M3: Bandeja_Tubetes | O3: Entregas por difusión
A4: 3 | B4: Abutilon incanum | C4: Pelotazo / Tronadora | D4: Exótico | E4: Arbustivo | G4: 3 | H4: Vivero Alejandro Caipa | I4: Región de Tarapacá | J4: Tamarugal | K4: Pozo Almonte | M4: Bolsas | O4: Entregas a Programas
A5: 4 | B5: Abutilon sp. | C5: Abutilón | D5: Exótico | E5: Arbustivo | G5: 4 | H5: Vivero Regional Antofagasta | I5: Región de Antofagasta | J5: Antofagasta | K5: Antofagasta | M5: Raíz_Desnuda | O5: Nuevo ingreso a inventario
A6: 5 | B6: Abutilon striatum | C6: Abutilón | D6: Exótico | E6: Arbustivo | G6: 5 | H6: Vivero Quillagua | I6: Región de Antofagasta | J6: Tocopilla | K6: María Elena | M6: Patrik | O6: Stock inventario
A7: 6 | B7: Acacia caven / Vachellia caven | C7: Espino | D7: Nativo | E7: Arbóreo | G7: 6 | H7: Vivero Copiapó | I7: Región de Atacama | J7: Copiapó | K7: Copiapó | O7: Traslado interno
A8: 7 | B8: Acacia cultriformis | C8: Acacia de hoja de cuchillo | D8: Exótico | E8: Arbustivo | G8: 7 | H8: Vivero Vallenar | I8: Región de Atacama | J8: Huasco | K8: Vallenar | M8: FUENTE DE ABASTECIMIENTO | O8: Venta
A9: 8 | B9: Acacia cyclops | C9: Acacia de costa | D9: Exótico | E9: Arbustivo | G9: 8 | H9: Vivero Illapel | I9: Región de Coquimbo | J9: Choapa | K9: Illapel | M9: Producción propia CONAF
A10: 9 | B10: Acacia dealbata | C10: Aromo común | D10: Exótico | E10: Arbóreo | G10: 9 | H10: Vivero Archipiélago Juan Fernández | I10: Región de Valparaíso | J10: Valparaíso | K10: Juan Fernández | M10: Compras a terceros | O10: Sectores
A11: 10 | B11: Acacia horrida / Vachellia horrida | C11: Acacia espinosa | D11: Exótico | E11: Arbóreo | G11: 10 | H11: Vivero Reserva Nacional Lago Peñuelas | I11: Región de Valparaíso | J11: Valparaíso | K11: Valparaíso | M11: Donación de terceros | O11: S 1
A12: 11 | B12: Acacia karroo | C12: Aromo de Sudáfrica | D12: Exótico | E12: Arbóreo | G12: 11 | H12: Vivero La Ligua | I12: Región de Valparaíso | J12: Petorca | K12: La Ligua | M12: Traslado Interno CONAF con Aportes Presupuestarios | O12: S 2
A13: 12 | B13: Acacia koa | C13: Koa | D13: Exótico | E13: Arbóreo | G13: 12 | H13: Vivero Llay Llay | I13: Región de Valparaíso | J13: San Felipe de Aconcagua | K13: Llay Llay | M13: Traslado interno de otras unidades CONAF | O13: S 3
A14: 13 | B14: Acacia longifolia | C14: Acacia trinervis | D14: Exótico | E14: Arbóreo | G14: 13 | H14: Vivero Chomedahue | I14: Región del Libertador Gral. Bernardo O'Higgins | J14: Colchagua | K14: Santa Cruz | M14: Movimientos internos en el Vivero | O14: S 4
A15: 14 | B15: Acacia macracantha | C15: Acacia macacranta | D15: Exótico | E15: Arbóreo | G15: 14 | H15: Centro de Acopio Pantanillo | I15: Región del Maule | J15: Talca | K15: Constitución | O15: S 5
A16: 15 | B16: Acacia melanoxylon | C16: Aromo australiano | D16: Exótico | E16: Arbóreo | G16: 15 | H16: Centro Experimental Cauquenes | I16: Región del Maule | J16: Cauquenes | K16: Cauquenes | M16: UNIDADES ADMINISTRATIVAS | O16: S 6
A17: 16 | B17: Acacia nilotica / Acacia arabica | C17: Acacia arabiga / Goma arábica | D17: Exótico | E17: Arbóreo | G17: 16 | H17: Base Brigada La Granja | I17: Región del Biobío | J17: Arauco | K17: Cañete | M17: Región de Arica y Parinacota | O17: S 7
A18: 17 | B18: Acacia rubida | C18: Zarzo rojo | D18: Exótico | E18: Arbustivo | G18: 17 | H18: Centro de Acondicionamiento Duqueco | I18: Región del Biobío | J18: BioBio | K18: Los Ángeles | M18: Región de Tarapacá | O18: S 8
A19: 18 | B19: Acacia salicina | C19: Zarzo | D19: Exótico | E19: Arbóreo | G19: 18 | H19: Liceo Nueva Zelandia | I19: Región del Biobío | J19: Concepción | K19: Santa Juana | M19: Región de Antofagasta | O19: S 9
A20: 19 | B20: Acacia saligna / Acacia cyanophylla | C20: Acacia azul | D20: Exótico | E20: Arbóreo | G20: 19 | H20: Vivero Curacautín | I20: Región de La Araucanía | J20: Malleco | K20: Curacautín | M20: Región de Atacama | O20: S 10
A21: 20 | B21: Acacia semperflorens | C21: Acacia semperflorens | D21: Exótico | E21: Arbóreo | G21: 20 | H21: Vivero Imperial | I21: Región de La Araucanía | J21: Cautín | K21: Nueva Imperial | M21: Región de Coquimbo
A22: 21 | B22: Acacia senegal | C22: Acacia Senegal | D22: Exótico | E22: Arbóreo | G22: 21 | H22: Vivero Huillilemu | I22: Región de Los Ríos | J22: Valdivia | K22: Mariquina | M22: Región de Valparaíso
A23: 22 | B23: Acacia sp. | C23: Acacia | D23: Exótico | E23: Arbóreo | G23: 22 | H23: Vivero San Juan | I23: Región de Los Ríos | J23: Valdivia | K23: Panguipulli | M23: Región del Libertador Gral. Bernardo O’Higgins | O23: Causas de Mortalidad de plantas
A24: 23 | B24: Acacia tomentosa / Vachellia tomentosa | C24: Acacia | D24: Exótico | E24: Arbóreo | G24: 23 | H24: Vivero Chabranco | I24: Región de Los Ríos | J24: Valdivia | K24: Futrono | M24: Región del Maule | O24: Ataques de gusanos cortadores
A25: 24 | B25: Acacia victoriae | C25: Gundabluie | D25: Exótico | E25: Arbustivo | G25: 24 | H25: Vivero Liceo Técnico de Ignao | I25: Región de Los Ríos | J25: Ranco | K25: Lago Ranco | M25: Región del Biobío | O25: Larvas de insectos
A26: 25 | B26: Acacia visco | C26: Vilca | D26: Exótico | E26: Arbóreo | G26: 25 | H26: Vivero Mashue | I26: Región de Los Ríos | J26: Ranco | K26: La Unión | M26: Región de La Araucanía | O26: Pájaros
A27: 26 | B27: Acalypha wilkesiana | C27: Acalifa | D27: Exótico | E27: Arbustivo | G27: 26 | H27: Vivero Llancacura | I27: Región de Los Ríos | J27: Ranco | K27: La Unión | M27: Región de Los Ríos | O27: Roedores
A28: 27 | B28: Acer japonicum | C28: Arce japónico | D28: Exótico | E28: Arbóreo | G28: 27 | H28: Vivero Butalcura | I28: Región de Los Lagos | J28: Chiloé | K28: Dalcahue | M28: Región de Los Lagos | O28: Hongos del follaje (botritis)
A29: 28 | B29: Acer negundo | C29: Arce negundo | D29: Exótico | E29: Arbóreo | G29: 28 | H29: Vivero Augusto Falcón | I29: Región de Aysén del Gral. Carlos Ibáñez del Campo | J29: General Carrera | K29: Chile chico | M29: Región de Aysén del Gral. Carlos Ibáñez del Campo | O29: Hongos del suelo (dumping off)
A30: 29 | B30: Acer palmatum | C30: Arce palmeado japonés | D30: Exótico | E30: Arbóreo | G30: 29 | H30: Centro de Acondicionamiento Cochrane | I30: Región de Aysén del Gral. Carlos Ibáñez del Campo | J30: Capitán Prat | K30: Cochrane | M30: Región de Magallanes y de La Antártica Chilena | O30: Nemátodos
A31: 30 | B31: Acer platanoides | C31: Arce de Noruega / Arce real | D31: Exótico | E31: Arbóreo | G31: 30 | H31: Vivero El Mallín | I31: Región de Aysén del Gral. Carlos Ibáñez del Campo | J31: Aysén | K31: Aysén | M31: Región Metropolitana de Santiago | O31: Bacterias
A32: 31 | B32: Acer pseudoplatanus | C32: Falso plátano | D32: Exótico | E32: Arbóreo | G32: 31 | H32: Vivero Las Lengas | I32: Región de Aysén del Gral. Carlos Ibáñez del Campo | J32: Coyhaique | K32: Coyhaique | M32: Centro de Semillas, Genética y Entomología | O32: Falta de riego
A33: 32 | B33: Acer sp. | C33: Acer | D33: Exótico | E33: Arbóreo | G33: 32 | H33: Vivero Dorotea | I33: Región de Magallanes y de La Antártica Chilena | J33: Última Esperanza | K33: Natales | M33: Isla de Pascua | O33: Exceso de riego
A34: 33 | B34: Achillea millefolium | C34: Milenrama | D34: Exótico | E34: Herbáceo | G34: 33 | H34: Vivero Río de Los Ciervos | I34: Región de Magallanes y de La Antártica Chilena | J34: Magallanes | K34: Punta Arenas | O34: Calidad de la semilla
A35: 34 | B35: Adesmia balsamica | C35: Jarilla | D35: Nativo Conservación | E35: Arbustivo | G35: 34 | H35: Vivero Buin | I35: Región Metropolitana | J35: Maipo | K35: Buin | M35: TIPO DE REPRODUCCIÓN | O35: Heladas
A36: 35 | B36: Adesmia confusa | C36: Palhuén / Espinillo / Varilla brava | D36: Nativo | E36: Arbustivo | G36: 35 | H36: Vivero Reserva Nacional Río Clarillo | I36: Región Metropolitana | J36: Cordillera | K36: Pirque | M36: Semilla | O36: Granizo
A37: 36 | B37: Adesmia echinus | C37: Adesmia | D37: Nativo | E37: Arbustivo | G37: 36 | H37: Vivero San Pedro | I37: Región Metropolitana | J37: Melipilla | K37: San Pedro | M37: Vegetativa (esquejes y/o estacas) | O37: Inundaciones
A38: 37 | B38: Adesmia emarginata | C38: Paramela / Paramilla | D38: Nativo | E38: Arbustivo | G38: 37 | H38: Vivero Centro de Semillas, Genética y Entomología | I38: Región de Ñuble - Centro de Semillas, Genética y Entomología | J38: Diguillin | K38: Chillán | M38: Regeneración natural (Repique bosque) | O38: Otras (agregar comentarios)
A39: 38 | B39: Adesmia hystrix | C39: Adesmia | D39: Nativo | E39: Arbustivo | G39: 38 | H39: Vivero Mataveri Otai | I39: Isla de Pascua | J39: Isla de Pascua | K39: Isla de Pascua
A40: 39 | B40: Adesmia loudonia | C40: Adesmia | D40: Nativo | E40: Arbustivo | M40: RANGO DE ALTURA
A41: 40 | B41: Adesmia phylloidea | C41: Adesmia | D41: Nativo | E41: Arbustivo | M41: 1A = 1 - 20 cm
A42: 41 | B42: Adesmia radicifolia | C42: Adesmia | D42: Nativo | E42: Arbustivo | M42: 1B = 21 - 40 cm
A43: 42 | B43: Adesmia resinosa | C43: Paramela de Tiltil | D43: Nativo Conservación | E43: Arbustivo | M43: 2 = 41 - 80 cm
A44: 43 | B44: Adesmia volckmannii / Adesmia campestris | C44: Mata espinosa | D44: Nativo | E44: Arbustivo | M44: 3 = 81 - 150 cm
A45: 44 | B45: Adiantum chilense | C45: Palito negro / Helecho de palo negro | D45: Nativo | E45: Helecho | M45: 4 = Mayor a 151 cm
A46: 45 | B46: Aesculus hippocastanum | C46: Castaño de las indias | D46: Exótico | E46: Arbóreo
A47: 46 | B47: Aesculus sativa | C47: Castaño | D47: Exótico | E47: Arbóreo | M47: PERIODO DE VIVERIZACIÓN
A48: 47 | B48: Aesculus x carnea | C48: Castaño de indias rojo | D48: Exótico | E48: Arbóreo | M48: 0 año
A49: 48 | B49: Aextoxicon punctatum | C49: Olivillo / Tique | D49: Nativo Conservación | E49: Arbóreo | M49: 1 año
A50: 49 | B50: Agapanthus sp. | C50: Agapanto | D50: Exótico | E50: Herbáceo | M50: 2 años
A51: 50 | B51: Agathea coelestis | C51: Margarita azul / Felicia / Agatea | D51: Exótico | E51: Herbáceo | M51: 3 años
A52: 51 | B52: Agave americana | C52: Pita / Agave amarillo | D52: Exótico | E52: Suculenta | M52: 4 años
A53: 52 | B53: Agavoideae sp. | C53: Ágave | D53: Exótico | E53: Suculenta | M53: 5 años
A54: 53 | B54: Ailanthus altissima | C54: Árbol de cielo / Ailanto | D54: Exótico | E54: Arbóreo | M54: 5 ó más años
A55: 54 | B55: Albizia falcataria | C55: Falcata | D55: Exótico | E55: Arbóreo
A56: 55 | B56: Albizia julibrissin | C56: Acacia de constantinopla / Albizia / Árbol de la seda | D56: Exótico | E56: Arbóreo | M56: DESTINO DE PLANTAS
A57: 56 | B57: Albizia lebbeck | C57: Ébano / Albizia | D57: Exótico | E57: Arbóreo | M57: Áreas Silvestres Protegidas | N57: ASP
A58: 57 | B58: Albizia lophanta | C58: Albizia amarilla | D58: Exótico | E58: Arbóreo | M58: Fomento al Bosque Nativo | N58: BN
A59: 58 | B59: Albizia sp. | C59: Albizia | D59: Exótico | E59: Arbóreo | M59: Compensación R. N. Pampa del Tamarugal | N59: CRNPT
A60: 59 | B60: Alnus acuminata | C60: Aliso andino | D60: Exótico | E60: Arbóreo | M60: Conservación | N60: C
A61: 60 | B61: Alnus glutinosa | C61: Aliso común | D61: Exótico | E61: Arbóreo | M61: Difusión | N61: D
A62: 61 | B62: Alnus sp. | C62: Aliso | D62: Exótico | E62: Arbóreo | M62: Especies con fines melíferos | N62: EFM
A63: 62 | B63: Aloe arborescens | C63: Aloe | D63: Exótico | E63: Suculenta | M63: Forestación Campesina | N63: FC
A64: 63 | B64: Aloea vera | C64: Aloe vera | D64: Exótico | E64: Suculenta | M64: Forestación Participativa | N64: FP
A65: 64 | B65: Aloysia citrodora / Aloysia triphylla | C65: Cedrón / Hierba Luisa | D65: Exótico | E65: Arbustivo | M65: Germoplasma | N65: G
A66: 65 | B66: Althaea rosea | C66: Malva | D66: Exótico | E66: Herbáceo | M66: Plantaciones Forestales | N66: O
A67: 66 | B67: Ambrosia chamissonis | C67: Ambrosia | D67: Nativo | E67: Herbáceo | M67: Plantas Gobierno Regional Aysén | N67: PF
A68: 67 | B68: Ammophila arenaria | C68: Barrón | D68: Exótico | E68: Herbáceo | M68: Programa Castor | N68: PGRA
... A79: 78 | B79: Araucaria sp. | C79: Araucaria | D79: Exótico | E79: Arbóreo | M79: Programa de Reactivación Económica Forestal | N79: PREF
A80: 79 | B80: Arbutus unedo | C80: Madroño | D80: Exótico | E80: Arbustivo | M80: Recuperación de Bosques Quemados
A81: 80 | B81: Archidasyphylluym excelsum | C81: Tayú del Norte | D81: Nativo | E81: Arbóreo | M81: Otro (especificar en observaciones) | N81: V
A82: 81 | B82: Argyranthemum frutescens / Chrysanthemum frutescens | C82: Paquerette | D82: Exótico | E82: Herbáceo
A83: 82 | B83: Argyranthemum sp. | C83: Ventosilla | D83: Exótico | E83: Herbáceo
A84: 83 | B84: Argythamnia berteroana | C84: Ventosilla | D84: Nativo | E84: Arbustivo
A85: 84 | B85: Argythamnia tricuspidata | C85: Ventosilla | D85: Nativo | E85: Arbustivo
A86: 85 | B86: Aristotelia chilensis | C86: Maqui | D86: Nativo | E86: Arbóreo
A87: 86 | B87: Armeria maritima | C87: Clavelina de mar | D87: Exótico | E87: Herbáceo
A88: 87 | B88: Artemisia absinthium | C88: Ajenjo | D88: Exótico | E88: Arbustivo
A89: 88 | B89: Artemisia vulgaris | C89: Artemisa / Hierba de San Juan | D89: Exótico | E89: Herbáceo
A90: 89 | B90: Asteriscium vidalii | C90: Anisillo | D90: Nativo | E90: Herbáceo
A91: 90 | B91: Astragalus paposanus | C91: Arvejilla de Paposo | D91: Nativo | E91: Herbáceo
A92: 91 | B92: Atriplex atacamensis | C92: Cachiyuyo | D92: Nativo | E92: Arbustivo
A93: 92 | B93: Atriplex coquimbana | C93: Atriplex cachiyuyo | D93: Nativo Conservación | E93: Arbustivo
... A891: 890 | B891: Zinnia sp. | C891: Zinnia sp. | D891: Exótico | E891: Herbáceo

Sheet CONSOLIDADO REGIONAL (ingresos)
B1: Control Inventario de Plantas SIGI-GBCC 8, 2022
B2: Viveros, centros de acopio y acondicionamiento CONAF
B4: Consolidado 2022
A5: ANTECEDENTES DEL VIVERO | H5: ANTECEDENTES DE LA ESPECIE | T5: N° DE PLANTAS NUEVAS | U5: N° DE PLANTAS ENTREGADAS Y/O VENDIDAS | X5: Movimientos internos (Cambios Rango de altura o contenedor) | Y5: TRASLADOS INTERNOS A OTRAS UNIDADES CONAF | AB5: BAJA DE PLANTAS DE INVENTARIO | AF5: STOCK | AG5: VALORIZACIÓN
A6: Ítems | B6: Unidad Productiva | C6: Unidad Administrativa | D6: Provincia | E6: Comuna | F6: Encargado | G6: Teléfono de Contacto | H6: Nombre Científico | I6: Nombre Común | J6: Origen | K6: Fuente de Abastecimiento | L6: Destino de la Planta | M6: Tipo de Reproducción | N6: Tipo de Contenedor | O6: Fecha Ingreso a Inventario (Día/Mes/Año) | P6: Periodo de Viverización | Q6: Rango de Altura | R6: Sectores del Vivero | S6: N° Total Plantas Inventario Diciembre 2019 | T6: N° Ingreso plantas a inventario | U6: N° Entregas por Difusión | V6: N° Entregas a Programas | W6: N° Plantas Venta | X6: N° Plantas (M.I.) | Y6: N° Plantas Trasladadas | Z6: Unidades Recepción de Traslado | AA6: N° de Documento, Factura o Guía de Despacho | AB6: N° Plantas de Baja | AC6: Causas | AD6: N° Resolución | AE6: Fecha de Resolución | AF6: N° TOTAL DE PLANTAS INVENTARIO MARZO 2020 | AG6: Valor Neto ($) por planta | AH6: Valor Total ($) por lote | AI6: Ingresos e Inventario Inicial | AJ6: Egresos | AK6: Stock | AL6: MES REPORTE
A7: ='Reporte Marzo 2026'!A361 -> Ingresos | B7: ='Reporte Marzo 2026'!B361 -> 0 | C7: ='Reporte Marzo 2026'!C361 | D7: ='Reporte Marzo 2026'!D361 | E7: ='Reporte Marzo 2026'!E361 | F7: ='Reporte Marzo 2026'!F361 -> 0 | G7: ='Reporte Marzo 2026'!G361 -> 0 | H7: ='Reporte Marzo 2026'!H361 -> 0 | ... AL7: ='Reporte Marzo 2026'!AL361 -> Marzo
A8: ='Reporte Marzo 2026'!A362 -> Ingresos | B8: ='Reporte Marzo 2026'!B362 -> 0 | C8: ='Reporte Marzo 2026'!C362 | D8: ='Reporte Marzo 2026'!D362 | E8: ='Reporte Marzo 2026'!E362 | F8: ='Reporte Marzo 2026'!F362 -> 0 | G8: ='Reporte Marzo 2026'!G362 -> 0 | H8: ='Reporte Marzo 2026'!H362 -> 0 | ... AL8: ='Reporte Marzo 2026'!AL362 -> Marzo
A9: ='Reporte Marzo 2026'!A363 -> Ingresos | B9: ='Reporte Marzo 2026'!B363 -> 0 | C9: ='Reporte Marzo 2026'!C363 | D9: ='Reporte Marzo 2026'!D363 | E9: ='Reporte Marzo 2026'!E363 | F9: ='Reporte Marzo 2026'!F363 -> 0 | G9: ='Reporte Marzo 2026'!G363 -> 0 | H9: ='Reporte Marzo 2026'!H363 -> 0 | ... AL9: ='Reporte Marzo 2026'!AL363 -> Marzo
A10: ='Reporte Marzo 2026'!A364 -> Ingresos | B10: ='Reporte Marzo 2026'!B364 -> 0 | C10: ='Reporte Marzo 2026'!C364 | D10: ='Reporte Marzo 2026'!D364 | E10: ='Reporte Marzo 2026'!E364 | F10: ='Reporte Marzo 2026'!F364 -> 0 | G10: ='Reporte Marzo 2026'!G364 -> 0 | H10: ='Reporte Marzo 2026'!H364 -> 0 | ... AL10: ='Reporte Marzo 2026'!AL364 -> Marzo
A11: ='Reporte Marzo 2026'!A365 -> Ingresos | B11: ='Reporte Marzo 2026'!B365 -> 0 | C11: ='Reporte Marzo 2026'!C365 | D11: ='Reporte Marzo 2026'!D365 | E11: ='Reporte Marzo 2026'!E365 | F11: ='Reporte Marzo 2026'!F365 -> 0 | G11: ='Reporte Marzo 2026'!G365 -> 0 | H11: ='Reporte Marzo 2026'!H365 -> 0 | ... AL11: ='Reporte Marzo 2026'!AL365 -> Marzo
A12: ='Reporte Marzo 2026'!A366 -> Ingresos | B12: ='Reporte Marzo 2026'!B366 -> 0 | C12: ='Reporte Marzo 2026'!C366 | D12: ='Reporte Marzo 2026'!D366 | E12: ='Reporte Marzo 2026'!E366 | F12: ='Reporte Marzo 2026'!F366 -> 0 | G12: ='Reporte Marzo 2026'!G366 -> 0 | H12: ='Reporte Marzo 2026'!H366 -> 0 | ... AL12: ='Reporte Marzo 2026'!AL366 -> Marzo
A13: ='Reporte Marzo 2026'!A367 -> Ingresos | B13: ='Reporte Marzo 2026'!B367 -> 0 | C13: ='Reporte Marzo 2026'!C367 | D13: ='Reporte Marzo 2026'!D367 | E13: ='Reporte Marzo 2026'!E367 | F13: ='Reporte Marzo 2026'!F367 -> 0 | G13: ='Reporte Marzo 2026'!G367 -> 0 | H13: ='Reporte Marzo 2026'!H367 -> 0 | ... AL13: ='Reporte Marzo 2026'!AL367 -> Marzo
A14: ='Reporte Marzo 2026'!A368 -> Ingresos | B14: ='Reporte Marzo 2026'!B368 -> 0 | C14: ='Reporte Marzo 2026'!C368 | D14: ='Reporte Marzo 2026'!D368 | E14: ='Reporte Marzo 2026'!E368 | F14: ='Reporte Marzo 2026'!F368 -> 0 | G14: ='Reporte Marzo 2026'!G368 -> 0 | H14: ='Reporte Marzo 2026'!H368 -> 0 | ... AL14: ='Reporte Marzo 2026'!AL368 -> Marzo
A15: ='Reporte Marzo 2026'!A369 -> Ingresos | B15: ='Reporte Marzo 2026'!B369 -> 0 | C15: ='Reporte Marzo 2026'!C369 | D15: ='Reporte Marzo 2026'!D369 | E15: ='Reporte Marzo 2026'!E369 | F15: ='Reporte Marzo 2026'!F369 -> 0 | G15: ='Reporte Marzo 2026'!G369 -> 0 | H15: ='Reporte Marzo 2026'!H369 -> 0 | ... AL15: ='Reporte Marzo 2026'!AL369 -> Marzo
A16: ='Reporte Marzo 2026'!A370 -> Ingresos | B16: ='Reporte Marzo 2026'!B370 -> 0 | C16: ='Reporte Marzo 2026'!C370 | D16: ='Reporte Marzo 2026'!D370 | E16: ='Reporte Marzo 2026'!E370 | F16: ='Reporte Marzo 2026'!F370 -> 0 | G16: ='Reporte Marzo 2026'!G370 -> 0 | H16: ='Reporte Marzo 2026'!H370 -> 0 | ... AL16: ='Reporte Marzo 2026'!AL370 -> Marzo
A17: ='Reporte Marzo 2026'!A371 -> Ingresos | B17: ='Reporte Marzo 2026'!B371 -> 0 | C17: ='Reporte Marzo 2026'!C371 | D17: ='Reporte Marzo 2026'!D371 | E17: ='Reporte Marzo 2026'!E371 | F17: ='Reporte Marzo 2026'!F371 -> 0 | G17: ='Reporte Marzo 2026'!G371 -> 0 | H17: ='Reporte Marzo 2026'!H371 -> 0 | ... AL17: ='Reporte Marzo 2026'!AL371 -> Marzo
A18: ='Reporte Marzo 2026'!A372 -> Ingresos | B18: ='Reporte Marzo 2026'!B372 -> 0 | C18: ='Reporte Marzo 2026'!C372 | D18: ='Reporte Marzo 2026'!D372 | E18: ='Reporte Marzo 2026'!E372 | F18: ='Reporte Marzo 2026'!F372 -> 0 | G18: ='Reporte Marzo 2026'!G372 -> 0 | H18: ='Reporte Marzo 2026'!H372 -> 0 | ... AL18: ='Reporte Marzo 2026'!AL372 -> Marzo
... A47: ='Reporte Marzo 2026'!A401 -> Ingresos | B47: ='Reporte Marzo 2026'!B401 -> 0 | C47: ='Reporte Marzo 2026'!C401 | D47: ='Reporte Marzo 2026'!D401 | E47: ='Reporte Marzo 2026'!E401 | F47: ='Reporte Marzo 2026'!F401 -> 0 | G47: ='Reporte Marzo 2026'!G401 -> 0 | H47: ='Reporte Marzo 2026'!H401 -> 0 | ... AL47: ='Reporte Marzo 2026'!AL401 -> Marzo
A48: ='Reporte Marzo 2026'!A433 -> Ingresos | B48: ='Reporte Marzo 2026'!B433 -> 0 | C48: ='Reporte Marzo 2026'!C433 | D48: ='Reporte Marzo 2026'!D433 | E48: ='Reporte Marzo 2026'!E433 | F48: ='Reporte Marzo 2026'!F433 -> 0 | G48: ='Reporte Marzo 2026'!G433 -> 0 | H48: ='Reporte Marzo 2026'!H433 -> 0 | ... AL48: ='Reporte Marzo 2026'!AL433 -> Marzo
A49: ='Reporte Marzo 2026'!A434 -> Ingresos | B49: ='Reporte Marzo 2026'!B434 -> 0 | C49: ='Reporte Marzo 2026'!C434 | D49: ='Reporte Marzo 2026'!D434 | E49: ='Reporte Marzo 2026'!E434 | F49: ='Reporte Marzo 2026'!F434 -> 0 | G49: ='Reporte Marzo 2026'!G434 -> 0 | H49: ='Reporte Marzo 2026'!H434 -> 0 | ... AL49: ='Reporte Marzo 2026'!AL434 -> Marzo
A50: ='Reporte Marzo 2026'!A435 -> Ingresos | B50: ='Reporte Marzo 2026'!B435 -> 0 | C50: ='Reporte Marzo 2026'!C435 | D50: ='Reporte Marzo 2026'!D435 | E50: ='Reporte Marzo 2026'!E435 | F50: ='Reporte Marzo 2026'!F435 -> 0 | G50: ='Reporte Marzo 2026'!G435 -> 0 | H50: ='Reporte Marzo 2026'!H435 -> 0 | ... AL50: ='Reporte Marzo 2026'!AL435 -> Marzo
A51: ='Reporte Marzo 2026'!A436 -> Ingresos | B51: ='Reporte Marzo 2026'!B436 -> 0 | C51: ='Reporte Marzo 2026'!C436 | D51: ='Reporte Marzo 2026'!D436 | E51: ='Reporte Marzo 2026'!E436 | F51: ='Reporte Marzo 2026'!F436 -> 0 | G51: ='Reporte Marzo 2026'!G436 -> 0 | H51: ='Reporte Marzo 2026'!H436 -> 0 | ... AL51: ='Reporte Marzo 2026'!AL436 -> Marzo
A52: ='Reporte Marzo 2026'!A437 -> Ingresos | B52: ='Reporte Marzo 2026'!B437 -> 0 | C52: ='Reporte Marzo 2026'!C437 | D52: ='Reporte Marzo 2026'!D437 | E52: ='Reporte Marzo 2026'!E437 | F52: ='Reporte Marzo 2026'!F437 -> 0 | G52: ='Reporte Marzo 2026'!G437 -> 0 | H52: ='Reporte Marzo 2026'!H437 -> 0 | ... AL52: ='Reporte Marzo 2026'!AL437 -> Marzo
A53: ='Reporte Marzo 2026'!A438 -> Ingresos | B53: ='Reporte Marzo 2026'!B438 -> 0 | C53: ='Reporte Marzo 2026'!C438 | D53: ='Reporte Marzo 2026'!D438 | E53: ='Reporte Marzo 2026'!E438 | F53: ='Reporte Marzo 2026'!F438 -> 0 | G53: ='Reporte Marzo 2026'!G438 -> 0 | H53: ='Reporte Marzo 2026'!H438 -> 0 | ... AL53: ='Reporte Marzo 2026'!AL438 -> Marzo
A54: ='Reporte Marzo 2026'!A439 -> Ingresos | B54: ='Reporte Marzo 2026'!B439 -> 0 | C54: ='Reporte Marzo 2026'!C439 | D54: ='Reporte Marzo 2026'!D439 | E54: ='Reporte Marzo 2026'!E439 | F54: ='Reporte Marzo 2026'!F439 -> 0 | G54: ='Reporte Marzo 2026'!G439 -> 0 | H54: ='Reporte Marzo 2026'!H439 -> 0 | ... AL54: ='Reporte Marzo 2026'!AL439 -> Marzo
A55: ='Reporte Marzo 2026'!A440 -> Ingresos | B55: ='Reporte Marzo 2026'!B440 -> 0 | C55: ='Reporte Marzo 2026'!C440 | D55: ='Reporte Marzo 2026'!D440 | E55: ='Reporte Marzo 2026'!E440 | F55: ='Reporte Marzo 2026'!F440 -> 0 | G55: ='Reporte Marzo 2026'!G440 -> 0 | H55: ='Reporte Marzo 2026'!H440 -> 0 | ... AL55: ='Reporte Marzo 2026'!AL440 -> Marzo
A56: ='Reporte Marzo 2026'!A441 -> Ingresos | B56: ='Reporte Marzo 2026'!B441 -> 0 | C56: ='Reporte Marzo 2026'!C441 | D56: ='Reporte Marzo 2026'!D441 | E56: ='Reporte Marzo 2026'!E441 | F56: ='Reporte Marzo 2026'!F441 -> 0 | G56: ='Reporte Marzo 2026'!G441 -> 0 | H56: ='Reporte Marzo 2026'!H441 -> 0 | ... AL56: ='Reporte Marzo 2026'!AL441 -> Marzo
A57: ='Reporte Marzo 2026'!A442 -> Ingresos | B57: ='Reporte Marzo 2026'!B442 -> 0 | C57: ='Reporte Marzo 2026'!C442 | D57: ='Reporte Marzo 2026'!D442 | E57: ='Reporte Marzo 2026'!E442 | F57: ='Reporte Marzo 2026'!F442 -> 0 | G57: ='Reporte Marzo 2026'!G442 -> 0 | H57: ='Reporte Marzo 2026'!H442 -> 0 | ... AL57: ='Reporte Marzo 2026'!AL442 -> Marzo
A58: ='Reporte Marzo 2026'!A452 -> Ingresos | B58: ='Reporte Marzo 2026'!B452 -> 0 | C58: ='Reporte Marzo 2026'!C452 | D58: ='Reporte Marzo 2026'!D452 | E58: ='Reporte Marzo 2026'!E452 | F58: ='Reporte Marzo 2026'!F452 -> 0 | G58: ='Reporte Marzo 2026'!G452 -> 0 | H58: ='Reporte Marzo 2026'!H452 -> 0 | ... AL58: ='Reporte Marzo 2026'!AL452 -> Marzo
A59: ='Reporte Marzo 2026'!A453 -> Ingresos | B59: ='Reporte Marzo 2026'!B453 -> 0 | C59: ='Reporte Marzo 2026'!C453 | D59: ='Reporte Marzo 2026'!D453 | E59: ='Reporte Marzo 2026'!E453 | F59: ='Reporte Marzo 2026'!F453 -> 0 | G59: ='Reporte Marzo 2026'!G453 -> 0 | H59: ='Reporte Marzo 2026'!H453 -> 0 | ... AL59: ='Reporte Marzo 2026'!AL453 -> Marzo
A60: ='Reporte Marzo 2026'!A454 -> Ingresos | B60: ='Reporte Marzo 2026'!B454 -> 0 | C60: ='Reporte Marzo 2026'!C454 | D60: ='Reporte Marzo 2026'!D454 | E60: ='Reporte Marzo 2026'!E454 | F60: ='Reporte Marzo 2026'!F454 -> 0 | G60: ='Reporte Marzo 2026'!G454 -> 0 | H60: ='Reporte Marzo 2026'!H454 -> 0 | ... AL60: ='Reporte Marzo 2026'!AL454 -> Marzo
A61: ='Reporte Marzo 2026'!A455 -> Ingresos | B61: ='Reporte Marzo 2026'!B455 -> 0 | C61: ='Reporte Marzo 2026'!C455 | D61: ='Reporte Marzo 2026'!D455 | E61: ='Reporte Marzo 2026'!E455 | F61: ='Reporte Marzo 2026'!F455 -> 0 | G61: ='Reporte Marzo 2026'!G455 -> 0 | H61: ='Reporte Marzo 2026'!H455 -> 0 | ... AL61: ='Reporte Marzo 2026'!AL455 -> Marzo
A62: ='Reporte Marzo 2026'!A456 -> Ingresos | B62: ='Reporte Marzo 2026'!B456 -> 0 | C62: ='Reporte Marzo 2026'!C456 | D62: ='Reporte Marzo 2026'!D456 | E62: ='Reporte Marzo 2026'!E456 | F62: ='Reporte Marzo 2026'!F456 -> 0 | G62: ='Reporte Marzo 2026'!G456 -> 0 | H62: ='Reporte Marzo 2026'!H456 -> 0 | ... AL62: ='Reporte Marzo 2026'!AL456 -> Marzo
A63: ='Reporte Marzo 2026'!A457 -> Ingresos | B63: ='Reporte Marzo 2026'!B457 -> 0 | C63: ='Reporte Marzo 2026'!C457 | D63: ='Reporte Marzo 2026'!D457 | E63: ='Reporte Marzo 2026'!E457 | F63: ='Reporte Marzo 2026'!F457 -> 0 | G63: ='Reporte Marzo 2026'!G457 -> 0 | H63: ='Reporte Marzo 2026'!H457 -> 0 | ... AL63: ='Reporte Marzo 2026'!AL457 -> Marzo
A64: ='Reporte Marzo 2026'!A458 -> Ingresos | B64: ='Reporte Marzo 2026'!B458 -> 0 | C64: ='Reporte Marzo 2026'!C458 | D64: ='Reporte Marzo 2026'!D458 | E64: ='Reporte Marzo 2026'!E458 | F64: ='Reporte Marzo 2026'!F458 -> 0 | G64: ='Reporte Marzo 2026'!G458 -> 0 | H64: ='Reporte Marzo 2026'!H458 -> 0 | ... AL64: ='Reporte Marzo 2026'!AL458 -> Marzo
A65: ='Reporte Marzo 2026'!A459 -> Ingresos | B65: ='Reporte Marzo 2026'!B459 -> 0 | C65: ='Reporte Marzo 2026'!C459 | D65: ='Reporte Marzo 2026'!D459 | E65: ='Reporte Marzo 2026'!E459 | F65: ='Reporte Marzo 2026'!F459 -> 0 | G65: ='Reporte Marzo 2026'!G459 -> 0 | H65: ='Reporte Marzo 2026'!H459 -> 0 | ... AL65: ='Reporte Marzo 2026'!AL459 -> Marzo
A66: ='Reporte Marzo 2026'!A460 -> Ingresos | B66: ='Reporte Marzo 2026'!B460 -> 0 | C66: ='Reporte Marzo 2026'!C460 | D66: ='Reporte Marzo 2026'!D460 | E66: ='Reporte Marzo 2026'!E460 | F66: ='Reporte Marzo 2026'!F460 -> 0 | G66: ='Reporte Marzo 2026'!G460 -> 0 | H66: ='Reporte Marzo 2026'!H460 -> 0 | ... AL66: ='Reporte Marzo 2026'!AL460 -> Marzo
A67: ='Reporte Marzo 2026'!A461 -> Ingresos | B67: ='Reporte Marzo 2026'!B461 -> 0 | C67: ='Reporte Marzo 2026'!C461 | D67: ='Reporte Marzo 2026'!D461 | E67: ='Reporte Marzo 2026'!E461 | F67: ='Reporte Marzo 2026'!F461 -> 0 | G67: ='Reporte Marzo 2026'!G461 -> 0 | H67: ='Reporte Marzo 2026'!H461 -> 0 | ... AL67: ='Reporte Marzo 2026'!AL461 -> Marzo
A68: ='Reporte Marzo 2026'!A462 -> Ingresos | B68: ='Reporte Marzo 2026'!B462 -> 0 | C68: ='Reporte Marzo 2026'!C462 | D68: ='Reporte Marzo 2026'!D462 | E68: ='Reporte Marzo 2026'!E462 | F68: ='Reporte Marzo 2026'!F462 -> 0 | G68: ='Reporte Marzo 2026'!G462 -> 0 | H68: ='Reporte Marzo 2026'!H462 -> 0 | ... AL68: ='Reporte Marzo 2026'!AL462 -> Marzo
A69: ='Reporte Marzo 2026'!A463 -> Ingresos | B69: ='Reporte Marzo 2026'!B463 -> 0 | C69: ='Reporte Marzo 2026'!C463 | D69: ='Reporte Marzo 2026'!D463 | E69: ='Reporte Marzo 2026'!E463 | F69: ='Reporte Marzo 2026'!F463 -> 0 | G69: ='Reporte Marzo 2026'!G463 -> 0 | H69: ='Reporte Marzo 2026'!H463 -> 0 | ... AL69: ='Reporte Marzo 2026'!AL463 -> Marzo
... A74: ='Reporte Marzo 2026'!A468 -> Ingresos | B74: ='Reporte Marzo 2026'!B468 -> 0 | C74: ='Reporte Marzo 2026'!C468 | D74: ='Reporte Marzo 2026'!D468 | E74: ='Reporte Marzo 2026'!E468 | F74: ='Reporte Marzo 2026'!F468 -> 0 | G74: ='Reporte Marzo 2026'!G468 -> 0 | H74: ='Reporte Marzo 2026'!H468 -> 0 | ... AL74: ='Reporte Marzo 2026'!AL468 -> Marzo
A75: ='Reporte Marzo 2026'!A490 -> Ingresos | B75: ='Reporte Marzo 2026'!B490 -> 0 | C75: ='Reporte Marzo 2026'!C490 | D75: ='Reporte Marzo 2026'!D490 | E75: ='Reporte Marzo 2026'!E490 | F75: ='Reporte Marzo 2026'!F490 -> 0 | G75: ='Reporte Marzo 2026'!G490 -> 0 | H75: ='Reporte Marzo 2026'!H490 -> 0 | ... AL75: ='Reporte Marzo 2026'!AL490 -> Marzo
A76: ='Reporte Marzo 2026'!#REF! -> #REF! | B76: ='Reporte Marzo 2026'!#REF! -> #REF! | C76: ='Reporte Marzo 2026'!#REF! -> #REF! | D76: ='Reporte Marzo 2026'!#REF! -> #REF! | E76: ='Reporte Marzo 2026'!#REF! -> #REF! | F76: ='Reporte Marzo 2026'!#REF! -> #REF! | G76: ='Reporte Marzo 2026'!#REF! -> #REF! | H76: ='Reporte Marzo 2026'!#REF! -> #REF! | ... AL76: ='Reporte Marzo 2026'!#REF! -> #REF!
A77: ='Reporte Marzo 2026'!#REF! -> #REF! | B77: ='Reporte Marzo 2026'!#REF! -> #REF! | C77: ='Reporte Marzo 2026'!#REF! -> #REF! | D77: ='Reporte Marzo 2026'!#REF! -> #REF! | E77: ='Reporte Marzo 2026'!#REF! -> #REF! | F77: ='Reporte Marzo 2026'!#REF! -> #REF! | G77: ='Reporte Marzo 2026'!#REF! -> #REF! | H77: ='Reporte Marzo 2026'!#REF! -> #REF! | ... AL77: ='Reporte Marzo 2026'!#REF! -> #REF!
A78: ='Reporte Marzo 2026'!A491 -> Total Marzo | B78: ='Reporte Marzo 2026'!B491 -> 0 | C78: ='Reporte Marzo 2026'!C491 -> 0 | D78: ='Reporte Marzo 2026'!D491 -> 0 | E78: ='Reporte Marzo 2026'!E491 -> 0 | F78: ='Reporte Marzo 2026'!F491 -> 0 | G78: ='Reporte Marzo 2026'!G491 -> 0 | H78: ='Reporte Marzo 2026'!H491 -> 0 | ... AL78: ='Reporte Marzo 2026'!AL491 -> 0
A79: ='Reporte Marzo 2026'!A492 -> 0 | B79: ='Reporte Marzo 2026'!B492 -> 0 | C79: ='Reporte Marzo 2026'!C492 -> 0 | D79: ='Reporte Marzo 2026'!D492 -> 0 | E79: ='Reporte Marzo 2026'!E492 -> 0 | F79: ='Reporte Marzo 2026'!F492 -> 0 | G79: ='Reporte Marzo 2026'!G492 -> 0 | H79: ='Reporte Marzo 2026'!H492 -> 0 | ... AL79: ='Reporte Marzo 2026'!AL492 -> 0
A80: ='Reporte Marzo 2026'!A493 -> 0 | B80: ='Reporte Marzo 2026'!B493 -> 0 | C80: ='Reporte Marzo 2026'!C493 -> 0 | D80: ='Reporte Marzo 2026'!D493 -> 0 | E80: ='Reporte Marzo 2026'!E493 -> 0 | F80: ='Reporte Marzo 2026'!F493 -> 0 | G80: ='Reporte Marzo 2026'!G493 -> 0 | H80: ='Reporte Marzo 2026'!H493 -> 0 | ... AL80: ='Reporte Marzo 2026'!AL493 -> 0
A81: ='Reporte Marzo 2026'!A494 -> 0 | B81: ='Reporte Marzo 2026'!B494 -> 0 | C81: ='Reporte Marzo 2026'!C494 -> 0 | D81: ='Reporte Marzo 2026'!D494 -> 0 | E81: ='Reporte Marzo 2026'!E494 -> 0 | F81: ='Reporte Marzo 2026'!F494 -> 0 | G81: ='Reporte Marzo 2026'!G494 -> 0 | H81: ='Reporte Marzo 2026'!H494 -> 0 | ... AL81: ='Reporte Marzo 2026'!AL494 -> 0
A82: ='Reporte Marzo 2026'!A495 -> 0 | B82: ='Reporte Marzo 2026'!B495 -> 0 | C82: ='Reporte Marzo 2026'!C495 -> 0 | D82: ='Reporte Marzo 2026'!D495 -> 0 | E82: ='Reporte Marzo 2026'!E495 -> 0 | F82: ='Reporte Marzo 2026'!F495 -> 0 | G82: ='Reporte Marzo 2026'!G495 -> 0 | H82: ='Reporte Marzo 2026'!H495 -> 0 | ... AL82: ='Reporte Marzo 2026'!AL495 -> 0
A83: ='Reporte Marzo 2026'!A496 -> 0 | B83: ='Reporte Marzo 2026'!B496 -> 0 | C83: ='Reporte Marzo 2026'!C496 -> 0 | D83: ='Reporte Marzo 2026'!D496 -> 0 | E83: ='Reporte Marzo 2026'!E496 -> 0 | F83: ='Reporte Marzo 2026'!F496 -> 0 | G83: ='Reporte Marzo 2026'!G496 -> 0 | H83: ='Reporte Marzo 2026'!H496 -> 0 | ... AL83: ='Reporte Marzo 2026'!AL496 -> 0
A84: ='Reporte Marzo 2026'!A497 -> 0 | B84: ='Reporte Marzo 2026'!B497 -> 0 | C84: ='Reporte Marzo 2026'!C497 -> 0 | D84: ='Reporte Marzo 2026'!D497 -> 0 | E84: ='Reporte Marzo 2026'!E497 -> 0 | F84: ='Reporte Marzo 2026'!F497 -> 0 | G84: ='Reporte Marzo 2026'!G497 -> 0 | H84: ='Reporte Marzo 2026'!H497 -> 0 | ... AL84: ='Reporte Marzo 2026'!AL497 -> 0
A85: ='Reporte Marzo 2026'!A498 -> 0 | B85: ='Reporte Marzo 2026'!B498 -> 0 | C85: ='Reporte Marzo 2026'!C498 -> 0 | D85: ='Reporte Marzo 2026'!D498 -> 0 | E85: ='Reporte Marzo 2026'!E498 -> 0 | F85: ='Reporte Marzo 2026'!F498 -> 0 | G85: ='Reporte Marzo 2026'!G498 -> 0 | H85: ='Reporte Marzo 2026'!H498 -> 0 | ... AL85: ='Reporte Marzo 2026'!AL498 -> 0
A86: ='Reporte Marzo 2026'!A499 -> 0 | B86: ='Reporte Marzo 2026'!B499 -> 0 | C86: ='Reporte Marzo 2026'!C499 -> 0 | D86: ='Reporte Marzo 2026'!D499 -> 0 | E86: ='Reporte Marzo 2026'!E499 -> 0 | F86: ='Reporte Marzo 2026'!F499 -> 0 | G86: ='Reporte Marzo 2026'!G499 -> 0 | H86: ='Reporte Marzo 2026'!H499 -> 0 | ... AL86: ='Reporte Marzo 2026'!AL499 -> 0
A87: ='Reporte Marzo 2026'!A500 -> 0 | B87: ='Reporte Marzo 2026'!B500 -> 0 | C87: ='Reporte Marzo 2026'!C500 -> 0 | D87: ='Reporte Marzo 2026'!D500 -> 0 | E87: ='Reporte Marzo 2026'!E500 -> 0 | F87: ='Reporte Marzo 2026'!F500 -> 0 | G87: ='Reporte Marzo 2026'!G500 -> 0 | H87: ='Reporte Marzo 2026'!H500 -> 0 | ... AL87: ='Reporte Marzo 2026'!AL500 -> 0
A88: ='Reporte Marzo 2026'!A501 -> 0 | B88: ='Reporte Marzo 2026'!B501 -> 0 | C88: ='Reporte Marzo 2026'!C501 -> 0 | D88: ='Reporte Marzo 2026'!D501 -> 0 | E88: ='Reporte Marzo 2026'!E501 -> 0 | F88: ='Reporte Marzo 2026'!F501 -> 0 | G88: ='Reporte Marzo 2026'!G501 -> 0 | H88: ='Reporte Marzo 2026'!H501 -> 0 | ... AL88: ='Reporte Marzo 2026'!AL501 -> 0
A89: ='Reporte Marzo 2026'!A502 -> 0 | B89: ='Reporte Marzo 2026'!B502 -> 0 | C89: ='Reporte Marzo 2026'!C502 -> 0 | D89: ='Reporte Marzo 2026'!D502 -> 0 | E89: ='Reporte Marzo 2026'!E502 -> 0 | F89: ='Reporte Marzo 2026'!F502 -> 0 | G89: ='Reporte Marzo 2026'!G502 -> 0 | H89: ='Reporte Marzo 2026'!H502 -> 0 | ... AL89: ='Reporte Marzo 2026'!AL502 -> 0
... A248: ='Reporte Marzo 2026'!A661 -> 0 | B248: ='Reporte Marzo 2026'!B661 -> 0 | C248: ='Reporte Marzo 2026'!C661 -> 0 | D248: ='Reporte Marzo 2026'!D661 -> 0 | E248: ='Reporte Marzo 2026'!E661 -> 0 | F248: ='Reporte Marzo 2026'!F661 -> 0 | G248: ='Reporte Marzo 2026'!G661 -> 0 | H248: ='Reporte Marzo 2026'!H661 -> 0 | ... AL248: ='Reporte Marzo 2026'!AL661 -> 0
A249: ='Reporte Junio 2026'!A361 -> Ingresos | B249: ='Reporte Junio 2026'!B361 -> 0 | C249: ='Reporte Junio 2026'!C361 | D249: ='Reporte Junio 2026'!D361 | E249: ='Reporte Junio 2026'!E361 | F249: ='Reporte Junio 2026'!F361 -> 0 | G249: ='Reporte Junio 2026'!G361 -> 0 | H249: ='Reporte Junio 2026'!H361 -> 0 | ... AL249: ='Reporte Junio 2026'!AL361 -> Junio
A250: ='Reporte Junio 2026'!A362 -> Ingresos | B250: ='Reporte Junio 2026'!B362 -> 0 | C250: ='Reporte Junio 2026'!C362 | D250: ='Reporte Junio 2026'!D362 | E250: ='Reporte Junio 2026'!E362 | F250: ='Reporte Junio 2026'!F362 -> 0 | G250: ='Reporte Junio 2026'!G362 -> 0 | H250: ='Reporte Junio 2026'!H362 -> 0 | ... AL250: ='Reporte Junio 2026'!AL362 -> Junio
A251: ='Reporte Junio 2026'!A363 -> Ingresos | B251: ='Reporte Junio 2026'!B363 -> 0 | C251: ='Reporte Junio 2026'!C363 | D251: ='Reporte Junio 2026'!D363 | E251: ='Reporte Junio 2026'!E363 | F251: ='Reporte Junio 2026'!F363 -> 0 | G251: ='Reporte Junio 2026'!G363 -> 0 | H251: ='Reporte Junio 2026'!H363 -> 0 | ... AL251: ='Reporte Junio 2026'!AL363 -> Junio
A252: ='Reporte Junio 2026'!A364 -> Ingresos | B252: ='Reporte Junio 2026'!B364 -> 0 | C252: ='Reporte Junio 2026'!C364 | D252: ='Reporte Junio 2026'!D364 | E252: ='Reporte Junio 2026'!E364 | F252: ='Reporte Junio 2026'!F364 -> 0 | G252: ='Reporte Junio 2026'!G364 -> 0 | H252: ='Reporte Junio 2026'!H364 -> 0 | ... AL252: ='Reporte Junio 2026'!AL364 -> Junio
A253: ='Reporte Junio 2026'!A365 -> Ingresos | B253: ='Reporte Junio 2026'!B365 -> 0 | C253: ='Reporte Junio 2026'!C365 | D253: ='Reporte Junio 2026'!D365 | E253: ='Reporte Junio 2026'!E365 | F253: ='Reporte Junio 2026'!F365 -> 0 | G253: ='Reporte Junio 2026'!G365 -> 0 | H253: ='Reporte Junio 2026'!H365 -> 0 | ... AL253: ='Reporte Junio 2026'!AL365 -> Junio
A254: ='Reporte Junio 2026'!A366 -> Ingresos | B254: ='Reporte Junio 2026'!B366 -> 0 | C254: ='Reporte Junio 2026'!C366 | D254: ='Reporte Junio 2026'!D366 | E254: ='Reporte Junio 2026'!E366 | F254: ='Reporte Junio 2026'!F366 -> 0 | G254: ='Reporte Junio 2026'!G366 -> 0 | H254: ='Reporte Junio 2026'!H366 -> 0 | ... AL254: ='Reporte Junio 2026'!AL366 -> Junio
A255: ='Reporte Junio 2026'!A367 -> Ingresos | B255: ='Reporte Junio 2026'!B367 -> 0 | C255: ='Reporte Junio 2026'!C367 | D255: ='Reporte Junio 2026'!D367 | E255: ='Reporte Junio 2026'!E367 | F255: ='Reporte Junio 2026'!F367 -> 0 | G255: ='Reporte Junio 2026'!G367 -> 0 | H255: ='Reporte Junio 2026'!H367 -> 0 | ... AL255: ='Reporte Junio 2026'!AL367 -> Junio
A256: ='Reporte Junio 2026'!A368 -> Ingresos | B256: ='Reporte Junio 2026'!B368 -> 0 | C256: ='Reporte Junio 2026'!C368 | D256: ='Reporte Junio 2026'!D368 | E256: ='Reporte Junio 2026'!E368 | F256: ='Reporte Junio 2026'!F368 -> 0 | G256: ='Reporte Junio 2026'!G368 -> 0 | H256: ='Reporte Junio 2026'!H368 -> 0 | ... AL256: ='Reporte Junio 2026'!AL368 -> Junio
A257: ='Reporte Junio 2026'!A369 -> Ingresos | B257: ='Reporte Junio 2026'!B369 -> 0 | C257: ='Reporte Junio 2026'!C369 | D257: ='Reporte Junio 2026'!D369 | E257: ='Reporte Junio 2026'!E369 | F257: ='Reporte Junio 2026'!F369 -> 0 | G257: ='Reporte Junio 2026'!G369 -> 0 | H257: ='Reporte Junio 2026'!H369 -> 0 | ... AL257: ='Reporte Junio 2026'!AL369 -> Junio
A258: ='Reporte Junio 2026'!A370 -> Ingresos | B258: ='Reporte Junio 2026'!B370 -> 0 | C258: ='Reporte Junio 2026'!C370 | D258: ='Reporte Junio 2026'!D370 | E258: ='Reporte Junio 2026'!E370 | F258: ='Reporte Junio 2026'!F370 -> 0 | G258: ='Reporte Junio 2026'!G370 -> 0 | H258: ='Reporte Junio 2026'!H370 -> 0 | ... AL258: ='Reporte Junio 2026'!AL370 -> Junio
A259: ='Reporte Junio 2026'!A371 -> Ingresos | B259: ='Reporte Junio 2026'!B371 -> 0 | C259: ='Reporte Junio 2026'!C371 | D259: ='Reporte Junio 2026'!D371 | E259: ='Reporte Junio 2026'!E371 | F259: ='Reporte Junio 2026'!F371 -> 0 | G259: ='Reporte Junio 2026'!G371 -> 0 | H259: ='Reporte Junio 2026'!H371 -> 0 | ... AL259: ='Reporte Junio 2026'!AL371 -> Junio
A260: ='Reporte Junio 2026'!A372 -> Ingresos | B260: ='Reporte Junio 2026'!B372 -> 0 | C260: ='Reporte Junio 2026'!C372 | D260: ='Reporte Junio 2026'!D372 | E260: ='Reporte Junio 2026'!E372 | F260: ='Reporte Junio 2026'!F372 -> 0 | G260: ='Reporte Junio 2026'!G372 -> 0 | H260: ='Reporte Junio 2026'!H372 -> 0 | ... AL260: ='Reporte Junio 2026'!AL372 -> Junio
... A293: ='Reporte Junio 2026'!A405 -> Ingresos | B293: ='Reporte Junio 2026'!B405 -> 0 | C293: ='Reporte Junio 2026'!C405 | D293: ='Reporte Junio 2026'!D405 | E293: ='Reporte Junio 2026'!E405 | F293: ='Reporte Junio 2026'!F405 -> 0 | G293: ='Reporte Junio 2026'!G405 -> 0 | H293: ='Reporte Junio 2026'!H405 -> 0 | ... AL293: ='Reporte Junio 2026'!AL405 -> Junio
A294: ='Reporte Junio 2026'!A447 -> Ingresos | B294: ='Reporte Junio 2026'!B447 -> 0 | C294: ='Reporte Junio 2026'!C447 | D294: ='Reporte Junio 2026'!D447 | E294: ='Reporte Junio 2026'!E447 | F294: ='Reporte Junio 2026'!F447 -> 0 | G294: ='Reporte Junio 2026'!G447 -> 0 | H294: ='Reporte Junio 2026'!H447 -> 0 | ... AL294: ='Reporte Junio 2026'!AL447 -> Junio
A295: ='Reporte Junio 2026'!A448 -> Ingresos | B295: ='Reporte Junio 2026'!B448 -> 0 | C295: ='Reporte Junio 2026'!C448 | D295: ='Reporte Junio 2026'!D448 | E295: ='Reporte Junio 2026'!E448 | F295: ='Reporte Junio 2026'!F448 -> 0 | G295: ='Reporte Junio 2026'!G448 -> 0 | H295: ='Reporte Junio 2026'!H448 -> 0 | ... AL295: ='Reporte Junio 2026'!AL448 -> Junio
A296: ='Reporte Junio 2026'!A449 -> Ingresos | B296: ='Reporte Junio 2026'!B449 -> 0 | C296: ='Reporte Junio 2026'!C449 | D296: ='Reporte Junio 2026'!D449 | E296: ='Reporte Junio 2026'!E449 | F296: ='Reporte Junio 2026'!F449 -> 0 | G296: ='Reporte Junio 2026'!G449 -> 0 | H296: ='Reporte Junio 2026'!H449 -> 0 | ... AL296: ='Reporte Junio 2026'!AL449 -> Junio
A297: ='Reporte Junio 2026'!A450 -> Ingresos | B297: ='Reporte Junio 2026'!B450 -> 0 | C297: ='Reporte Junio 2026'!C450 | D297: ='Reporte Junio 2026'!D450 | E297: ='Reporte Junio 2026'!E450 | F297: ='Reporte Junio 2026'!F450 -> 0 | G297: ='Reporte Junio 2026'!G450 -> 0 | H297: ='Reporte Junio 2026'!H450 -> 0 | ... AL297: ='Reporte Junio 2026'!AL450 -> Junio
A298: ='Reporte Junio 2026'!A451 -> Ingresos | B298: ='Reporte Junio 2026'!B451 -> 0 | C298: ='Reporte Junio 2026'!C451 | D298: ='Reporte Junio 2026'!D451 | E298: ='Reporte Junio 2026'!E451 | F298: ='Reporte Junio 2026'!F451 -> 0 | G298: ='Reporte Junio 2026'!G451 -> 0 | H298: ='Reporte Junio 2026'!H451 -> 0 | ... AL298: ='Reporte Junio 2026'!AL451 -> Junio
A299: ='Reporte Junio 2026'!A452 -> Ingresos | B299: ='Reporte Junio 2026'!B452 -> 0 | C299: ='Reporte Junio 2026'!C452 | D299: ='Reporte Junio 2026'!D452 | E299: ='Reporte Junio 2026'!E452 | F299: ='Reporte Junio 2026'!F452 -> 0 | G299: ='Reporte Junio 2026'!G452 -> 0 | H299: ='Reporte Junio 2026'!H452 -> 0 | ... AL299: ='Reporte Junio 2026'!AL452 -> Junio
A300: ='Reporte Junio 2026'!A453 -> Ingresos | B300: ='Reporte Junio 2026'!B453 -> 0 | C300: ='Reporte Junio 2026'!C453 | D300: ='Reporte Junio 2026'!D453 | E300: ='Reporte Junio 2026'!E453 | F300: ='Reporte Junio 2026'!F453 -> 0 | G300: ='Reporte Junio 2026'!G453 -> 0 | H300: ='Reporte Junio 2026'!H453 -> 0 | ... AL300: ='Reporte Junio 2026'!AL453 -> Junio
A301: ='Reporte Junio 2026'!A454 -> Ingresos | B301: ='Reporte Junio 2026'!B454 -> 0 | C301: ='Reporte Junio 2026'!C454 | D301: ='Reporte Junio 2026'!D454 | E301: ='Reporte Junio 2026'!E454 | F301: ='Reporte Junio 2026'!F454 -> 0 | G301: ='Reporte Junio 2026'!G454 -> 0 | H301: ='Reporte Junio 2026'!H454 -> 0 | ... AL301: ='Reporte Junio 2026'!AL454 -> Junio
A302: ='Reporte Junio 2026'!A455 -> Ingresos | B302: ='Reporte Junio 2026'!B455 -> 0 | C302: ='Reporte Junio 2026'!C455 | D302: ='Reporte Junio 2026'!D455 | E302: ='Reporte Junio 2026'!E455 | F302: ='Reporte Junio 2026'!F455 -> 0 | G302: ='Reporte Junio 2026'!G455 -> 0 | H302: ='Reporte Junio 2026'!H455 -> 0 | ... AL302: ='Reporte Junio 2026'!AL455 -> Junio
A303: ='Reporte Junio 2026'!A456 -> Ingresos | B303: ='Reporte Junio 2026'!B456 -> 0 | C303: ='Reporte Junio 2026'!C456 | D303: ='Reporte Junio 2026'!D456 | E303: ='Reporte Junio 2026'!E456 | F303: ='Reporte Junio 2026'!F456 -> 0 | G303: ='Reporte Junio 2026'!G456 -> 0 | H303: ='Reporte Junio 2026'!H456 -> 0 | ... AL303: ='Reporte Junio 2026'!AL456 -> Junio
A304: ='Reporte Junio 2026'!A457 -> Ingresos | B304: ='Reporte Junio 2026'!B457 -> 0 | C304: ='Reporte Junio 2026'!C457 | D304: ='Reporte Junio 2026'!D457 | E304: ='Reporte Junio 2026'!E457 | F304: ='Reporte Junio 2026'!F457 -> 0 | G304: ='Reporte Junio 2026'!G457 -> 0 | H304: ='Reporte Junio 2026'!H457 -> 0 | ... AL304: ='Reporte Junio 2026'!AL457 -> Junio
A305: ='Reporte Junio 2026'!A458 -> Ingresos | B305: ='Reporte Junio 2026'!B458 -> 0 | C305: ='Reporte Junio 2026'!C458 | D305: ='Reporte Junio 2026'!D458 | E305: ='Reporte Junio 2026'!E458 | F305: ='Reporte Junio 2026'!F458 -> 0 | G305: ='Reporte Junio 2026'!G458 -> 0 | H305: ='Reporte Junio 2026'!H458 -> 0 | ... AL305: ='Reporte Junio 2026'!AL458 -> Junio
... A311: ='Reporte Junio 2026'!A464 -> Ingresos | B311: ='Reporte Junio 2026'!B464 -> 0 | C311: ='Reporte Junio 2026'!C464 | D311: ='Reporte Junio 2026'!D464 | E311: ='Reporte Junio 2026'!E464 | F311: ='Reporte Junio 2026'!F464 -> 0 | G311: ='Reporte Junio 2026'!G464 -> 0 | H311: ='Reporte Junio 2026'!H464 -> 0 | ... AL311: ='Reporte Junio 2026'!AL464 -> Junio
A312: ='Reporte Junio 2026'!A482 -> Ingresos | B312: ='Reporte Junio 2026'!B482 -> 0 | C312: ='Reporte Junio 2026'!C482 | D312: ='Reporte Junio 2026'!D482 | E312: ='Reporte Junio 2026'!E482 | F312: ='Reporte Junio 2026'!F482 -> 0 | G312: ='Reporte Junio 2026'!G482 -> 0 | H312: ='Reporte Junio 2026'!H482 -> 0 | ... AL312: ='Reporte Junio 2026'!AL482 -> Junio
A313: ='Reporte Junio 2026'!A483 -> Ingresos | B313: ='Reporte Junio 2026'!B483 -> 0 | C313: ='Reporte Junio 2026'!C483 | D313: ='Reporte Junio 2026'!D483 | E313: ='Reporte Junio 2026'!E483 | F313: ='Reporte Junio 2026'!F483 -> 0 | G313: ='Reporte Junio 2026'!G483 -> 0 | H313: ='Reporte Junio 2026'!H483 -> 0 | ... AL313: ='Reporte Junio 2026'!AL483 -> Junio
A314: ='Reporte Junio 2026'!A484 -> Ingresos | B314: ='Reporte Junio 2026'!B484 -> 0 | C314: ='Reporte Junio 2026'!C484 | D314: ='Reporte Junio 2026'!D484 | E314: ='Reporte Junio 2026'!E484 | F314: ='Reporte Junio 2026'!F484 -> 0 | G314: ='Reporte Junio 2026'!G484 -> 0 | H314: ='Reporte Junio 2026'!H484 -> 0 | ... AL314: ='Reporte Junio 2026'!AL484 -> Junio
A315: ='Reporte Junio 2026'!A485 -> Ingresos | B315: ='Reporte Junio 2026'!B485 -> 0 | C315: ='Reporte Junio 2026'!C485 | D315: ='Reporte Junio 2026'!D485 | E315: ='Reporte Junio 2026'!E485 | F315: ='Reporte Junio 2026'!F485 -> 0 | G315: ='Reporte Junio 2026'!G485 -> 0 | H315: ='Reporte Junio 2026'!H485 -> 0 | ... AL315: ='Reporte Junio 2026'!AL485 -> Junio
A316: ='Reporte Junio 2026'!A486 -> Ingresos | B316: ='Reporte Junio 2026'!B486 -> 0 | C316: ='Reporte Junio 2026'!C486 | D316: ='Reporte Junio 2026'!D486 | E316: ='Reporte Junio 2026'!E486 | F316: ='Reporte Junio 2026'!F486 -> 0 | G316: ='Reporte Junio 2026'!G486 -> 0 | H316: ='Reporte Junio 2026'!H486 -> 0 | ... AL316: ='Reporte Junio 2026'!AL486 -> Junio
A317: ='Reporte Junio 2026'!A487 -> Ingresos | B317: ='Reporte Junio 2026'!B487 -> 0 | C317: ='Reporte Junio 2026'!C487 | D317: ='Reporte Junio 2026'!D487 | E317: ='Reporte Junio 2026'!E487 | F317: ='Reporte Junio 2026'!F487 -> 0 | G317: ='Reporte Junio 2026'!G487 -> 0 | H317: ='Reporte Junio 2026'!H487 -> 0 | ... AL317: ='Reporte Junio 2026'!AL487 -> Junio
A318: ='Reporte Junio 2026'!A489 -> Ingresos | B318: ='Reporte Junio 2026'!B489 -> 0 | C318: ='Reporte Junio 2026'!C489 | D318: ='Reporte Junio 2026'!D489 | E318: ='Reporte Junio 2026'!E489 | F318: ='Reporte Junio 2026'!F489 -> 0 | G318: ='Reporte Junio 2026'!G489 -> 0 | H318: ='Reporte Junio 2026'!H489 -> 0 | ... AL318: ='Reporte Junio 2026'!AL489 -> Junio
A319: ='Reporte Junio 2026'!A490 -> Ingresos | B319: ='Reporte Junio 2026'!B490 -> 0 | C319: ='Reporte Junio 2026'!C490 | D319: ='Reporte Junio 2026'!D490 | E319: ='Reporte Junio 2026'!E490 | F319: ='Reporte Junio 2026'!F490 -> 0 | G319: ='Reporte Junio 2026'!G490 -> 0 | H319: ='Reporte Junio 2026'!H490 -> 0 | ... AL319: ='Reporte Junio 2026'!AL490 -> Junio
A320: ='Reporte Junio 2026'!A491 -> TOTAL JUNIO | B320: ='Reporte Junio 2026'!B491 -> 0 | C320: ='Reporte Junio 2026'!C491 -> 0 | D320: ='Reporte Junio 2026'!D491 -> 0 | E320: ='Reporte Junio 2026'!E491 -> 0 | F320: ='Reporte Junio 2026'!F491 -> 0 | G320: ='Reporte Junio 2026'!G491 -> 0 | H320: ='Reporte Junio 2026'!H491 -> 0 | ... AL320: ='Reporte Junio 2026'!AL491 -> 0
A321: ='Reporte Septiembre 2026'!A361 -> Ingresos | B321: ='Reporte Septiembre 2026'!B361 -> 0 | C321: ='Reporte Septiembre 2026'!C361 | D321: ='Reporte Septiembre 2026'!D361 | E321: ='Reporte Septiembre 2026'!E361 | F321: ='Reporte Septiembre 2026'!F361 -> 0 | G321: ='Reporte Septiembre 2026'!G361 -> 0 | H321: ='Reporte Septiembre 2026'!H361 -> 0 | ... AL321: ='Reporte Septiembre 2026'!AL361 -> Septiembre
A322: ='Reporte Septiembre 2026'!A362 -> Ingresos | B322: ='Reporte Septiembre 2026'!B362 -> 0 | C322: ='Reporte Septiembre 2026'!C362 | D322: ='Reporte Septiembre 2026'!D362 | E322: ='Reporte Septiembre 2026'!E362 | F322: ='Reporte Septiembre 2026'!F362 -> 0 | G322: ='Reporte Septiembre 2026'!G362 -> 0 | H322: ='Reporte Septiembre 2026'!H362 -> 0 | ... AL322: ='Reporte Septiembre 2026'!AL362 -> Septiembre
A323: ='Reporte Septiembre 2026'!A363 -> Ingresos | B323: ='Reporte Septiembre 2026'!B363 -> 0 | C323: ='Reporte Septiembre 2026'!C363 | D323: ='Reporte Septiembre 2026'!D363 | E323: ='Reporte Septiembre 2026'!E363 | F323: ='Reporte Septiembre 2026'!F363 -> 0 | G323: ='Reporte Septiembre 2026'!G363 -> 0 | H323: ='Reporte Septiembre 2026'!H363 -> 0 | ... AL323: ='Reporte Septiembre 2026'!AL363 -> Septiembre
A324: ='Reporte Septiembre 2026'!A364 -> Ingresos | B324: ='Reporte Septiembre 2026'!B364 -> 0 | C324: ='Reporte Septiembre 2026'!C364 | D324: ='Reporte Septiembre 2026'!D364 | E324: ='Reporte Septiembre 2026'!E364 | F324: ='Reporte Septiembre 2026'!F364 -> 0 | G324: ='Reporte Septiembre 2026'!G364 -> 0 | H324: ='Reporte Septiembre 2026'!H364 -> 0 | ... AL324: ='Reporte Septiembre 2026'!AL364 -> Septiembre
A325: ='Reporte Septiembre 2026'!A365 -> Ingresos | B325: ='Reporte Septiembre 2026'!B365 -> 0 | C325: ='Reporte Septiembre 2026'!C365 | D325: ='Reporte Septiembre 2026'!D365 | E325: ='Reporte Septiembre 2026'!E365 | F325: ='Reporte Septiembre 2026'!F365 -> 0 | G325: ='Reporte Septiembre 2026'!G365 -> 0 | H325: ='Reporte Septiembre 2026'!H365 -> 0 | ... AL325: ='Reporte Septiembre 2026'!AL365 -> Septiembre
A326: ='Reporte Septiembre 2026'!A366 -> Ingresos | B326: ='Reporte Septiembre 2026'!B366 -> 0 | C326: ='Reporte Septiembre 2026'!C366 | D326: ='Reporte Septiembre 2026'!D366 | E326: ='Reporte Septiembre 2026'!E366 | F326: ='Reporte Septiembre 2026'!F366 -> 0 | G326: ='Reporte Septiembre 2026'!G366 -> 0 | H326: ='Reporte Septiembre 2026'!H366 -> 0 | ... AL326: ='Reporte Septiembre 2026'!AL366 -> Septiembre
A327: ='Reporte Septiembre 2026'!A367 -> Ingresos | B327: ='Reporte Septiembre 2026'!B367 -> 0 | C327: ='Reporte Septiembre 2026'!C367 | D327: ='Reporte Septiembre 2026'!D367 | E327: ='Reporte Septiembre 2026'!E367 | F327: ='Reporte Septiembre 2026'!F367 -> 0 | G327: ='Reporte Septiembre 2026'!G367 -> 0 | H327: ='Reporte Septiembre 2026'!H367 -> 0 | ... AL327: ='Reporte Septiembre 2026'!AL367 -> Septiembre
A328: ='Reporte Septiembre 2026'!A368 -> Ingresos | B328: ='Reporte Septiembre 2026'!B368 -> 0 | C328: ='Reporte Septiembre 2026'!C368 | D328: ='Reporte Septiembre 2026'!D368 | E328: ='Reporte Septiembre 2026'!E368 | F328: ='Reporte Septiembre 2026'!F368 -> 0 | G328: ='Reporte Septiembre 2026'!G368 -> 0 | H328: ='Reporte Septiembre 2026'!H368 -> 0 | ... AL328: ='Reporte Septiembre 2026'!AL368 -> Septiembre
...

Sheet INFORME INGRESOS
B1: Para actualizar tablas dinamicas, hacer clic en cualquier parte de la tabla para activar el menu "Herramientas de tablas dinámicas", | F1: NOTA N° ..REGISTRO DE INGRESOS PLANTAS A INVENTARIO 2026
B2: ubicado en la parte superior de la hoja (letras roja). En este menu hacer clic en el icono "Actualizar"
B3: Informe Resumen Ingresos de Plantas | F3: Unidad Administrativa | G3: 0
B4: a Inventario Indicador SIGI GBCC 8, 2026 | F4: Unidad Productiva | G4: 0
F5: Ítems | G5: Ingresos
B6: Ítems | C6: Ingresos
B7: Unidad Administrativa | C7: (Todas) | F7: N° Ingresos plantas a Inventario
F8: MES REPORTE | G8: Fecha Ingreso a Inventario (Día/Mes/Año) | H8: Fuente de Abastecimiento | I8: Origen | J8: Tipo de Contenedor | K8: Rango de Altura | L8: Total
B9: N° Ingresos plantas a inventario | F9: Total general
B10: MES REPORTE | C10: Fuente de Abastecimiento | D10: Total
B11: Marzo | C11: 0 | D11: 0
B12: Junio | C12: 0 | D12: 0
B13: Septiembre | C13: 0 | D13: 0
B14: Diciembre | C14: 0 | D14: 0
B15: Total general | D15: 0

Sheet Informe SALIDAS
B1: NOTA N° …… SALIDAS DE PLANTAS DEL INVENTARIO 2026
B3: Ítems | C3: (Todas)
B4: Unidad Administrativa | C4: (Todas)
D6: N° plantas de SALIDAS
B7: Unidad Productiva | C7: MES REPORTE | D7: N° Plantas Entregas por Difusión | E7: N° Plantas Entregas a Programas | F7: N° Plantas Ventas | G7: N° Plantas de Mov. Internos | H7: N° Plantas Traslado Entre Viveros
B8: 0 | C8: 0 | D8: 0 | E8: 0 | F8: 0 | G8: 0 | H8: 0
C9: Marzo | D9: 0 | E9: 0 | F9: 0 | G9: 0 | H9: 0
C10: Junio | D10: 0 | E10: 0 | F10: 0 | G10: 0 | H10: 0
C11: Septiembre | D11: 0 | E11: 0 | F11: 0 | G11: 0 | H11: 0
C12: Diciembre | D12: 0 | E12: 0 | F12: 0 | G12: 0 | H12: 0
B13: Total general | D13: 0 | E13: 0 | F13: 0 | G13: 0 | H13: 0

Sheet Informe BAJAS
B1: NOTA N° …………. REGISTRO BAJAS DE PLANTAS DEL INVENTARIO 2026
B4: Ítems | C4: (Todas)
B5: Unidad Administrativa | C5: (Todas)
B8: Unidad Productiva | C8: Nombre Científico | D8: Origen | E8: Tipo de Contenedor | F8: Rango de Altura | G8: Periodo de Viverización | H8: N° Plantas de Baja | I8: Causas
B9: 0 | C9: 0 | D9: 0 | E9: 0 | F9: 0 | G9: 0 | H9: 0 | I9: 0
E10: 0 | F10: 0 | G10: 0 | H10: 0 | I10: 0
C11: #¡REF! | E11: 0 | F11: 0 | G11: 0 | H11: 0 | I11: 0
B12: #¡REF! | C12: #¡REF! | D12: #¡REF! | E12: #¡REF! | F12: #¡REF! | G12: #¡REF! | H12: #¡REF! | I12: #¡REF!
B13: Total general

Sheet Informe STOCK
B4: INFORME STOCK TRIMESTRAL (N° DE PLANTAS)
B6: Unidad Administrativa | C6: 0
B7: Ítems | C7: (Todas)
B9: N° Plantas Stock Trimestral
B10: MES REPORTE | C10: Fuente de Abastecimiento | D10: Total
B11: Marzo | C11: 0 | D11: 0
B12: Total Marzo | D12: 0
B13: Junio | C13: 0 | D13: 0
B14: Total Junio | D14: 0
B15: Septiembre | C15: 0 | D15: 0
B16: Total Septiembre | D16: 0
B17: Diciembre | C17: 0 | D17: 0
B18: Total Diciembre | D18: 0

Sheet CONSOLIDADO REGIONAL
B1: Control Inventario de Plantas SIGI-GEDEFF 8, 2022
B2: Viveros, centros de acopio y acondicionamiento CONAF
B4: Consolidado 2022
A5: ANTECEDENTES DEL VIVERO | H5: ANTECEDENTES DE LA ESPECIE | T5: N° DE PLANTAS NUEVAS | U5: N° DE PLANTAS ENTREGADAS Y/O VENDIDAS | X5: Movimientos internos (Cambios Rango de altura o contenedor) | Y5: TRASLADOS INTERNOS A OTRAS UNIDADES CONAF | AB5: BAJA DE PLANTAS DE INVENTARIO | AF5: STOCK | AG5: VALORIZACIÓN
A6: Ítems | B6: Unidad Productiva | C6: Unidad Administrativa | D6: Provincia | E6: Comuna | F6: Encargado | G6: Teléfono de Contacto | H6: Nombre Científico | I6: Nombre Común | J6: Origen | K6: Fuente de Abastecimiento | L6: Destino de la Planta | M6: Tipo de Reproducción | N6: Tipo de Contenedor | O6: Fecha Ingreso a Inventario (Día/Mes/Año) | P6: Periodo de Viverización | Q6: Rango de Altura | R6: Sectores del Vivero | S6: N° Total Plantas Inventario Diciembre 2019 | T6: N° Ingreso plantas a inventario | U6: N° Entregas por Difusión | V6: N° Entregas a Programas | W6: N° Plantas Venta | X6: N° Plantas (M.I.) | Y6: N° Plantas Trasladadas | Z6: Unidades Recepción de Traslado | AA6: N° de Documento, Factura o Guía de Despacho | AB6: N° Plantas de Baja | AC6: Causas | AD6: N° Resolución | AE6: Fecha de Resolución | AF6: N° TOTAL DE PLANTAS INVENTARIO MARZO 2020 | AG6: Valor Neto ($) por planta | AH6: Valor Total ($) por lote | AI6: Ingresos e Inventario Inicial | AJ6: Egresos | AK6: Stock | AL6: MES REPORTE
A7: ='Reporte Marzo 2026'!A7 -> Inventario | B7: ='Reporte Marzo 2026'!B7 -> 0 | C7: ='Reporte Marzo 2026'!C7 | D7: ='Reporte Marzo 2026'!D7 | E7: ='Reporte Marzo 2026'!E7 | F7: ='Reporte Marzo 2026'!F7 -> 0 | G7: ='Reporte Marzo 2026'!G7 -> 0 | H7: ='Reporte Marzo 2026'!H7 -> 0 | ... AL7: ='Reporte Marzo 2026'!AL7 -> Marzo
A8: ='Reporte Marzo 2026'!A8 -> Inventario | B8: ='Reporte Marzo 2026'!B8 -> 0 | C8: ='Reporte Marzo 2026'!C8 | D8: ='Reporte Marzo 2026'!D8 | E8: ='Reporte Marzo 2026'!E8 | F8: ='Reporte Marzo 2026'!F8 -> 0 | G8: ='Reporte Marzo 2026'!G8 -> 0 | H8: ='Reporte Marzo 2026'!H8 -> 0 | ... AL8: ='Reporte Marzo 2026'!AL8 -> Marzo
A9: ='Reporte Marzo 2026'!A9 -> Inventario | B9: ='Reporte Marzo 2026'!B9 -> 0 | C9: ='Reporte Marzo 2026'!C9 | D9: ='Reporte Marzo 2026'!D9 | E9: ='Reporte Marzo 2026'!E9 | F9: ='Reporte Marzo 2026'!F9 -> 0 | G9: ='Reporte Marzo 2026'!G9 -> 0 | H9: ='Reporte Marzo 2026'!H9 -> 0 | ... AL9: ='Reporte Marzo 2026'!AL9 -> Marzo
A10: ='Reporte Marzo 2026'!A10 -> Inventario | B10: ='Reporte Marzo 2026'!B10 -> 0 | C10: ='Reporte Marzo 2026'!C10 | D10: ='Reporte Marzo 2026'!D10 | E10: ='Reporte Marzo 2026'!E10 | F10: ='Reporte Marzo 2026'!F10 -> 0 | G10: ='Reporte Marzo 2026'!G10 -> 0 | H10: ='Reporte Marzo 2026'!H10 -> 0 | ... AL10: ='Reporte Marzo 2026'!AL10 -> Marzo
A11: ='Reporte Marzo 2026'!A11 -> Inventario | B11: ='Reporte Marzo 2026'!B11 -> 0 | C11: ='Reporte Marzo 2026'!C11 | D11: ='Reporte Marzo 2026'!D11 | E11: ='Reporte Marzo 2026'!E11 | F11: ='Reporte Marzo 2026'!F11 -> 0 | G11: ='Reporte Marzo 2026'!G11 -> 0 | H11: ='Reporte Marzo 2026'!H11 -> 0 | ... AL11: ='Reporte Marzo 2026'!AL11 -> Marzo
A12: ='Reporte Marzo 2026'!A12 -> Inventario | B12: ='Reporte Marzo 2026'!B12 -> 0 | C12: ='Reporte Marzo 2026'!C12 | D12: ='Reporte Marzo 2026'!D12 | E12: ='Reporte Marzo 2026'!E12 | F12: ='Reporte Marzo 2026'!F12 -> 0 | G12: ='Reporte Marzo 2026'!G12 -> 0 | H12: ='Reporte Marzo 2026'!H12 -> 0 | ... AL12: ='Reporte Marzo 2026'!AL12 -> Marzo
A13: ='Reporte Marzo 2026'!A13 -> Inventario | B13: ='Reporte Marzo 2026'!B13 -> 0 | C13: ='Reporte Marzo 2026'!C13 | D13: ='Reporte Marzo 2026'!D13 | E13: ='Reporte Marzo 2026'!E13 | F13: ='Reporte Marzo 2026'!F13 -> 0 | G13: ='Reporte Marzo 2026'!G13 -> 0 | H13: ='Reporte Marzo 2026'!H13 -> 0 | ... AL13: ='Reporte Marzo 2026'!AL13 -> Marzo
A14: ='Reporte Marzo 2026'!A14 -> Inventario | B14: ='Reporte Marzo 2026'!B14 -> 0 | C14: ='Reporte Marzo 2026'!C14 | D14: ='Reporte Marzo 2026'!D14 | E14: ='Reporte Marzo 2026'!E14 | F14: ='Reporte Marzo 2026'!F14 -> 0 | G14: ='Reporte Marzo 2026'!G14 -> 0 | H14: ='Reporte Marzo 2026'!H14 -> 0 | ... AL14: ='Reporte Marzo 2026'!AL14 -> Marzo
A15: ='Reporte Marzo 2026'!A15 -> Inventario | B15: ='Reporte Marzo 2026'!B15 -> 0 | C15: ='Reporte Marzo 2026'!C15 | D15: ='Reporte Marzo 2026'!D15 | E15: ='Reporte Marzo 2026'!E15 | F15: ='Reporte Marzo 2026'!F15 -> 0 | G15: ='Reporte Marzo 2026'!G15 -> 0 | H15: ='Reporte Marzo 2026'!H15 -> 0 | ... AL15: ='Reporte Marzo 2026'!AL15 -> Marzo
A16: ='Reporte Marzo 2026'!A16 -> Inventario | B16: ='Reporte Marzo 2026'!B16 -> 0 | C16: ='Reporte Marzo 2026'!C16 | D16: ='Reporte Marzo 2026'!D16 | E16: ='Reporte Marzo 2026'!E16 | F16: ='Reporte Marzo 2026'!F16 -> 0 | G16: ='Reporte Marzo 2026'!G16 -> 0 | H16: ='Reporte Marzo 2026'!H16 -> 0 | ... AL16: ='Reporte Marzo 2026'!AL16 -> Marzo
A17: ='Reporte Marzo 2026'!A17 -> Inventario | B17: ='Reporte Marzo 2026'!B17 -> 0 | C17: ='Reporte Marzo 2026'!C17 | D17: ='Reporte Marzo 2026'!D17 | E17: ='Reporte Marzo 2026'!E17 | F17: ='Reporte Marzo 2026'!F17 -> 0 | G17: ='Reporte Marzo 2026'!G17 -> 0 | H17: ='Reporte Marzo 2026'!H17 -> 0 | ... AL17: ='Reporte Marzo 2026'!AL17 -> Marzo
A18: ='Reporte Marzo 2026'!A18 -> Inventario | B18: ='Reporte Marzo 2026'!B18 -> 0 | C18: ='Reporte Marzo 2026'!C18 | D18: ='Reporte Marzo 2026'!D18 | E18: ='Reporte Marzo 2026'!E18 | F18: ='Reporte Marzo 2026'!F18 -> 0 | G18: ='Reporte Marzo 2026'!G18 -> 0 | H18: ='Reporte Marzo 2026'!H18 -> 0 | ... AL18: ='Reporte Marzo 2026'!AL18 -> Marzo
... A251: ='Reporte Marzo 2026'!A251 -> Inventario | B251: ='Reporte Marzo 2026'!B251 -> 0 | C251: ='Reporte Marzo 2026'!C251 | D251: ='Reporte Marzo 2026'!D251 | E251: ='Reporte Marzo 2026'!E251 | F251: ='Reporte Marzo 2026'!F251 -> 0 | G251: ='Reporte Marzo 2026'!G251 -> 0 | H251: ='Reporte Marzo 2026'!H251 -> 0 | ... AL251: ='Reporte Marzo 2026'!AL251 -> Marzo
A252: ='Reporte Marzo 2026'!A335 -> Inventario | B252: ='Reporte Marzo 2026'!B335 -> 0 | C252: ='Reporte Marzo 2026'!C335 | D252: ='Reporte Marzo 2026'!D335 | E252: ='Reporte Marzo 2026'!E335 | F252: ='Reporte Marzo 2026'!F335 -> 0 | G252: ='Reporte Marzo 2026'!G335 -> 0 | H252: ='Reporte Marzo 2026'!H335 -> 0 | ... AL252: ='Reporte Marzo 2026'!AL335 -> Marzo
A253: ='Reporte Marzo 2026'!A336 -> Inventario | B253: ='Reporte Marzo 2026'!B336 -> 0 | C253: ='Reporte Marzo 2026'!C336 | D253: ='Reporte Marzo 2026'!D336 | E253: ='Reporte Marzo 2026'!E336 | F253: ='Reporte Marzo 2026'!F336 -> 0 | G253: ='Reporte Marzo 2026'!G336 -> 0 | H253: ='Reporte Marzo 2026'!H336 -> 0 | ... AL253: ='Reporte Marzo 2026'!AL336 -> Marzo
A254: ='Reporte Marzo 2026'!A337 -> Inventario | B254: ='Reporte Marzo 2026'!B337 -> 0 | C254: ='Reporte Marzo 2026'!C337 | D254: ='Reporte Marzo 2026'!D337 | E254: ='Reporte Marzo 2026'!E337 | F254: ='Reporte Marzo 2026'!F337 -> 0 | G254: ='Reporte Marzo 2026'!G337 -> 0 | H254: ='Reporte Marzo 2026'!H337 -> 0 | ... AL254: ='Reporte Marzo 2026'!AL337 -> Marzo
A255: ='Reporte Marzo 2026'!A338 -> Inventario | B255: ='Reporte Marzo 2026'!B338 -> 0 | C255: ='Reporte Marzo 2026'!C338 | D255: ='Reporte Marzo 2026'!D338 | E255: ='Reporte Marzo 2026'!E338 | F255: ='Reporte Marzo 2026'!F338 -> 0 | G255: ='Reporte Marzo 2026'!G338 -> 0 | H255: ='Reporte Marzo 2026'!H338 -> 0 | ... AL255: ='Reporte Marzo 2026'!AL338 -> Marzo
A256: ='Reporte Marzo 2026'!#REF! -> #REF! | B256: ='Reporte Marzo 2026'!#REF! -> #REF! | C256: ='Reporte Marzo 2026'!#REF! -> #REF! | D256: ='Reporte Marzo 2026'!#REF! -> #REF! | E256: ='Reporte Marzo 2026'!#REF! -> #REF! | F256: ='Reporte Marzo 2026'!#REF! -> #REF! | G256: ='Reporte Marzo 2026'!#REF! -> #REF! | H256: ='Reporte Marzo 2026'!#REF! -> #REF! | ... AL256: ='Reporte Marzo 2026'!#REF! -> #REF!
A257: ='Reporte Marzo 2026'!#REF! -> #REF! | B257: ='Reporte Marzo 2026'!#REF! -> #REF! | C257: ='Reporte Marzo 2026'!#REF! -> #REF! | D257: ='Reporte Marzo 2026'!#REF! -> #REF! | E257: ='Reporte Marzo 2026'!#REF! -> #REF! | F257: ='Reporte Marzo 2026'!#REF! -> #REF! | G257: ='Reporte Marzo 2026'!#REF! -> #REF! | H257: ='Reporte Marzo 2026'!#REF! -> #REF! | ... AL257: ='Reporte Marzo 2026'!#REF! -> #REF!
A258: ='Reporte Marzo 2026'!A361 -> Ingresos | B258: ='Reporte Marzo 2026'!B361 -> 0 | C258: ='Reporte Marzo 2026'!C361 | D258: ='Reporte Marzo 2026'!D361 | E258: ='Reporte Marzo 2026'!E361 | F258: ='Reporte Marzo 2026'!F361 -> 0 | G258: ='Reporte Marzo 2026'!G361 -> 0 | H258: ='Reporte Marzo 2026'!H361 -> 0 | ... AL258: ='Reporte Marzo 2026'!AL361 -> Marzo
A259: ='Reporte Marzo 2026'!A362 -> Ingresos | B259: ='Reporte Marzo 2026'!B362 -> 0 | C259: ='Reporte Marzo 2026'!C362 | D259: ='Reporte Marzo 2026'!D362 | E259: ='Reporte Marzo 2026'!E362 | F259: ='Reporte Marzo 2026'!F362 -> 0 | G259: ='Reporte Marzo 2026'!G362 -> 0 | H259: ='Reporte Marzo 2026'!H362 -> 0 | ... AL259: ='Reporte Marzo 2026'!AL362 -> Marzo
A260: ='Reporte Marzo 2026'!A363 -> Ingresos | B260: ='Reporte Marzo 2026'!B363 -> 0 | C260: ='Reporte Marzo 2026'!C363 | D260: ='Reporte Marzo 2026'!D363 | E260: ='Reporte Marzo 2026'!E363 | F260: ='Reporte Marzo 2026'!F363 -> 0 | G260: ='Reporte Marzo 2026'!G363 -> 0 | H260: ='Reporte Marzo 2026'!H363 -> 0 | ... AL260: ='Reporte Marzo 2026'!AL363 -> Marzo
A261: ='Reporte Marzo 2026'!A364 -> Ingresos | B261: ='Reporte Marzo 2026'!B364 -> 0 | C261: ='Reporte Marzo 2026'!C364 | D261: ='Reporte Marzo 2026'!D364 | E261: ='Reporte Marzo 2026'!E364 | F261: ='Reporte Marzo 2026'!F364 -> 0 | G261: ='Reporte Marzo 2026'!G364 -> 0 | H261: ='Reporte Marzo 2026'!H364 -> 0 | ... AL261: ='Reporte Marzo 2026'!AL364 -> Marzo
A262: ='Reporte Marzo 2026'!A365 -> Ingresos | B262: ='Reporte Marzo 2026'!B365 -> 0 | C262: ='Reporte Marzo 2026'!C365 | D262: ='Reporte Marzo 2026'!D365 | E262: ='Reporte Marzo 2026'!E365 | F262: ='Reporte Marzo 2026'!F365 -> 0 | G262: ='Reporte Marzo 2026'!G365 -> 0 | H262: ='Reporte Marzo 2026'!H365 -> 0 | ... AL262: ='Reporte Marzo 2026'!AL365 -> Marzo
A263: ='Reporte Marzo 2026'!A366 -> Ingresos | B263: ='Reporte Marzo 2026'!B366 -> 0 | C263: ='Reporte Marzo 2026'!C366 | D263: ='Reporte Marzo 2026'!D366 | E263: ='Reporte Marzo 2026'!E366 | F263: ='Reporte Marzo 2026'!F366 -> 0 | G263: ='Reporte Marzo 2026'!G366 -> 0 | H263: ='Reporte Marzo 2026'!H366 -> 0 | ... AL263: ='Reporte Marzo 2026'!AL366 -> Marzo
